Workbook

Sheet Overview
A1: Aamir Khan: Filmography Overview | AN1: Overall Relationship Classification
A2: Generated 2026-10-08 from the research files. Research cutoff: 2026-09-12. Released feature-film acting appearances through 12 September 2026, including child roles, cameos, song appearances and a voice role. Excluded: the silent short Paranoia (1983); the documentaries Madness in the Desert (2004) and Big in Bollywood (2011); producer-only credits; television; and Lahore 1947 (released 14 August 2026, Wikipedia page now titled Batwara 1947), where he is credited only as producer. Pre-2000 box-office figures come from Wikipedia citations of trade sources and are graded down accordingly. Collaborators covers directors, producers or banners, composers and key writers with at least two of his films, plus directors of historically significant single collaborations. Awards covers documented Filmfare and National Film Award wins for his non-cameo films, all of Aamir Khan's own Filmfare nominations, his wins at other ceremonies, civilian honours, and major international awards and nominations. | AN2: Frictionless idealized romance
AN3: United couple versus external world
A4: Career summary | AN4: Friendship to love
A5: Metric | B5: Value | C5: Method | D5: Notes | AN5: Rivals to lovers
A6: Actor | B6: Aamir Khan | C6: Research file | AN6: Playful conflict masking attraction
A7: Career period | B7: =IF(COUNT(Films!$D$2:$D$58)=0,"n/a",MIN(Films!$D$2:$D$58)&"–"&MAX(Films!$D$2:$D$58)) | C7: Formula | D7: First to latest theatrical release year in Films | AN7: Genuine incompatibility gradually resolved
A8: Research cutoff date | B8: 46277 | C8: Research file | AN8: Established relationship
A9: Total released acting films | B9: =COUNTA(Films!$A$2:$A$58) | C9: Formula | AN9: Marriage under strain
A10: Lead and co-lead films | B10: =COUNTIF(Films!$T$2:$T$58,"Lead")+COUNTIF(Films!$T$2:$T$58,"Co-lead")+COUNTIF(Films!$T$2:$T$58,"Ensemble lead") | C10: Formula | D10: Role Type: Lead, Co-lead, Ensemble lead | AN10: Relationship damaged by mistrust
A11: Supporting roles | B11: =COUNTIF(Films!$T$2:$T$58,"Supporting")+COUNTIF(Films!$T$2:$T$58,"Antagonist") | C11: Formula | D11: Role Type: Supporting, Antagonist | AN11: Relationship manipulated by outsiders
A12: Cameos and special appearances | B12: =COUNTIF(Films!$T$2:$T$58,"Cameo")+COUNTIF(Films!$T$2:$T$58,"Extended special appearance")+COUNTIF(Films!$T$2:$T$58,"Self appearance") | C12: Formula | D12: Role Type: Cameo, Extended special appearance, Self appearance | AN12: Forbidden love
A13: Voice, narration and child roles | B13: =COUNTIF(Films!$T$2:$T$58,"Voice role")+COUNTIF(Films!$T$2:$T$58,"Narrator")+COUNTIF(Films!$T$2:$T$58,"Child role") | C13: Formula | D13: Role Type: Voice role, Narrator, Child role | AN13: Unrequited love
A14: Films with central romance | B14: =COUNTIF(Films!$AE$2:$AE$58,"Central") | C14: Formula | D14: Romance Presence: Central | AN14: Love triangle
A15: Films with major romance | B15: =COUNTIF(Films!$AE$2:$AE$58,"Major") | C15: Formula | D15: Romance Presence: Major | AN15: Tragic lovers
A16: Films with secondary romance | B16: =COUNTIF(Films!$AE$2:$AE$58,"Secondary") | C16: Formula | D16: Romance Presence: Secondary | AN16: Unequal or coercive relationship
A17: Films with minor or implied romance | B17: =COUNTIF(Films!$AE$2:$AE$58,"Minor")+COUNTIF(Films!$AE$2:$AE$58,"Implied") | C17: Formula | D17: Romance Presence: Minor, Implied | AN17: Obsessive pursuit
A18: Films without meaningful romance | B18: =COUNTIF(Films!$AE$2:$AE$58,"None") | C18: Formula | D18: Romance Presence: None | AN18: Romance subordinate to another genre
A19: Distinct principal female co-stars | B19: 40 | C19: Build script | D19: Distinct names in Principal Female Lead or Leads | AN19: Multiple romantic relationships
A20: Romantic pairings recorded | B20: =COUNTA(Romances!$A$2:$A$38) | C20: Formula | AN20: No meaningful romance
A21: Most frequent romantic co-star | B21: Juhi Chawla (6 films) | C21: Build script | D21: Films with a Romances row for her
A22: Most frequent director | B22: Ashutosh Gowariker; Indra Kumar; Mansoor Khan; Zoya Akhtar (3 films each) | C22: Build script
A23: Most frequent producer or production banner | B23: Aamir Khan Productions (11 films) | C23: Build script | D23: From Production Banner
A24: Most frequent music director | B24: A. R. Rahman; Anand–Milind (6 films each) | C24: Build script | D24: From Song Composer
A25: Average pair-friction score | B25: =IFERROR(ROUND(AVERAGE(Romances!$Q$2:$Q$38),1),"n/a") | C25: Formula | D25: Per pairing
A26: Average external-opposition score | B26: =IFERROR(ROUND(AVERAGE(Romances!$S$2:$S$38),1),"n/a") | C26: Formula | D26: Per pairing
A27: Average lover-boy score | B27: =IFERROR(ROUND(AVERAGE(Romances!$V$2:$V$38),1),"n/a") | C27: Formula | D27: Per pairing
A28: Average romance-centrality score | B28: =IFERROR(ROUND(AVERAGE(Films!$AF$2:$AF$58),1),"n/a") | C28: Formula | D28: Per film
A29: Highest-grossing film | B29: Dangal (2016): 2,024 INR crore | C29: Build script | D29: Largest nominal worldwide gross among 14 film(s) reported in INR crore; not inflation-adjusted; 3 film(s) with ranged or disputed figures excluded
A30: Award wins received by the actor | B30: =COUNTIFS(Awards!$I$2:$I$144,"Win",Awards!$G$2:$G$144,"*Aamir Khan*") | C30: Formula | D30: Awards rows whose Recipient includes the actor, in any capacity: acting, directing, producing, honours
A31: Acting award wins | B31: =COUNTIFS(Awards!$I$2:$I$144,"Win",Awards!$G$2:$G$144,"*Aamir Khan*",Awards!$H$2:$H$144,"Actor") | C31: Formula | D31: As above, limited to Recipient Type 'Actor'
A32: Award nominations received by the actor | B32: =COUNTIFS(Awards!$I$2:$I$144,"Nomination",Awards!$G$2:$G$144,"*Aamir Khan*") | C32: Formula | D32: Nominations that did not win
A33: Award wins for his films (all recipients) | B33: =COUNTIF(Awards!$I$2:$I$144,"Win") | C33: Formula
A34: Source-confidence summary (films) | B34: ="High "&COUNTIF(Films!$AS$2:$AS$58,"High")&" · "&"Medium "&COUNTIF(Films!$AS$2:$AS$58,"Medium")&" · "&"Low "&COUNTIF(Films!$AS$2:$AS$58,"Low")&" · "&"Unknown "&COUNTIF(Films!$AS$2:$AS$58,"Unknown") | C34: Formula | D34: Confidence Grade in Films
A35: Sources by reliability tier | B35: ="A "&COUNTIF(Sources!$L$2:$L$215,"A")&" · "&"B "&COUNTIF(Sources!$L$2:$L$215,"B")&" · "&"C "&COUNTIF(Sources!$L$2:$L$215,"C")&" · "&"D "&COUNTIF(Sources!$L$2:$L$215,"D") | C35: Formula | D35: A official · B reputable press · C reference databases · D weak
A37: Career phases
A38: Phase | B38: Years | C38: Films | D38: Summary | E38: Avg lover-boy score
A39: Child actor | B39: 1973–1974 | C39: =COUNTIFS(Films!$D$2:$D$58,">=1973",Films!$D$2:$D$58,"<=1974") | D39: Brief child roles in two films, including the title song of his uncle Nasir Hussain's Yaadon Ki Baaraat. | E39: =IFERROR(ROUND(AVERAGEIFS(Romances!$V$2:$V$38,Romances!$D$2:$D$38,">=1973",Romances!$D$2:$D$38,"<=1974"),1),"n/a")
A40: Early romantic-hero phase | B40: 1984–1994 | C40: =COUNTIFS(Films!$D$2:$D$58,">=1984",Films!$D$2:$D$58,"<=1994") | D40: After the parallel-cinema Holi, Qayamat Se Qayamat Tak made him a teenage romantic lead; most films pair a young couple against feuding or class-proud families, often opposite Juhi Chawla. | E40: =IFERROR(ROUND(AVERAGEIFS(Romances!$V$2:$V$38,Romances!$D$2:$D$38,">=1984",Romances!$D$2:$D$38,"<=1994"),1),"n/a")
A41: Star consolidation and genre range | B41: 1995–2001 | C41: =COUNTIFS(Films!$D$2:$D$58,">=1995",Films!$D$2:$D$58,"<=2001") | D41: Rangeela, Raja Hindustani and Ghulam move him to street-smart and working-class lovers; Sarfarosh, Earth and Lagaan widen his range, and romance becomes one strand among others. | E41: =IFERROR(ROUND(AVERAGEIFS(Romances!$V$2:$V$38,Romances!$D$2:$D$38,">=1995",Romances!$D$2:$D$38,"<=2001"),1),"n/a")
A42: Selective prestige lead phase | B42: 2005–2014 | C42: =COUNTIFS(Films!$D$2:$D$58,">=2005",Films!$D$2:$D$58,"<=2014") | D42: Roughly one film a year, mostly event films with social or historical themes; romance is usually subordinate, with Fanaa and Ghajini the main exceptions. | E42: =IFERROR(ROUND(AVERAGEIFS(Romances!$V$2:$V$38,Romances!$D$2:$D$38,">=2005",Romances!$D$2:$D$38,"<=2014"),1),"n/a")
A43: Character-actor and producer phase | B43: 2015–2026 | C43: =COUNTIFS(Films!$D$2:$D$58,">=2015",Films!$D$2:$D$58,"<=2026") | D43: Older, flawed or comic characters (Dangal, Secret Superstar, Sitaare Zameen Par), a voice role, song cameos and special appearances; romance appears mainly as marriage or unrequited devotion. | E43: =IFERROR(ROUND(AVERAGEIFS(Romances!$V$2:$V$38,Romances!$D$2:$D$38,">=2015",Romances!$D$2:$D$38,"<=2026"),1),"n/a")
A45: Romantic co-stars (top 10)
A46: Actress | B46: Films with a pairing
A47: Juhi Chawla | B47: 6
A48: Rani Mukerji | B48: 3
A49: Madhuri Dixit | B49: 2
A50: Manisha Koirala | B50: 2
A51: Kareena Kapoor | B51: 2
A52: Supriya Pathak | B52: 1
A53: Farha Naaz | B53: 1
A54: Neelam | B54: 1
A55: Pooja Bhatt | B55: 1
A56: Pooja Bedi | B56: 1
A58: Romance centrality by decade
A59: Decade | B59: Films | C59: Avg romance centrality
A60: 1970s | B60: 2 | C60: 0
A61: 1980s | B61: 4 | C61: 5.8
A62: 1990s | B62: 25 | C62: 6
A63: 2000s | B63: 10 | C63: 4.5
A64: 2010s | B64: 10 | C64: 1.8
A65: 2020s | B65: 6 | C65: 1.8
A67: Column colour key
A68: Fact | B68: Fact: credits, dates, figures and descriptive fields
A69: Score | B69: Score (0–10): cells shaded white (0) to orange (10)
A70: Analysis | B70: Interpretive analysis: header green, cells tinted green

Sheet Films
A1: Film ID | B1: Title | C1: Release Date | D1: Release Year | E1: Decade | F1: Language | G1: Genre | H1: Secondary Genre | I1: Runtime | J1: Director | K1: Producer or Producers | L1: Production Banner | M1: Writer or Writers | N1: Source Material or Remake Status | O1: Song Composer | P1: Background-Score Composer | Q1: Lyricist | R1: Actor’s Character | S1: Alternate Identity or Double Role | T1: Role Type | U1: Billing Position | V1: Character Occupation | W1: Character Social Background | X1: Role Gist | Y1: Principal Motivation | Z1: Principal Conflict | AA1: Character Arc | AB1: Moral Alignment | AC1: Character Outcome | AD1: Principal Female Lead or Leads | AE1: Romance Presence | AF1: Romance Centrality Score | AG1: Overall Relationship Classification | AH1: Budget | AI1: Domestic Nett | AJ1: Domestic Gross | AK1: Overseas Gross | AL1: Worldwide Gross | AM1: Currency | AN1: Box-Office Verdict | AO1: Annual Box-Office Rank | AP1: Critical Reception Summary | AQ1: Recognition or Legacy | AR1: Source IDs | AS1: Confidence Grade | AT1: Research Notes
A2: FILM-001 | B2: Yaadon Ki Baaraat | C2: 26977 | D2: 1973 | E2: 1970s | F2: Hindi | G2: Masala | H2: Musical | I2: 168 | J2: Nasir Hussain | K2: Nasir Hussain | L2: Nasir Hussain Films | M2: Salim–Javed; Nasir Hussain | N2: Original | O2: R. D. Burman | Q2: Majrooh Sultanpuri | R2: Young Ratan | S2: Credited as Master Aamir | T2: Child role | W2: Younger version of Ratan (played as an adult by Tariq Khan) | X2: Credited as Master Aamir, the eight-year-old plays the younger Ratan in the flashback built around the title song 'Yaadon Ki Baaraat Nikli Hai', which shows the brothers as children before they are separated. The appearance is brief and has no independent arc; the adult Ratan is played by Tariq Khan. | AA2: Not applicable (brief child role) | AE2: None | AF2: 0 | AG2: No meaningful romance | AM2: INR crore | AO2: 5 | AQ2: Described as the first quintessential masala film; popularised the separated-siblings-reunited formula and launched the careers of Zeenat Aman, Neetu Singh and Tariq Khan. | AR2: SOURCE-004; SOURCE-001 | AS2: Medium | AT2: Release date 9 November 1973 per Wikipedia; Bollywood Hungama lists 3 November 1973. Wikipedia gives box office of ₹5.5 crore (Box Office India) without a nett/gross label, so it is not entered; annual rank 5 refers to that unlabeled measure.
A3: FILM-002 | B3: Madhosh | C3: 1974 | D3: 1974 | E3: 1970s | F3: Hindi | G3: Drama | I3: 133 | J3: Desh Gautam | K3: Tahir Hussain | O3: R. D. Burman | Q3: Majrooh Sultanpuri | R3: Younger Raj | T3: Child role | W3: Younger version of Raj Kumar (played as an adult by Mahendra Sandhu) | X3: Aamir Khan is credited as the younger version of Raj, the lead played by Mahendra Sandhu, in a 1974 drama produced by Tahir Hussain. The sources consulted carry no plot summary and do not describe the child role, so the character's function in the film is unverified beyond the cast credit. | AA3: Not applicable (brief child role) | AE3: None | AF3: 0 | AG3: No meaningful romance | AR3: SOURCE-005; SOURCE-001 | AS3: Low | AT3: Exact release date, writers, box office and reception not found. Wikipedia's article is a stub flagged as needing a plot summary.
A4: FILM-003 | B4: Holi | C4: 30909 | D4: 1984 | E4: 1980s | F4: Hindi | G4: Drama | H4: Coming-of-age | I4: 120 | J4: Ketan Mehta | K4: Pradeep Uppoor | M4: Ketan Mehta; Mahesh Elkunchwar (screenplay) | N4: Based on a play by Marathi playwright Mahesh Elkunchwar | O4: Rajat Dholakia | R4: Madan Sharma | S4: Credited as Aamir Hussain | T4: Ensemble lead | V4: College hostel student | W4: Student in a college hostel | X4: Madan is one of the restless hostel students whose boredom and resentment of the principal escalate into a campus revolt. He joins the protest, is suspended, is implicated after a classmate's suicide and is arrested. The largely improvised parallel-cinema ensemble gave Aamir Khan his first adult screen role, credited as Aamir Hussain. | Y4: Rebellion against the college authorities | Z4: Student protest against the principal and its fallout | AA4: Bored participant in hostel pranks becomes implicated in tragedy | AB4: Morally ambiguous | AC4: Suspended and arrested | AE4: None | AF4: 0 | AG4: No meaningful romance | AP4: Vincent Canby (The New York Times, 1985) found it decently and exuberantly performed by its largely non-professional cast. | AQ4: Wikipedia lists a National Film Award for Best Cinematography (Jehangir Choudhary), flagged as needing a citation. | AR4: SOURCE-006; SOURCE-001 | AS4: Medium | AT4: No budget or box-office data found. Production company not stated.
A5: FILM-004 | B5: Qayamat Se Qayamat Tak | C5: 32262 | D5: 1988 | E5: 1980s | F5: Hindi | G5: Romance | H5: Musical tragedy | I5: 163 | J5: Mansoor Khan | K5: Nasir Hussain | L5: Nasir Hussain Films | M5: Nasir Hussain (story, screenplay); Nuzhat Khan, Aamir Khan (assistant writers) | N5: Original; modern retelling of Layla–Majnun, Heer–Ranjha and Romeo and Juliet | O5: Anand–Milind | Q5: Majrooh Sultanpuri | R5: Rajveer "Raj" Singh | S5: Poses as Roop Singh, Rashmi's intended suitor, at her birthday party | T5: Lead | U5: 1 | V5: Graduate who joins the family clothing business | W5: Rajput family from Dhanakpur, raised in Delhi by his uncle after his father's imprisonment for murder | X5: Raj, the college-educated son of a Rajput family broken by a murder, falls for Rashmi without knowing she belongs to the clan his father wronged. He gatecrashes her birthday under a false name, courts her on holiday and, when both families forbid the match, elopes with her to a ruined fort. Hired killers shoot Rashmi; Raj stabs himself and dies beside her. | Y5: Love for Rashmi and a life free of the family feud | Z5: Loves the daughter of his family's sworn enemy | AA5: Dutiful, wholesome son becomes a lover who defies both families and chooses death over separation | AB5: Heroic | AC5: Dies by suicide beside Rashmi after she is shot | AD5: Juhi Chawla | AE5: Central | AF5: 10 | AG5: Tragic lovers | AH5: 2.5 | AI5: 5 | AM5: INR crore | AN5: Blockbuster | AO5: 3 | AP5: Positive reviews; credited with reinventing the romantic musical and bringing family audiences back to cinemas. | AQ5: Cult classic with a 50-week run; subject of a 2016 book crediting it with reviving Hindi cinema; remade in Telugu, Bangladeshi Bengali, Sinhala and Nepali. | AR5: SOURCE-007 | AS5: Medium | AT5: Budget ₹25 million and domestic nett ₹50 million (The Times of India, via Wikipedia). Wikipedia also lists ₹50 million as worldwide gross without a separate source; not recorded because it duplicates the nett figure. Annual rank 3 (behind Tezaab and Shahenshah) per Box Office India via Wikipedia.
A6: FILM-005 | B6: Raakh | C6: 32619 | D6: 1989 | E6: 1980s | F6: Hindi | G6: Action crime | H6: Revenge drama | I6: 124 | J6: Aditya Bhattacharya | K6: Asif Noor; Sangeeth Sivan; Aditya Bhattacharya | M6: Aditya Bhattacharya; Nuzhat Khan | N6: Original screenplay | P6: Ranjit Barot | R6: Amir Hussein | T6: Lead | U6: 1 | V6: Aimless young man who becomes a vigilante | W6: From a well-off family, leading an otherwise mundane life | X6: Amir is a fearless but aimless young man whose older, more pragmatic girlfriend Neeta is raped by the crime boss Hassan Karmali while he is forced to watch. Guided by a disillusioned policeman, he sets out to wipe out the Karmali family, growing used to violence and even enjoying it. Neeta slowly rebuilds her life; Amir ends on death row. | Y6: Revenge for the assault on Neeta | Z6: Rage at an unjust system against guilt over his own violence | AA6: Innocent, fearless youth becomes a hardened killer | AB6: Anti-hero | AC6: Awaits execution on death row | AD6: Supriya Pathak | AE6: Secondary | AF6: 4 | AG6: Romance subordinate to another genre | AM6: INR crore | AP6: Strong critical acclaim; developed a considerable cult following. | AQ6: Three National Film Awards, including a Special Mention for Aamir Khan (shared with Qayamat Se Qayamat Tak); Bollywood debuts of cinematographer Santosh Sivan and editor A. Sreekar Prasad. | AR6: SOURCE-008 | AS6: Medium | AT6: Shot before but released after Qayamat Se Qayamat Tak. Wikipedia gives box office of ₹15 million (₹1.5 crore) citing Talking Moviez, without a nett/gross label; not entered.
A7: FILM-006 | B7: Love Love Love | C7: 32724 | D7: 1989 | E7: 1980s | F7: Hindi | G7: Romantic action | I7: 146 | J7: Babbar Subhash | K7: Babbar Subhash | L7: B. Subhash Movie Unit | M7: Babbar Subhash | O7: Bappi Lahiri | R7: Amit Verma | T7: Lead | U7: 1 | V7: Student | W7: Poor household with his father, stepmother and sister | X7: Amit, a student from a poor family, falls for his wealthy schoolmate Reema, who is coveted by the violent Vicky. Vicky and his father threaten Amit's family and force the lovers apart, and Amit is humiliated at Reema's engagement party. The couple flee, Amit survives an assassination attempt, and they are reunited after Reema's father kills both antagonists. | Y7: Love for Reema across the class divide | Z7: A violent rival and threats against his family | AA7: Humiliated poor lover persists and survives to win Reema | AB7: Heroic | AC7: Reunited with Reema | AD7: Juhi Chawla | AE7: Central | AF7: 9 | AG7: United couple versus external world | AM7: INR crore | AN7: Average | AP7: Did not match the expectations set by the pair's debut film but was appreciated by viewers. | AQ7: Second film of the Aamir Khan–Juhi Chawla pairing. | AR7: SOURCE-009 | AS7: Medium | AT7: Wikipedia gives box office of ₹2.8 crore citing Indicine, without a nett/gross label; not entered. Budget not found.
A8: FILM-007 | B8: Awwal Number | C8: 33004 | D8: 1990 | E8: 1990s | F8: Hindi | G8: Sports action | I8: 143 | J8: Dev Anand | K8: Dev Anand | M8: Dev Anand | O8: Bappi Lahiri | Q8: Amit Khanna | R8: Sunny | T8: Co-lead | U8: 2 | V8: Cricketer newly selected for the national team | W8: Up-and-coming player replacing an established star | X8: Sunny is a young cricketer picked for India in place of the established star Ronny, who turns vengeful. As DIG Vikram Singh races to stop a terrorist plot to bomb an India–Australia match, Sunny weathers Ronny's hostility and becomes a star by playing the match-winning stroke. A light romance with Aarti offers him emotional support. | Y8: Prove himself in international cricket | Z8: Rivalry with the displaced star Ronny amid a terror plot | AA8: Untested newcomer becomes a match-winner | AB8: Heroic | AC8: Wins the match for India | AD8: Ekta Sohini | AE8: Minor | AF8: 2 | AG8: Romance subordinate to another genre | AP8: A 2019 retrospective blog review treats the film as unintentionally comic. | AR8: SOURCE-010; SOURCE-011; SOURCE-065 | AS8: Low | AT8: Second-billed after Dev Anand. The romance with Aarti (Ekta Sohini) is documented only through the 'I love you' recorder scene, so no Romances row was created. Bollywood Hungama's 1 January 1990 date is a placeholder; Wikipedia's 11 May 1990 is used. No box-office data found.
A9: FILM-008 | B9: Tum Mere Ho | C9: 33018 | D9: 1990 | E9: 1990s | F9: Hindi | G9: Fantasy | H9: Action | I9: 129 | J9: Tahir Hussain | K9: Tahir Hussain | L9: Tahir Hussain Enterprises | M9: Tahir Hussain, M. Kaleem Rahi (screenplay); Tahir Hussain, Surinder Singh (story) | O9: Anand–Milind | Q9: Majrooh Sultanpuri | R9: Shiva | T9: Lead | U9: 1 | V9: Snake charmer | W9: Foundling raised by a poor snake charmer after surviving a serpent's revenge as a baby | X9: Shiva survives a shape-shifting serpent's revenge as a baby and is raised by a poor snake charmer. His music enchants Paro at a fair and they fall in love, but her family reveals she was married as a child and must live as a widow, and her father sends men to kill him. Shiva finally uses his charmer's powers to force the serpent to undo her curse. | Y9: Love for Paro | Z9: Paro's family, the child-widow custom and the serpent's curse | AA9: Cursed foundling becomes a charmer powerful enough to defeat the serpent | AB9: Heroic | AC9: Defeats the serpent; union with Paro implied but not confirmed by sources | AD9: Juhi Chawla | AE9: Central | AF9: 8 | AG9: Forbidden love | AN9: Disaster | AP9: A box-office disaster later enjoyed as a so-bad-it's-good cult film; one 2019 review credits it with using snake tropes to dramatise patriarchal custom. | AR9: SOURCE-012; SOURCE-013 | AS9: Low | AT9: Wikipedia and The Cultural Gutter describe Shiva's origin differently (his father kills the snake versus a stranger stealing its crown); the shared elements are used. The ending is not stated explicitly in either source. No budget or box-office figures found.
A10: FILM-009 | B10: Dil | C10: 33046 | D10: 1990 | E10: 1990s | F10: Hindi | G10: Romantic action | I10: 172 | J10: Indra Kumar | K10: Indra Kumar; Ashok Thakeria | L10: Maruti International | M10: Naushir Khatau (story, screenplay); Rajeev Kaul, Praful Parekh (screenplay); Kamlesh Pandey (dialogue) | O10: Anand–Milind | Q10: Sameer | R10: Raja Prasad | T10: Lead | U10: 1 | V10: College student, later construction worker | W10: Son of Hazari Prasad, a miserly and greedy wastepaper businessman | X10: Raja, the spendthrift son of a miserly scrap dealer, meets the arrogant heiress Madhu at college, fakes blindness to fool her and trades pranks with her. After she falsely accuses him of attempted rape and he rebukes her, they fall in love. Disowned by both fathers, they marry secretly and live in poverty; when Raja is injured, his father tricks Madhu into leaving, but they reunite. | Y10: Love for Madhu | Z10: Both fathers' greed and class pride | AA10: Pleasure-seeking prankster becomes a hard-working husband | AB10: Heroic | AC10: Reunited with Madhu | AD10: Madhuri Dixit | AE10: Central | AF10: 10 | AG10: Rivals to lovers | AH10: 2 | AM10: INR crore | AN10: Highest-grossing film of the year | AO10: 1 | AP10: Positive reviews, with praise for the soundtrack and cast performances. | AQ10: Madhuri Dixit's first Filmfare Best Actress award; soundtrack sold about 2 million units; remade in Telugu (Tholi Muddu) and Kannada (Shivaranjani). | AR10: SOURCE-014 | AS10: Medium | AT10: Wikipedia gives two release dates (15 and 22 June 1990); the infobox date 22 June is used, matching Bollywood Hungama. Box office 'est. ₹20 crore' (Box Office India via Wikipedia) has no nett/gross label and is not entered.
A11: FILM-010 | B11: Deewana Mujh Sa Nahin | C11: 33074 | D11: 1990 | E11: 1990s | F11: Hindi | G11: Romantic action | I11: 130 | J11: Y. Nageshwar Rao | K11: Aji | L11: Vandana Productions | M11: M. Parvez | N11: Remake of the 1986 Pakistani film Beyqaraar | O11: Anand–Milind | Q11: Sameer | R11: Ajay Sharma | T11: Lead | U11: 1 | V11: Photographer at a modelling agency | X11: Ajay, a photographer at a modelling agency, becomes convinced that his colleague Anita returns his love, though she sees him only as a friend. When she becomes engaged to Vikram, Ajay keeps preparing to marry her anyway, and she must act to stop his obsession. Events expose that Vikram does not love her and that Ajay's devotion is sincere, and the film ends happily with them together. | Y11: Marry Anita | Z11: Anita does not love him and is engaged to Vikram | AA11: Deluded, fixated admirer is finally accepted | AB11: Sympathetic but obsessive | AC11: Wins Anita | AD11: Madhuri Dixit | AE11: Central | AF11: 9 | AG11: Obsessive pursuit | AR11: SOURCE-015 | AS11: Low | AT11: No budget, box-office, reception or award data found. Plot detail comes from a short Wikipedia synopsis.
A12: FILM-011 | B12: Jawani Zindabad | C12: 33102 | D12: 1990 | E12: 1990s | F12: Hindi | G12: Romantic action | H12: Social drama | I12: 163 | J12: Arun Bhatt | K12: Jay Mehta | L12: Prathima Films | M12: Bhushan Vanmali | N12: Remake of the Kannada film Avale Nanna Hendthi (1988) | O12: Anand–Milind | R12: Shashi Sharma | T12: Lead | U12: 1 | V12: Office worker | W12: Family scarred by dowry: his elder sister died a dowry victim | X12: Shashi, whose elder sister died as a victim of dowry, vows never to give or take dowry. Defying his mother, he marries Sugandha without any dowry, then takes on the greedy in-laws of his younger sister Rama, led by the politician Goverdhan Verma. Seriously injured in the confrontation, he survives to see Goverdhan reform. | Y12: End the dowry practice that killed his sister | Z12: Protecting Rama from her in-laws' greed | AA12: A principled young man holds to his vow against family pressure and political power | AB12: Heroic | AC12: Survives serious injuries; Goverdhan reforms | AD12: Farha Naaz | AE12: Secondary | AF12: 4 | AG12: Romance subordinate to another genre | AR12: SOURCE-016 | AS12: Low | AT12: Marriage to Sugandha is documented, but not how they meet. No box-office, reception or award data found.
A13: FILM-012 | B13: Afsana Pyar Ka | C13: 33354 | D13: 1991 | E13: 1990s | F13: Hindi | G13: Romantic drama | I13: 145 | J13: M. R. Shahjahan | K13: Manoj Seksaria; Sanjay Seksaria; Arvind Seksaria | M13: Bono Deb (story, screenplay); Ramesh Pant (dialogue) | O13: Bappi Lahiri | Q13: Sameer; Anjaan | R13: Raj | T13: Lead | U13: 1 | V13: College student | W13: Raised by his father Mahendra Behl, apart from the mother who left him as an infant | X13: Raj and Nikita meet at college and, after early misunderstandings, fall in love without knowing their families share a long-standing feud. Raj also does not realise that the college's new principal is the mother who left him with his father. When both families forbid the marriage and arrange other matches, the couple decide to elope. | Y13: Marry Nikita | Z13: Feuding families refuse the match | AA13: A college romance becomes open defiance of both families | AB13: Heroic | AC13: Elopes with Nikita; later events not verified | AD13: Neelam | AE13: Central | AF13: 9 | AG13: Forbidden love | AR13: SOURCE-017; SOURCE-065 | AS13: Low | AT13: The family backstory and elopement come from web search summaries of IMDb-style plot synopses. The songs 'Nazren Mili' and 'Tip Tip Tip Tip Baarish Shuru Ho Gayi' were popular. No box-office data found.
A14: FILM-013 | B14: Dil Hai Ke Manta Nahin | C14: 33431 | D14: 1991 | E14: 1990s | F14: Hindi | G14: Romantic comedy | H14: Road film | I14: 151 | J14: Mahesh Bhatt | K14: Gulshan Kumar; Mukesh Bhatt | L14: T-Series; Vishesh Films | M14: Robin Bhatt; Sharad Joshi | N14: Adaptation of It Happened One Night (1934) and Chori Chori (1956) | O14: Nadeem–Shravan | Q14: Sameer; Faaiz Anwar; Rani Malik; Aziz Khan | R14: Raghu Jetley | T14: Lead | U14: 1 | V14: Journalist who has just lost his job | W14: Working-class and financially insecure | X14: Raghu, a newly unemployed journalist, recognises a runaway heiress on a bus and forces a bargain: he will help her reach her film-star fiancé in exchange for an exclusive story. The road trip turns bickering into love. When he leaves to raise money so he can propose, she believes he has used her and returns to marry the star, until her father reveals Raghu's integrity. | Y14: An exclusive story to rescue his career, then love for Pooja | Z14: Has no money or standing to marry the heiress he has fallen for | AA14: Opportunistic blackmailer becomes a devoted, scrupulous lover | AB14: Morally grey to heroic | AC14: Pooja leaves her wedding to marry him with her father's blessing | AD14: Pooja Bhatt | AE14: Central | AF14: 9 | AG14: Playful conflict masking attraction | AM14: INR crore | AN14: Box office success | AP14: A commercial success whose soundtrack was praised; boosted Pooja Bhatt's career and consolidated Aamir Khan's stardom. | AQ14: Remade in Telugu as Kurradi Kurrodu (1994) and Tamil as Kadhal Rojavae (2000). | AR14: SOURCE-018; SOURCE-019 | AS14: Medium | AT14: Wikipedia gives box office of ₹42 million (₹4.2 crore) citing Box Office India, without saying whether it is nett or gross; Box Office India's own film page shows no figures. Not entered in any commercial column. Runtime from Box Office India. Filmfare: Best Actor nomination for Aamir Khan.
A15: FILM-014 | B15: Daulat Ki Jung | C15: 33620 | D15: 1992 | E15: 1990s | F15: Hindi | G15: Action adventure | J15: S. A. Kader | K15: Jalil Ahmed | N15: Inspired by Mackenna's Gold (1969) | O15: Anand–Milind | Q15: Majrooh Sultanpuri | R15: Rajesh Chaudhry | T15: Lead | U15: 1 | V15: College student | W15: Son of the wealthy businessman Bhushan Chaudhry | X15: Rajesh, the son of a wealthy businessman, loves his classmate Asha, whose father is his father's business rival. When both fathers clamp down on them, the couple elope in a stolen car and stumble into a treasure hunt around a tribal village, pursued by crooks. An undercover police officer disposes of the criminals and the lovers are united. | Y15: Be with Asha | Z15: Rival fathers and treasure-hunting criminals | AA15: Sheltered rich son becomes a fugitive lover | AB15: Heroic | AC15: United with Asha | AD15: Juhi Chawla | AE15: Central | AF15: 7 | AG15: United couple versus external world | AN15: Box office failure | AR15: SOURCE-020 | AS15: Low | AT15: Release date 17 January 1992 per Wikipedia; Bollywood Hungama lists 3 January 1992. Runtime, writers and box-office figures not found.
A16: FILM-015 | B16: Jo Jeeta Wohi Sikandar | C16: 33746 | D16: 1992 | E16: 1990s | F16: Hindi | G16: Sports drama | H16: Coming-of-age | I16: 169 | J16: Mansoor Khan | K16: Nasir Hussain | L16: Nasir Hussain Films | M16: Nasir Hussain; Mansoor Khan | N16: Original; resemblance to Breaking Away (1979) noted after release | O16: Jatin–Lalit | Q16: Majrooh Sultanpuri | R16: Sanjaylal "Sanju" Sharma | T16: Lead | U16: 1 | V16: Student at Model College | W16: Middle-class son of Ramlal Sharma; younger brother of the college's star cyclist Ratan | X16: Sanju is a carefree Model College student living in the shadow of his brother Ratan and the elite Rajput College. He fakes wealth to date the rich Devika, ignoring his loyal friend Anjali's warnings, and is humiliated when exposed. After Ratan is badly injured in the rivalry, a chastened Sanju takes his place in the inter-college cycle race and wins it in the final seconds. | Y16: Status and fun, later redemption for his brother and father | Z16: Class rivalry with Rajput College and its champion Shekhar | AA16: Irresponsible show-off becomes a disciplined, humbled champion | AB16: Flawed, redeemed | AC16: Wins the cycle race for Model College | AD16: Ayesha Jhulka; Pooja Bedi | AE16: Major | AF16: 6 | AG16: Multiple romantic relationships | AM16: INR crore | AN16: Commercially successful | AP16: The Indian Express (1992) praised the cinematography, sets and performances of Aamir Khan, Ayesha Jhulka and Pooja Bedi but criticised the music. | AQ16: Cult following; often cited among the best Indian coming-of-age films. Filmfare Best Film. | AR16: SOURCE-021 | AS16: Medium | AT16: Wikipedia gives India box office of ₹70 million (₹7 crore), citing Bollywood Hungama and Box Office India, without a nett/gross label; not entered.
A17: FILM-016 | B17: Isi Ka Naam Zindagi | C17: 33844 | D17: 1992 | E17: 1990s | F17: Hindi | G17: Supernatural action comedy | I17: 145 | J17: Kalidas | K17: Ratan Mukherjee | N17: Remake of the Bengali film Banchharamer Bagaan (1980), based on Manoj Mitra's play Shajano Bagaan | O17: Bappi Lahiri | Q17: Ramesh Pant | R17: Chhotu | T17: Co-lead | U17: 1 | W17: Grandson of Bansiram, who guards a coveted plot of land | X17: Chhotu is the grandson of Bansiram, an old man who refuses to surrender a prized plot of land to successive heirs of a zamindar family. The film's weight rests on Pran's Bansiram, and later comment describes Aamir Khan's part as largely inconsequential, relegated to songs and a romance with Chumki. No detailed account of Chhotu's own arc was found. | AD17: Farah | AE17: Minor | AF17: 3 | AG17: Romance subordinate to another genre | AM17: INR crore | AN17: Box office failure | AP17: Pran's performance was singled out and used to promote the film. | AR17: SOURCE-022; SOURCE-065 | AS17: Low | AT17: Billed first but functions as a co-lead to Pran. Wikipedia gives box office of ₹18 million (Indicine) without a nett/gross label; not entered. No Romances row because the relationship with Chumki is undocumented beyond the cast list.
A18: FILM-017 | B18: Damini | C18: 34089 | D18: 1993 | E18: 1990s | F18: Hindi | G18: Legal drama | I18: 150 | J18: Rajkumar Santoshi | K18: Karim Morani; Bunty Soorma; Ali Morani | L18: Cineyug Films | M18: Rajkumar Santoshi (story, screenplay); Sutanu Gupta (story); Dilip Shukla (dialogue) | O18: Nadeem–Shravan | P18: Vanraj Bhatia | Q18: Sameer | R18: Himself | T18: Self appearance | X18: Aamir Khan appears as himself in the stage-show dance number 'Bin Sajan Jhoola Jhoolu' in Rajkumar Santoshi's legal drama. The appearance doubles as promotion for his then-upcoming Santoshi film Andaz Apna Apna and has no narrative function. The drama itself, led by Meenakshi Seshadri and Sunny Deol, is regarded as a cult feminist film and won National Film and Filmfare awards. | AE18: None | AF18: 0 | AG18: No meaningful romance | AM18: INR crore | AP18: Universal acclaim for its execution and performances; regarded as a cult feminist film. | AQ18: National Film Award for Best Supporting Actor (Sunny Deol); Filmfare Best Director, Supporting Actor, Story and Sound. | AR18: SOURCE-023 | AS18: Medium | AT18: Wikipedia's 'est. ₹11.75 crore' box office has no nett/gross label and is not entered.
A19: FILM-018 | B19: Parampara | C19: 34103 | D19: 1993 | E19: 1990s | F19: Hindi | G19: Action drama | I19: 155 | J19: Yash Chopra | K19: Firoz A. Nadiadwala | M19: Honey Irani (story, screenplay); Aditya Chopra (screenplay); Rahi Masoom Raza (dialogue) | O19: Shiv–Hari | R19: Ranvir Prithvi Singh | T19: Co-lead | V19: College student | W19: Son of Prithvi Singh and the gypsy woman Tara, raised in the Thakur household after her death | X19: Ranvir, son of Prithvi Singh and the gypsy woman Tara, grows up in the Thakur household alongside his half-brother Pratap. On learning who ordered his mother's execution, he turns on Pratap and a violent feud engulfs the family. After the patriarch's death the brothers embrace and the bloodshed ends. | Y19: Justice for his mother's death | Z19: Feud with his half-brother Pratap over the family's past | AA19: Unaware youth becomes vengeful, then reconciles | AB19: Morally conflicted | AC19: Reconciles with Pratap | AE19: Minor | AF19: 2 | AG19: Romance subordinate to another genre | AN19: Flop | AP19: Largely negative reviews; one review singled out Aamir Khan's performance while calling the younger cast out of place. | AR19: SOURCE-024; SOURCE-065 | AS19: Low | AT19: Neelam (Sapna) and Raveena Tandon (Vijaya) appear, but no source consulted documents a romantic pairing for Ranvir, so Principal Female Lead is left blank and no Romances row was created. Saif Ali Khan's Hindi film debut. No box-office figures found.
A20: FILM-019 | B20: Hum Hain Rahi Pyar Ke | C20: 34173 | D20: 1993 | E20: 1990s | F20: Hindi | G20: Romantic comedy-drama | I20: 150 | J20: Mahesh Bhatt | K20: Tahir Hussain | L20: Tahir Hussain Enterprises | M20: Robin Bhatt (story, screenplay, dialogue); Aamir Khan (screenplay, dialogue) | N20: Based on Houseboat (1958) | O20: Nadeem–Shravan | P20: Shyam–Surender; Nadeem–Shravan | Q20: Sameer | R20: Rahul Malhotra | T20: Lead | U20: 1 | V20: Runs a garment company under pressure to deliver a large shirt order | W20: Guardian of his late sister's three mischievous children | X20: Rahul, struggling to run a garment business and control his late sister's three unruly children, agrees to marry the businessman Bijlani's daughter Maya for the children's sake. The children secretly shelter Vyjayanti, who has escaped her father's confinement, and she wins them over and then Rahul. Surviving sabotage by the spurned Bijlanis and her tradition-bound father's resistance, Rahul marries Vyjayanti. | Y20: Keep the business afloat and give the children a stable home | Z20: Obligation to the Bijlanis against love for Vyjayanti | AA20: Stern, overwhelmed guardian becomes a warm father figure and partner | AB20: Heroic | AC20: Completes the order despite sabotage and marries Vyjayanti | AD20: Juhi Chawla | AE20: Central | AF20: 8 | AG20: Friendship to love | AM20: INR crore | AP20: Positive reviews, with particular praise for Juhi Chawla's performance. | AQ20: National Film Awards: Special Jury Award (Mahesh Bhatt) and Best Female Playback Singer (Alka Yagnik). Filmfare Best Film and Best Actress. Soundtrack sold 2.5 million units. Remade in Telugu and Malayalam. | AR20: SOURCE-025 | AS20: Medium | AT20: Aamir Khan co-wrote the screenplay and dialogue. Wikipedia's ₹97 million box office (Box Office India) has no nett/gross label and is not entered.
A21: FILM-020 | B21: Pehla Nasha | C21: 34194 | D21: 1993 | E21: 1990s | F21: Hindi | G21: Thriller | I21: 131 | J21: Ashutosh Gowariker | K21: Mohammed A. Rahim; Viral Shah | M21: Neeraj Vora (story); Ashutosh Gowariker (screenplay); Sanjay Chhel (dialogue) | N21: Remake of Body Double (1984) | O21: Uttankk V. Vora; Neeraj Vora | Q21: Anand Bakshi | R21: Himself | T21: Self appearance | X21: Aamir Khan appears as himself in a scene with Shah Rukh Khan, Saif Ali Khan, Rahul Roy and Sudesh Berry in Ashutosh Gowariker's directorial debut, a remake of Body Double. It is noted as the only film to put Aamir, Shah Rukh and Saif Khan in a single scene; the cameo has no narrative role. | AE21: None | AF21: 0 | AG21: No meaningful romance | AN21: Failure | AP21: Negative reviews. | AR21: SOURCE-026 | AS21: Medium | AT21: First collaboration with Ashutosh Gowariker as director. No box-office figures found.
A22: FILM-021 | B22: Andaz Apna Apna | C22: 34642 | D22: 1994 | E22: 1990s | F22: Hindi | G22: Comedy | H22: Action | I22: 160 | J22: Rajkumar Santoshi | K22: Vinay Kumar Sinha | L22: Vinay Pictures | M22: Rajkumar Santoshi; Dilip Shukla | O22: Tushar Bhatia | P22: Viju Shah | Q22: Majrooh Sultanpuri | R22: Amar Manohar | S22: Uses the alias Teelu; feigns amnesia and blindness | T22: Lead | U22: 1 | V22: Unemployed daydreamer | W22: Lives with his father Murli Manohar | X22: Amar, a lazy daydreamer, sets out to marry the heiress Raveena Bajaj for her father's money and meets his match in the equally scheming Prem. Unaware that Raveena and her secretary Karishma have swapped identities, he falls for the woman he believes is the heiress. Through feigned amnesia, rival cons and a villainous twin, he ends up marrying the real Karishma for love. | Y22: Get rich by marrying an heiress | Z22: Rivalry with Prem for the heiress | AA22: Gold-digger falls genuinely in love and becomes a reluctant hero | AB22: Comic rogue | AC22: Marries Karishma | AD22: Raveena Tandon; Karisma Kapoor | AE22: Major | AF22: 6 | AG22: Romance subordinate to another genre | AH22: 2.9 | AJ22: 8.18 | AL22: 8.653 | AM22: INR crore | AN22: Commercially unsuccessful | AP22: Unsuccessful on release; later praised as one of the greatest Hindi comedies (Raja Sen, Khalid Mohamed). | AQ22: Cult classic; voted second-best Bollywood comedy in an Indian Express online poll; 4K re-release on 25 April 2025. | AR22: SOURCE-027; SOURCE-065 | AS22: Medium | AT22: Box Office India via Wikipedia: budget ₹29 million, domestic ₹8.18 crore, overseas US$150,000, worldwide gross ₹8.653 crore. The domestic figure is recorded as gross because it plus overseas approximates the worldwide gross. Release date 4 November 1994 per Wikipedia; Bollywood Hungama lists 3 September 1994. Raveena Tandon plays Karishma, the secretary posing as the heiress; she is Amar's partner.
A23: FILM-022 | B23: Baazi | C23: 34803 | D23: 1995 | E23: 1990s | F23: Hindi | G23: Action thriller | I23: 180 | J23: Ashutosh Gowariker | K23: Salim Akhtar | L23: Aftab Pictures | M23: Ashutosh Gowariker; Neeraj Vora; Naushil Mehta (writers); Santosh Saroj (dialogue) | N23: Original; critics likened it to Die Hard | O23: Anu Malik | P23: Aadesh Shrivastava | Q23: Majrooh Sultanpuri; Anwar Sagar | R23: Inspector Amar Damjee Rathod | S23: Goes undercover in drag as Miss Julie Braganza | T23: Lead | U23: 1 | V23: Police inspector | W23: Son of a police inspector; both parents were murdered by Chaubey | X23: Inspector Amar, whose parents were murdered by the politician Chaubey, investigates a multi-crore scandal and is framed for killing the police commissioner's daughter. Hunted, he works undercover, including in drag as Miss Julie Braganza, and fights through a hostage siege that endangers journalist Sanjana. He electrocutes Chaubey in the climax and is honoured by the Chief Minister. | Y23: Expose the scandal and avenge his parents | Z23: Framed and hunted by a powerful politician | AA23: Dedicated officer becomes a fugitive and avenger | AB23: Heroic | AC23: Kills Chaubey and is honoured | AD23: Mamta Kulkarni | AE23: Secondary | AF23: 3 | AG23: Romance subordinate to another genre | AH23: 3.25 | AM23: INR crore | AP23: Mixed reviews; India Today called it an ambitious collage of Die Hard, Point Break and Rambo that 'just doesn't work'. | AR23: SOURCE-028 | AS23: Medium | AT23: Budget ₹32.50 million; box office 'est. ₹88 million' (boxofficeindia.com via Wikipedia) has no nett/gross label and is not entered. Release date 14 April 1995 per Wikipedia; Bollywood Hungama lists 13 April.
A24: FILM-023 | B24: Aatank Hi Aatank | C24: 34915 | D24: 1995 | E24: 1990s | F24: Hindi | G24: Action crime | I24: 155 | J24: Dilip Shankar | K24: Mangal; Xavier Marquis (presenter) | L24: Suyash Films | M24: Dilip Shankar | N24: Heavily inspired by The Godfather (1972) | O24: Bappi Lahiri | Q24: Naqsh Lyallpuri; Anwar Sagar; Sanam Ghazipuri; others | R24: Rohan | T24: Co-lead | U24: 2 | V24: Son of a crime boss who becomes one himself | W24: Younger son of the crime patriarch Shiv Charan Sharma | X24: Rohan, the younger son of crime patriarch Shiv Charan Sharma, has kept away from the family business until his father is shot. He takes revenge on the rival Gogia Advani, goes on the run, and four years later has become a crime lord alongside his brother Munna. His girlfriend Neha and a later attraction to Ganga sit at the margins of this Godfather-inspired gang war. | Y24: Avenge the attack on his father | Z24: Gang war with rival dons | AA24: Outsider son becomes a crime lord | AB24: Anti-hero | AD24: Juhi Chawla; Pooja Bedi | AE24: Minor | AF24: 3 | AG24: Romance subordinate to another genre | AN24: Box office failure | AR24: SOURCE-029 | AS24: Low | AT24: Second-billed after Rajinikanth. Relationships with Neha (Juhi Chawla) and Ganga (Pooja Bedi) are documented only as one-line cast descriptions, so no Romances rows were created. Ending, box-office figures and reviews not found.
A25: FILM-024 | B25: Rangeela | C25: 34950 | D25: 1995 | E25: 1990s | F25: Hindi | G25: Musical | H25: Romantic drama | I25: 150 | J25: Ram Gopal Varma | K25: Jhamu Sughand; Ram Gopal Varma | L25: Varma Creations | M25: Ram Gopal Varma (story, screenplay); Neeraj Vora, Sanjay Chhel (dialogue) | O25: A. R. Rahman | P25: A. R. Rahman | Q25: Mehboob | R25: Munna | T25: Lead | U25: 1 | V25: Black-market cinema ticket seller | W25: Streetwise Mumbai orphan (tapori) | X25: Munna, a streetwise orphan who sells cinema tickets on the black market, has loved his childhood friend Mili for years without saying so. When Mili starts working with the star Raj Kamal, Munna's sense of inferiority deepens as she spends her days with Raj, and every attempt to confess fails. He writes a farewell letter and leaves town, but Mili reads it and, with Raj's help, reaches him. | Y25: Love for Mili | Z25: Cannot confess his love while a film star seems to offer Mili a better life | AA25: Insecure tapori finds the courage to reveal his feelings | AB25: Heroic | AC25: Reunited with Mili | AD25: Urmila Matondkar | AE25: Central | AF25: 9 | AG25: Love triangle | AH25: 4.5 | AM25: INR crore | AN25: Blockbuster | AO25: 4 | AP25: Critical acclaim, with particular praise for A. R. Rahman's soundtrack and Urmila Matondkar's performance. | AQ25: Landmark film credited with a modern sensibility in mid-1990s Hindi cinema; Filmfare wins for Supporting Actor, Music Director, Story, Costume and Choreography; BFJA Best Actor (Hindi) for Aamir Khan. | AR25: SOURCE-030 | AS25: Medium | AT25: Wikipedia's ₹33.4 crore box office (Box Office India) has no nett/gross label and is not entered. Release date 8 September 1995 per Wikipedia; Bollywood Hungama lists 9 August 1995.
A26: FILM-025 | B26: Akele Hum Akele Tum | C26: 35034 | D26: 1995 | E26: 1990s | F26: Hindi | G26: Romantic drama | H26: Musical | I26: 163 | J26: Mansoor Khan | K26: Champak Jain; Ratan Jain | L26: Venus Movies | M26: Mansoor Khan (story, screenplay); Nasir Hussain (dialogue) | N26: Loosely based on Kramer vs. Kramer (1979) | O26: Anu Malik | Q26: Majrooh Sultanpuri | R26: Rohit Kumar | T26: Lead | U26: 1 | V26: Aspiring playback singer | X26: Rohit, an aspiring playback singer, marries Kiran despite her parents' opposition, and her own ambitions recede into housework while his career stalls. Too proud to accept her support, he reads it as pity; she leaves to build a career while he raises their son Sunil alone. She wins custody in court but chooses not to separate father and son, and the family reconciles. | Y26: Success as a singer and a stable family | Z26: Wounded pride as his wife's career overtakes his | AA26: Proud, struggling artist becomes a devoted single father | AB26: Flawed, sympathetic | AC26: Reconciles with Kiran | AD26: Manisha Koirala | AE26: Central | AF26: 9 | AG26: Marriage under strain | AH26: 4.5 | AM26: INR crore | AN26: Successful | AP26: Both leads' performances were acclaimed. | AQ26: Eight Filmfare nominations; soundtrack sold about 2.5 million units, the year's ninth-highest seller. | AR26: SOURCE-031 | AS26: Medium | AT26: Wikipedia's ₹12.37 crore box office (Box Office India) has no nett/gross label and is not entered. Release date 1 December 1995 per Wikipedia; Bollywood Hungama lists 30 November.
A27: FILM-026 | B27: Raja Hindustani | C27: 35384 | D27: 1996 | E27: 1990s | F27: Hindi | G27: Romantic action | I27: 177 | J27: Dharmesh Darshan | K27: Ali Morani; Karim Morani; Bunty Soorma | L27: Cineyug Films | M27: Dharmesh Darshan (story); Robin Bhatt (screenplay); Javed Siddiqui (dialogue) | N27: Inspired by Jab Jab Phool Khile (1965) | O27: Nadeem–Shravan | P27: Surinder Sodhi | Q27: Sameer | R27: Raja Hindustani | T27: Lead | U27: 1 | V27: Taxi driver | W27: Working-class driver in the small hill town of Palankhet | X27: Raja, a proud small-town taxi driver, is hired by the wealthy Aarti, who has come to Palankhet to find traces of her late mother. They fall in love and marry over her father's objections, but her scheming stepmother Shalini convinces each that the other wants out. Separated, Raja takes their infant son, fearing Aarti will keep him away; the deception is exposed and the family reunites. | Y27: Love for Aarti and his self-respect | Z27: The class gap and the stepmother's conspiracy | AA27: Proud working-class lover survives separation and misunderstanding to reunite his family | AB27: Heroic | AC27: Reunited with Aarti and their son | AD27: Karisma Kapoor | AE27: Central | AF27: 10 | AG27: Relationship manipulated by outsiders | AH27: 5.75 | AI27: 43.15 | AJ27: 73.84 | AL27: 76.34 | AM27: INR crore | AN27: All-time blockbuster | AO27: 1 | AP27: Mixed: Anupama Chopra (India Today) found it dated but called Karisma Kapoor its lifeblood; the lead pair's chemistry was praised. | AQ27: Five Filmfare Awards including Best Actor for Aamir Khan; seven Screen Awards; soundtrack sold 11 million copies; fourth-highest domestic grosser of the 1990s. | AR27: SOURCE-032 | AS27: Medium | AT27: All commercial figures from Box Office India via Wikipedia. Overseas gross is not stated separately and is not derived.
A28: FILM-027 | B28: Ishq | C28: 35762 | D28: 1997 | E28: 1990s | F28: Hindi | G28: Romantic comedy | H28: Masala | I28: 168 | J28: Indra Kumar | K28: Gordhan Tanwani | L28: Baba Films | M28: Praful Parekh, Rajeev Kaul (story, screenplay); Tanveer Khan (dialogue) | O28: Anu Malik | P28: Surinder Sodhi | Q28: Rahat Indori; Javed Akhtar | R28: Raja | T28: Co-lead | U28: 1 | V28: Mechanic | W28: Working-class; best friend of the wealthy Ajay | X28: Raja, a working-class mechanic, is best friends with the rich Ajay. Raja falls for Madhu, the heiress whom the fathers want Ajay to marry, while Ajay loves the poor Kajal. Both fathers, contemptuous of the poor, use bribes and fake photographs to turn the couples against each other. Raja exposes the scheme, and Ajay and Madhu reach the departing ship just in time to reunite with their true partners. | Y28: Love for Madhu and loyalty to Ajay | Z28: Two rich fathers' schemes against cross-class marriages | AA28: Comic underdog outwits the fathers | AB28: Heroic | AC28: United with Madhu | AD28: Juhi Chawla; Kajol | AE28: Central | AF28: 8 | AG28: United couple versus external world | AH28: 11 | AI28: 24.93 | AL28: 45.61 | AM28: INR crore | AN28: Commercial success | AO28: 3 | AP28: Mixed to positive; praised for humour, soundtrack and performances, criticised for story and screenplay. | AQ28: Soundtrack sold about 3 million units; remade in Kannada as Snehana Preethina (2007). | AR28: SOURCE-033 | AS28: Medium | AT28: Raja is paired with Madhu (Juhi Chawla) and Ajay (Ajay Devgn) with Kajal (Kajol), per the verbatim plot and cast lines. Commercial figures from Box Office India via Wikipedia.
A29: FILM-028 | B29: Ghulam | C29: 35965 | D29: 1998 | E29: 1990s | F29: Hindi | G29: Action | H29: Crime drama | I29: 162 | J29: Vikram Bhatt | K29: Mukesh Bhatt | L29: Vishesh Films | M29: Anjum Rajabali | N29: Based on On the Waterfront (1954) | O29: Jatin–Lalit | P29: Amar Haldipur | Q29: Indeevar; Nitin Raikwar; Sameer; Vinod Mahendra | R29: Siddharth "Siddhu" Marathe | T29: Lead | U29: 1 | V29: Amateur boxer and small-time hustler | W29: Mumbai neighbourhood youth; younger brother of Jai, right-hand man to the gangster Ronnie | X29: Siddhu, an aimless amateur boxer, drifts on the edges of the gang run by Ronnie, whom his brother Jai serves. He wins a reckless dare against an oncoming train, falls for Alisha, and unwittingly lures her brother Hari, a social worker, into a fatal ambush. Losing Alisha and then Jai, he confronts his family's history of cowardice, testifies against Ronnie and beats him in a public boxing bout. | Y29: Redemption and standing up to Ronnie | Z29: Loyalty to his brother against his conscience | AA29: Aimless hustler becomes the neighbourhood's champion | AB29: Flawed, redeemed | AC29: Defeats Ronnie and rallies the community | AD29: Rani Mukerji | AE29: Secondary | AF29: 5 | AG29: Romance subordinate to another genre | AH29: 7.5 | AM29: INR crore | AN29: Hit | AP29: A commercial success; the train-race sequence won Filmfare's Best Scene of the Year. | AQ29: Aamir Khan's own song 'Aati Kya Khandala' earned him a Filmfare Best Male Playback Singer nomination. | AR29: SOURCE-034; SOURCE-065 | AS29: Medium | AT29: Wikipedia's ₹24.2 crore box office (Box Office India) has no nett/gross label and is not entered. The train dare and Alisha's link to a motorcycle gang come from web search summaries; Wikipedia records a breakup but not whether the couple reunite.
A30: FILM-029 | B30: Sarfarosh | C30: 36280 | D30: 1999 | E30: 1990s | F30: Hindi | G30: Action thriller | H30: Crime | I30: 163 | J30: John Matthew Matthan | K30: John Matthew Matthan | L30: Cinematt Pictures | M30: John Matthew Matthan (story, screenplay); Hriday Lani, Pathik Vats (dialogue) | N30: Original; drew on 1990s state-sponsored terrorism in India | O30: Jatin–Lalit | P30: Sanjoy Chowdhury | Q30: Israr Ansari; Nida Fazli; Sameer; Indeevar | R30: ACP Ajay Singh Rathod | T30: Lead | U30: 1 | V30: Assistant Commissioner of Police leading a special investigation | W30: Middle-class family scarred by terrorism: brother killed, father left mute | X30: Ajay joins the police after terrorists kill his brother and leave his father unable to speak. As an ACP he tracks an arms-smuggling network while resented by the senior Inspector Saleem, and slowly discovers that his admired friend Gulfam Hassan is a Pakistani intelligence agent. Recovering from wounds, he tricks Gulfam into self-incrimination and destroys the network; his reunion with college crush Seema is a warm secondary thread. | Y30: Fight the terrorism that destroyed his family | Z30: Exposing a trusted friend as the mastermind of the arms network | AA30: Idealistic, inexperienced officer learns to pair integrity with cunning | AB30: Heroic | AC30: Dismantles the network and is honoured in Mumbai | AD30: Sonali Bendre | AE30: Secondary | AF30: 3 | AG30: Romance subordinate to another genre | AH30: 8 | AM30: INR crore | AN30: Commercially successful | AP30: Critical acclaim; Filmfare gave four stars for its characterisation and performances, and Naseeruddin Shah was especially praised. | AQ30: National Film Award for Best Popular Film Providing Wholesome Entertainment; screened at IFFI; remade in Kannada and Telugu. Zee Cine Best Actor for Aamir Khan. | AR30: SOURCE-036 | AS30: Medium | AT30: Wikipedia gives box office of ₹33.46 crore citing Box Office India without a nett/gross label; not entered in a commercial column. Budget ₹8 crore.
A31: FILM-030 | B31: Mann | C31: 36350 | D31: 1999 | E31: 1990s | F31: Hindi | G31: Romantic drama | I31: 140 | J31: Indra Kumar | K31: Indra Kumar; Ashok Thakeria | L31: Maruti International | M31: Aatish Kapadia | N31: Inspired by An Affair to Remember (1957) | O31: Sanjeev–Darshan | Q31: Sameer | R31: Dev Karan Singh | T31: Lead | U31: 1 | V31: Painter | W31: Flamboyant, debt-ridden playboy engaged to a tycoon's daughter for money | X31: Dev, a debt-ridden playboy painter engaged to a tycoon's daughter for money, meets Priya on a cruise; she is engaged too. They fall in love and agree to settle their affairs and meet on Valentine's Day in six months. Dev breaks his engagement and works to succeed, but Priya loses her legs in an accident on the way to meet him and hides it; he discovers the truth and marries her. | Y31: Win Priya and become worthy of her | Z31: Believes Priya rejected him, unaware of her accident | AA31: Mercenary casanova becomes a faithful, self-made artist | AB31: Redeemed | AC31: Marries Priya | AD31: Manisha Koirala | AE31: Central | AF31: 10 | AG31: Frictionless idealized romance | AH31: 14 | AM31: INR crore | AN31: Profitable | AP31: Positive reviews; the soundtrack was well received but accused of plagiarising international songs. | AQ31: Soundtrack sold about 2.8 million units, the year's sixth-highest seller. | AR31: SOURCE-037; SOURCE-083 | AS31: Medium | AT31: Wikipedia's ₹35.45 crore box office (Box Office India) has no nett/gross label and is not entered. Dev's broken engagement to Anita Singhania (Deepti Bhatnagar) is recorded here rather than as a Romances row. Indra Kumar's Wikipedia article calls Mann a commercial failure, contradicting the film article's 'profitable'; no verdict entered.
A32: FILM-031 | B32: Earth | C32: 36413 | D32: 1999 | E32: 1990s | F32: Hindi | G32: Period drama | H32: Romance | I32: 101 | J32: Deepa Mehta | K32: Anne Masson; Deepa Mehta | M32: Deepa Mehta | N32: Based on Bapsi Sidhwa's novel Cracking India (first published as Ice Candy Man) | O32: A. R. Rahman | Q32: Javed Akhtar | R32: Dil Navaz, the Ice Candy Man | T32: Co-lead | U32: 1 | V32: Ice-candy seller | W32: Muslim man in 1947 Lahore, part of a mixed-faith circle of friends | X32: Dil Navaz, the Ice Candy Man, belongs to a mixed-faith circle gathered around Shanta, a nanny in Lahore, and competes for her with Hassan, the masseur she plans to marry. The sight of a train of massacred refugees during Partition turns his hurt into communal hatred. He tricks the child Lenny into revealing where Shanta is hiding, delivering her to a mob. | Y32: Win Shanta | Z32: Rejected love and grief poisoned by Partition violence | AA32: Charming suitor becomes a vengeful betrayer | AB32: Becomes antagonist | AC32: Betrays Shanta to a mob | AD32: Nandita Das | AE32: Major | AF32: 7 | AG32: Love triangle | AP32: Strong international reviews (86% on Rotten Tomatoes); Roger Ebert gave three of four stars, and Rediff called it probably the best performance of Aamir Khan's life. | AQ32: India's submission for the Academy Award for Best Foreign Language Film; Filmfare debut awards for Rahul Khanna and Nandita Das. | AR32: SOURCE-035; SOURCE-002 | AS32: Medium | AT32: Indo-Canadian production. Premiered at the Toronto festival on 11 September 1998 (Wikipedia lists it as a 1998 film); released in India as 1947: Earth on 10 September 1999 (Bollywood Hungama), used as the primary release date. Box-office figures not found.
A33: FILM-032 | B33: Mela | C33: 36532 | D33: 2000 | E33: 2000s | F33: Hindi | G33: Masala | H33: Action | I33: 172 | J33: Dharmesh Darshan | K33: Ganesh Jain | L33: Venus Movies | M33: Suneel Darshan (story); Neeraj Vora, Sanjeev Duggal, Robin Bhatt (screenplay); Neeraj Vora, Dharmesh Darshan (dialogue) | N33: Original; the director cited Caravan (1971) as an inspiration | O33: Anu Malik; Rajesh Roshan; Lesle Lewis | P33: Surinder Sodhi | Q33: Dev Kohli; Dharmesh Darshan; Sameer | R33: Kishan Pyare | T33: Lead | U33: 1 | V33: Touring theatre and dance-show performer | W33: Performer in a travelling troupe with his partner Shankar | X33: Kishan, a touring performer, first meets Roopa when she steals his clothes, then fights off goons harassing her and makes her the heroine of his dance show. Roopa feigns love to win his help against the bandit Gujjar Singh, who killed her brother and wants her as his mistress. Heartbroken when she confesses, Kishan leaves, then returns with a police ally to trap and defeat Gujjar. | Y33: Love for Roopa | Z33: The bandit Gujjar Singh and Roopa's strategic deception | AA33: Carefree entertainer becomes a protector | AB33: Heroic | AC33: Defeats Gujjar and ends with Roopa | AD33: Twinkle Khanna | AE33: Major | AF33: 7 | AG33: Relationship damaged by mistrust | AM33: INR crore | AP33: Mixed reviews; Rediff called Aamir Khan the film's saving grace, while song placement and Twinkle Khanna's dubbed voice were criticised. | AR33: SOURCE-038; SOURCE-095 | AS33: Medium | AT33: Wikipedia gives 'est. ₹18 crore' budget and 'est. ₹25 crore' box office (Box Office India) without a nett/gross label; neither is entered because both are estimates and the box-office measure is unlabeled. Aishwarya Rai appears specially as Champakali, paired with Shankar (Faisal Khan). Dharmesh Darshan's Wikipedia article calls Mela a major commercial disaster with highly negative reviews; no verdict entered.
A34: FILM-033 | B34: Lagaan | C34: 37057 | D34: 2001 | E34: 2000s | F34: Hindi | G34: Sports drama | H34: Period epic | I34: 233 | J34: Ashutosh Gowariker | K34: Aamir Khan; Jhamu Sughand (co-producer) | L34: Aamir Khan Productions | M34: Ashutosh Gowariker (story, screenplay); Kumar Dave, Sanjay Dayma (screenplay); K. P. Saxena (Hindi dialogue) | N34: Original | O34: A. R. Rahman | P34: A. R. Rahman | Q34: Javed Akhtar | R34: Bhuvan | T34: Lead | U34: 1 | V34: Farmer | W34: Villager of drought-stricken Champaner in British India, 1893 | X34: Bhuvan, a young farmer in drought-stricken Champaner in 1893, accepts Captain Russell's wager: beat the British at cricket and the tax is lifted, or pay triple. He builds a team across caste and faith, including the untouchable Kachra, is secretly coached by Russell's sister Elizabeth, survives Lakha's betrayal, and hits the winning six on the final ball before marrying Gauri. | Y34: Free his village from crushing taxation | Z34: The cricket wager against Captain Russell | AA34: Defiant farmer becomes a unifying leader | AB34: Heroic | AC34: Wins the match and marries Gauri | AD34: Gracy Singh; Rachel Shelley | AE34: Secondary | AF34: 4 | AG34: Romance subordinate to another genre | AH34: 25 | AI34: 34.31 | AJ34: 55.13 | AK34: 10.84 | AL34: 67.68 | AM34: INR crore | AN34: Hit | AO34: 3 | AP34: Near-universal acclaim: 95% on Rotten Tomatoes and 84 on Metacritic; Roger Ebert gave 3.5 of 4 stars. | AQ34: Nominated for the Academy Award for Best Foreign Language Film; eight Filmfare Awards (including Best Film, Director and Actor) and eight National Film Awards; Locarno audience prize; listed in Channel 4's 50 Films to See Before You Die and Empire's 100 Best Films of World Cinema. | AR34: SOURCE-039; SOURCE-003 | AS34: Medium | AT34: Box Office India via Wikipedia. Worldwide gross ₹65.97 crore for the 2001 release; ₹67.68 crore including the 2003 China release (₹1.71 crore), which is the figure entered. Budget ₹250 million, then the highest for an Indian film.
A35: FILM-034 | B35: Dil Chahta Hai | C35: 37113 | D35: 2001 | E35: 2000s | F35: Hindi | G35: Comedy-drama | H35: Coming-of-age | I35: 185 | J35: Farhan Akhtar | K35: Ritesh Sidhwani | L35: Excel Entertainment | M35: Farhan Akhtar | N35: Original; drawn from Farhan Akhtar's travel diaries with inputs from Kassim Jagmagia | O35: Shankar–Ehsaan–Loy | P35: Shankar–Ehsaan–Loy | Q35: Javed Akhtar | R35: Akash Malhotra | T35: Ensemble lead | U35: 1 | V35: Heir working in his family's Sydney-based business | W35: Wealthy upper-class Mumbai family | X35: Akash is the flippant, wisecracking member of a trio of affluent Mumbai friends who treats love as a joke. Posted to his family's business in Sydney, he spends time with Shalini, who is engaged to his college batchmate Rohit, and realises he loves her only after she returns to India for her wedding. He comes home to declare himself, and she leaves the wedding to be with him. | Y35: A carefree life with his friends, then winning Shalini | Z35: Falls for a woman committed to marry someone else | AA35: Detached cynic who mocks romance becomes emotionally open and vulnerable | AB35: Sympathetic | AC35: United with Shalini and reconciled with his friends | AD35: Preity Zinta | AE35: Major | AF35: 7 | AG35: Friendship to love | AH35: 8 | AJ35: 33.28 | AK35: 6.44 | AL35: 39.72 | AM35: INR crore | AO35: 5 | AP35: Widespread critical acclaim for its fresh narrative, direction, performances and realistic portrayal of urban youth; Saif Ali Khan and Akshaye Khanna particularly praised. | AQ35: Cult status; credited with launching a new wave of urban Hindi cinema. National Film Award for Best Feature Film in Hindi; seven Filmfare Awards including Best Film (Critics). | AR35: SOURCE-040 | AS35: Medium | AT35: Box Office India via Wikipedia: domestic ₹332.8 million, overseas ₹64.4 million, worldwide gross ₹397.2 million. The domestic figure is recorded as gross because domestic plus overseas equals the stated worldwide gross. Annual rank refers to domestic earnings.
A36: FILM-035 | B36: Mangal Pandey: The Rising | C36: 38576 | D36: 2005 | E36: 2000s | F36: Hindi | G36: Historical drama | H36: Biographical | I36: 151 | J36: Ketan Mehta | K36: Aamir Khan; Bobby Bedi; Deepa Sahi | L36: Kaleidoscope Entertainment; TKF Films | M36: Farrukh Dhondy (story, screenplay); Ranjit Kapoor (dialogue) | N36: Life of Mangal Pandey and the start of the 1857 Indian Rebellion | O36: A. R. Rahman | P36: A. R. Rahman | Q36: Javed Akhtar | R36: Mangal Pandey | T36: Lead | U36: 1 | V36: Sepoy in the 34th Bengal Native Infantry | W36: Brahmin soldier in the East India Company army | X36: Mangal Pandey, a loyal Brahmin sepoy who once saved Captain William Gordon's life, befriends the officer across the colonial divide. Rumours that new rifle cartridges are greased with pig and cow fat, together with the Company's wider abuses, turn him against his masters; he ends the friendship and opens fire in mutiny. Court-martialled despite Gordon's defence, he marries Heera in his cell and is hanged, inspiring revolt. | Y36: Religious dignity and resistance to Company rule | Z36: The greased-cartridge crisis and his friendship with Gordon | AA36: Trusting soldier becomes a rebel martyr | AB36: Heroic | AC36: Hanged; his execution sparks wider rebellion | AD36: Rani Mukerji; Ameesha Patel | AE36: Secondary | AF36: 3 | AG36: Romance subordinate to another genre | AH36: 37 | AL36: 52.57 | AM36: INR crore | AN36: Average | AO36: 4 | AP36: Mostly positive (85% of 13 critics on Rotten Tomatoes); Taran Adarsh praised it, while Raja Sen dismissed it as 'cleavage and cliche'. Political parties objected to its depiction of Pandey visiting a brothel. | AQ36: Screened at the Marché du Film, Cannes 2005; marked Aamir Khan's return after four years; Filmfare Best Actor nomination. | AR36: SOURCE-041 | AS36: Medium | AT36: Box Office India via Wikipedia: India ₹39.92 crore (label not stated, not entered) and worldwide ₹52.57 crore. Historian Kim A. Wagner criticised the film's lack of historical evidence. Ameesha Patel's Jwala is paired with Gordon, not Pandey.
A37: FILM-036 | B37: Rang De Basanti | C37: 38743 | D37: 2006 | E37: 2000s | F37: Hindi | G37: Political drama | H37: Coming-of-age | I37: 167 | J37: Rakeysh Omprakash Mehra | K37: Rakeysh Omprakash Mehra; Ronnie Screwvala | L37: Rakeysh Omprakash Mehra Pictures; UTV Motion Pictures | M37: Kamlesh Pandey (story); Rensil D'Silva, Rakeysh Omprakash Mehra (screenplay); Prasoon Joshi (dialogue) | O37: A. R. Rahman | P37: A. R. Rahman | Q37: Prasoon Joshi; Blaaze | R37: Daljit "DJ" Singh | S37: Plays Chandrashekhar Azad in the film-within-the-film | T37: Ensemble lead | U37: 1 | V37: University student | W37: Punjabi family in Delhi; son of Mitro Kaur | X37: DJ is the cynical, fun-loving leader of a group of Delhi students cast by British filmmaker Sue McKinley as revolutionaries, himself playing Chandrashekhar Azad. As rehearsals draw them toward the freedom fighters' ideals, their friend Flight Lieutenant Ajay dies in a MiG-21 crash tied to corruption. The friends turn to violence against those responsible and seize All India Radio to explain themselves; DJ is shot dead. | Y37: Justice for Ajay's death | Z37: Official corruption behind the crash | AA37: Apathetic youth becomes a committed, doomed rebel | AB37: Heroic vigilante | AC37: Shot dead during the radio-station occupation | AD37: Alice Patten; Soha Ali Khan | AE37: Minor | AF37: 3 | AG37: Romance subordinate to another genre | AH37: 25 | AM37: INR crore | AN37: Record opening; major success | AO37: 7 | AP37: Overwhelmingly positive, particularly for the ensemble; the BBC gave five stars. | AQ37: National Film Award for Best Popular Film; BAFTA nomination; India's Academy Award submission; Filmfare Best Film and Best Actor (Critics) for Aamir Khan; credited with inspiring youth activism, the so-called 'RDB effect'. | AR37: SOURCE-042 | AS37: Medium | AT37: Commercial figures conflict within Wikipedia: domestic ₹1.23 billion, worldwide 'more than ₹1.36 billion', and an infobox total of ₹97.90 crore; none is entered. Budget ₹250 million plus ₹100 million marketing. DJ's relationship with Sue rests on one plot sentence.
A38: FILM-037 | B38: Fanaa | C38: 38863 | D38: 2006 | E38: 2000s | F38: Hindi | G38: Romantic thriller | H38: Action | I38: 169 | J38: Kunal Kohli | K38: Aditya Chopra; Yash Chopra | L38: Yash Raj Films | M38: Shibani Bathija (story, screenplay); Kunal Kohli (dialogue) | O38: Jatin–Lalit | P38: Salim–Sulaiman | Q38: Prasoon Joshi | R38: Rehan Qadri | S38: Delhi tour guide by cover; secretly a commander of the militant IKF | T38: Lead | U38: 1 | V38: Tour guide (cover); separatist militant | W38: Grandson of the IKF's leader | X38: Rehan, a charming Delhi tour guide, woos Zooni, a blind Kashmiri woman visiting with friends, and spends her last night in the city with her. He is secretly a separatist militant and fakes his death after a bombing. Seven years later he arrives wounded at the remote home where Zooni, now sighted, is raising their son. Torn between family and cause, he kills her father and is shot by Zooni as he tries to deliver a nuclear trigger. | Y38: The separatist cause; later love for Zooni and their son | Z38: Love for Zooni against loyalty to the militant cause | AA38: Seductive deceiver is torn between family and terror and cannot abandon the cause | AB38: Antagonist | AC38: Shot dead by Zooni | AD38: Kajol; Tabu | AE38: Central | AF38: 9 | AG38: Tragic lovers | AH38: ₹30 crore including marketing | AL38: 105.48 | AM38: INR crore | AN38: Major commercial success | AO38: 6 | AP38: Mixed to positive: praised for the lead performances and visuals, criticised as melodramatic and implausible. | AQ38: Filmfare Best Actress (Kajol), Best Lyricist and Best Male Playback for 'Chand Sifarish'; Kajol's return after five years; banned in Gujarat after Aamir Khan's remarks on the Narmada dam. | AR38: SOURCE-043 | AS38: Medium | AT38: Worldwide gross ₹105.48 crore (Box Office India via Wikipedia). Wikipedia's domestic figures ('₹72.04 million gross, ₹51.87 million nett') appear to use the wrong unit and are not entered. Screen Awards nominated Aamir Khan for Best Villain.
A39: FILM-038 | B39: Taare Zameen Par | C39: 39437 | D39: 2007 | E39: 2000s | F39: Hindi | G39: Drama | H39: Family | I39: 164 | J39: Aamir Khan | K39: Aamir Khan | L39: Aamir Khan Productions; PVR Pictures | M39: Amole Gupte | O39: Shankar–Ehsaan–Loy; Shailendra Barve | P39: Shankar–Ehsaan–Loy | Q39: Prasoon Joshi; Amole Gupte; Shailendra Barve | R39: Ram Shankar Nikumbh | T39: Supporting | V39: Substitute art teacher at a boarding school; formerly taught children with developmental disabilities | X39: Nikumbh, a cheerful substitute art teacher, joins the boarding school where eight-year-old Ishaan is failing and withdrawing. Recognising dyslexia in the boy's artwork and schoolwork, he challenges the father's denial, works patiently with Ishaan on reading and helps him regain his confidence. Having struggled as a child himself, he stays on as a permanent teacher. | Y39: Help Ishaan overcome dyslexia | Z39: The father's and school's dismissal of the diagnosis | AA39: Temporary substitute becomes a transformative mentor | AB39: Heroic | AC39: Ishaan flourishes; Nikumbh joins the permanent staff | AE39: None | AF39: 0 | AG39: No meaningful romance | AH39: 12 | AM39: INR crore | AN39: Commercially successful | AP39: Widespread critical acclaim (93% on Rotten Tomatoes). | AQ39: Aamir Khan's directorial debut; Filmfare Best Film and Best Director; National Film Award for Best Film on Family Welfare; India's Academy Award submission; credited with raising dyslexia awareness and prompting extra exam time for disabled students. | AR39: SOURCE-044; SOURCE-003 | AS39: Medium | AT39: Wikipedia treats Darsheel Safary's Ishaan as the protagonist; Aamir Khan was nominated for Filmfare Best Supporting Actor. Worldwide grosses conflict: ₹88.97 crore (Box Office India), ₹98.48 crore (Bollywood Hungama), ₹107 crore (Box Office Mojo), ₹131 crore (Telegraph) and ₹135 crore (Indian Express); none entered. Amole Gupte was originally to direct.
A40: FILM-039 | B40: Ghajini | C40: 39807 | D40: 2008 | E40: 2000s | F40: Hindi | G40: Action thriller | H40: Romance | I40: 185 | J40: A. R. Murugadoss | K40: Allu Aravind; Tagore B. Madhu; Madhu Mantena | L40: Geetha Arts | M40: A. R. Murugadoss (story, screenplay); Aamir Khan (screenplay); Piyush Mishra (dialogue) | N40: Remake of the Tamil film Ghajini (2005); memory device inspired by Memento (2000) | O40: A. R. Rahman | P40: A. R. Rahman | Q40: Prasoon Joshi | R40: Sanjay Singhania | S40: Poses as a struggling model called Sachin Chauhan | T40: Lead | U40: 1 | V40: Chairman of the telecom company Air Voice | W40: Wealthy second-generation businessman | X40: Sanjay, a telecom tycoon, courts the generous Kalpana while posing as a struggling model called Sachin, and proposes to her. When she rescues girls from a trafficking ring, its boss Ghajini ambushes her and kills her in front of Sanjay, leaving him with anterograde amnesia. Using photographs, notes and tattoos, Sanjay hunts Ghajini down and kills him with the same iron rod. | Y40: Avenge Kalpana's murder | Z40: Hunting her killer while losing his memory every fifteen minutes | AA40: Romantic tycoon becomes a vengeful amnesiac, then finds peace | AB40: Vigilante | AC40: Kills Ghajini; later volunteers at an orphanage named after Kalpana | AD40: Asin; Jiah Khan | AE40: Central | AF40: 8 | AG40: Tragic lovers | AH40: ₹52–65 crore | AI40: 194.58 | AM40: INR crore | AN40: All-time blockbuster | AO40: 1 | AP40: Mixed to positive (54% on Rotten Tomatoes): praised as entertaining and for Aamir Khan's performance, criticised for its length and violence. | AQ40: First Hindi film to cross ₹100 crore nett in India, creating the '100 crore club'; year's best-selling soundtrack; Filmfare Best Female Debut for Asin. | AR40: SOURCE-045 | AS40: Medium | AT40: Wikipedia gives a ₹52 crore budget in the infobox and ₹65 crore in the text; entered as a range. Domestic nett is an estimate from Box Office India. Overseas and worldwide grosses not stated. Sunita (Jiah Khan) is a confidante, not a romantic interest.
A41: FILM-040 | B41: Luck by Chance | C41: 39843 | D41: 2009 | E41: 2000s | F41: Hindi | G41: Drama | I41: 156 | J41: Zoya Akhtar | K41: Farhan Akhtar; Ritesh Sidhwani | L41: Excel Entertainment | M41: Zoya Akhtar; Javed Akhtar | O41: Shankar–Ehsaan–Loy | R41: Himself | T41: Self appearance | X41: Aamir Khan is one of the film-industry figures who appear as themselves in Zoya Akhtar's debut, a drama about newcomers trying to break into Bollywood that shows the industry's lesser-seen side. The sources consulted list him among the guest appearances but do not describe his scene. | AE41: None | AF41: 0 | AG41: No meaningful romance | AH41: 15 | AM41: INR crore | AN41: Moderate commercial success | AP41: Widespread critical acclaim (83% on Rotten Tomatoes). | AQ41: Filmfare Best Debut Director for Zoya Akhtar (tied). | AR41: SOURCE-046 | AS41: Medium | AT41: Budget ₹150 million; box office 'est. ₹290 million' has no nett/gross label and is not entered.
A42: FILM-041 | B42: 3 Idiots | C42: 40172 | D42: 2009 | E42: 2000s | F42: Hindi | G42: Comedy-drama | H42: Coming-of-age | I42: 171 | J42: Rajkumar Hirani | K42: Vidhu Vinod Chopra | L42: Vinod Chopra Films | M42: Rajkumar Hirani; Abhijat Joshi | N42: Adapted from Chetan Bhagat's novel Five Point Someone (story credit disputed) | O42: Shantanu Moitra | P42: Shantanu Moitra; Atul Raninga; Sanjay Wandrekar | Q42: Swanand Kirkire | R42: Ranchhoddas "Rancho" Shamaldas Chanchad | S42: Real identity Phunsukh Wangdu; studied under his employer's son's name | T42: Lead | U42: 1 | V42: Engineering student; later inventor and educator in Ladakh | W42: Gardener's son educated in place of a wealthy family's son | X42: Rancho, a brilliant engineering student who scorns rote learning, befriends Farhan and Raju and clashes with the director Viru 'Virus' Sahastrabuddhe, whose daughter Pia he loves. After a classmate's suicide and a baby delivery Rancho improvises during a blackout, he graduates and vanishes. Years later his friends find him in Ladakh as the celebrated inventor Phunsukh Wangdu, and Pia reunites with him. | Y42: Learning for passion rather than marks | Z42: The rote-learning system embodied by Virus | AA42: Idealistic student becomes an inventor-educator who proves his philosophy | AB42: Heroic | AC42: Revealed as Phunsukh Wangdu and reunited with Pia | AD42: Kareena Kapoor | AE42: Secondary | AF42: 4 | AG42: Romance subordinate to another genre | AH42: 55 | AJ42: 273 | AK42: 186 | AL42: 460 | AM42: INR crore | AN42: All-time blockbuster | AP42: Widespread acclaim in India and abroad (100% of 15 critics on Rotten Tomatoes). | AQ42: Six Filmfare Awards including Best Film and Director; National Film Award for Best Popular Film; highest-grossing Indian film until 2013; Guinness World Records listing; remade in Tamil (Nanban) and Mexico (3 Idiotas); influential on education debates in India, China and South Korea. | AR42: SOURCE-047 | AS42: Medium | AT42: Budget ₹55 crore per Wikipedia; IANS estimated ₹35–45 crore. Overseas gross given as US$30.5 million (₹186 crore).
A43: FILM-042 | B43: Dhobi Ghat | C43: 40564 | D43: 2011 | E43: 2010s | F43: Hindi; English | G43: Drama | H43: Art-house | I43: 102 | J43: Kiran Rao | K43: Kiran Rao; Aamir Khan | L43: Aamir Khan Productions | M43: Kiran Rao | O43: Gustavo Santaolalla | P43: Gustavo Santaolalla | R43: Arun | T43: Ensemble lead | V43: Reclusive painter | W43: Divorced artist whose ex-wife and child live in Australia | X43: Arun, a reclusive divorced painter, has a one-night stand with the banker and photographer Shai and coldly ends it the next morning. In his new flat he finds three video diaries left by the previous tenant, Yasmin, and becomes absorbed in her loneliness and her husband's infidelity. When the last tape suggests she meant to take her own life, he flees the flat and turns her story into a painting. | Y43: Solitude and his art; later understanding Yasmin | Z43: Emotional detachment and fixation on a dead stranger's diaries | AA43: Detached artist is shaken into grief and creation | AB43: Morally ambiguous | AC43: Moves out and completes a painting of Yasmin | AD43: Monica Dogra; Kriti Malhotra | AE43: Minor | AF43: 3 | AG43: Romance subordinate to another genre | AL43: 25.6 | AM43: INR crore | AN43: Average | AP43: Critically well received (70% on Rotten Tomatoes), though some reviewers called it pretentious. | AQ43: Kiran Rao's directorial debut; premiered at the Toronto International Film Festival (September 2010); longlisted for the BAFTA for Best Film Not in the English Language. | AR43: SOURCE-048 | AS43: Medium | AT43: Theatrical release 21 January 2011 after the 2010 Toronto premiere. Wikipedia's ₹40 crore budget conflicts with Aamir Khan's statement that the film made double its cost on a ₹25.6 crore global gross; budget not entered.
A44: FILM-043 | B44: Delhi Belly | C44: 40725 | D44: 2011 | E44: 2010s | F44: English; Hindi | G44: Dark comedy | I44: 100 | J44: Abhinay Deo | K44: Aamir Khan; Kiran Rao; Ronnie Screwvala; Jim Furgele | L44: Aamir Khan Productions; UTV Motion Pictures | M44: Akshat Verma | O44: Ram Sampath | Q44: Amitabh Bhattacharya; Munna Dhiman; Ram Sampath; Akshat Verma; Chetan Shashital | R44: Disco Fighter | T44: Cameo | X44: Aamir Khan appears as 'Disco Fighter' in the song 'I Hate You (Like I Love You)', which plays over the closing credits of this black comedy starring Imran Khan, Vir Das and Kunaal Roy Kapur, which he co-produced. The cameo is outside the story. | AE44: None | AF44: 0 | AG44: No meaningful romance | AH44: 23 | AM44: INR crore | AN44: Super hit | AP44: Widespread acclaim as an original ensemble comedy; the song 'Bhaag D.K. Bose' drew controversy. | AQ44: Filmfare Best Screenplay (Akshat Verma). | AR44: SOURCE-049 | AS44: Medium | AT44: Wikipedia's ₹87.60 crore box office has no nett/gross label and is not entered.
A45: FILM-044 | B45: Talaash: The Answer Lies Within | C45: 41243 | D45: 2012 | E45: 2010s | F45: Hindi | G45: Psychological thriller | H45: Neo-noir | I45: 139 | J45: Reema Kagti | K45: Ritesh Sidhwani; Aamir Khan; Farhan Akhtar | L45: Aamir Khan Productions; Excel Entertainment | M45: Reema Kagti, Zoya Akhtar (story, screenplay); Farhan Akhtar, Anurag Kashyap (dialogue) | O45: Ram Sampath | Q45: Javed Akhtar | R45: Inspector Surjan Singh Shekhawat | T45: Lead | U45: 1 | V45: Senior police inspector in Mumbai | W45: Grieving father whose eight-year-old son Karan drowned | X45: Surjan, a Mumbai inspector sleepless with guilt over his young son's drowning, investigates the death of a film star whose car plunged into the sea. His marriage to Roshni is frozen by grief, and he scorns her visits to a psychic. Helped by the escort Rosie, he uncovers a buried hit-and-run and realises Rosie is the victim's ghost; after cremating her remains, he accepts his son's forgiveness and reconciles with Roshni. | Y45: Solve the case and escape his grief | Z45: Guilt over his son's death against a case that leads into the supernatural | AA45: Rational, grief-frozen detective accepts loss and the inexplicable | AB45: Heroic | AC45: Solves the case and reconciles with Roshni | AD45: Rani Mukerji; Kareena Kapoor | AE45: Secondary | AF45: 4 | AG45: Marriage under strain | AH45: 71 | AI45: 93 | AL45: ₹174–181 crore (estimate) | AM45: INR crore | AN45: Hit | AP45: Positive (81% on Rotten Tomatoes); some critics found the twist derivative of The Sixth Sense. | AQ45: Filmfare nominations for Rani Mukerji and Nawazuddin Siddiqui. | AR45: SOURCE-050 | AS45: Medium | AT45: Box Office India via Wikipedia: domestic nett about ₹93 crore; overseas gross US$8.5 million; worldwide estimated at ₹174.21–180.83 crore, combining domestic nett with overseas gross, so the worldwide figure mixes measures and is entered as text.
A46: FILM-045 | B46: Bombay Talkies | C46: 41397 | D46: 2013 | E46: 2010s | F46: Hindi | G46: Anthology | I46: 128 | J46: Karan Johar; Dibakar Banerjee; Zoya Akhtar; Anurag Kashyap | K46: Ashi Dua | L46: Flying Unicorn Entertainment; Dharma Productions; Dibakar Banerjee Productions; Excel Entertainment; Aamir Khan Productions; Sikhya Entertainment | O46: Amit Trivedi | Q46: Amitabh Bhattacharya; Swanand Kirkire | R46: Himself | T46: Self appearance | X46: Aamir Khan appears as himself among many stars in the song 'Apna Bombay Talkies', which celebrates the centenary of Indian cinema in this four-part anthology by Karan Johar, Dibakar Banerjee, Zoya Akhtar and Anurag Kashyap. The appearance sits outside the anthology's stories. | AE46: None | AF46: 0 | AG46: No meaningful romance | AH46: 30 | AM46: INR crore | AP46: Positive reviews; screened at the 2013 Cannes Film Festival. | AQ46: Made for the 100th year of Indian cinema; Karan Johar's segment received a Queer Palm nomination. | AR46: SOURCE-051 | AS46: Medium | AT46: Wikipedia's estimated earnings of ₹10 crore have no nett/gross label and are not entered.
A47: FILM-046 | B47: Dhoom 3 | C47: 41628 | D47: 2013 | E47: 2010s | F47: Hindi | G47: Action thriller | H47: Heist | I47: 172 | J47: Vijay Krishna Acharya | K47: Aditya Chopra | L47: Yash Raj Films | M47: Vijay Krishna Acharya (screenplay); Aditya Chopra, Vijay Krishna Acharya (story) | O47: Pritam | P47: Julius Packiam | R47: Sahir Khan; Samar Khan | S47: Double role as twin brothers | T47: Lead | U47: 1 | V47: Circus performers and bank robbers | W47: Sons of Iqbal Khan, whose Chicago circus was foreclosed by a bank | X47: As a boy, Sahir watches his father kill himself when the Western Bank of Chicago forecloses on their circus. Grown up, he robs the bank in daring heists with his secret twin Samar, whose existence is hidden. Indian detectives Jai and Ali close in by exploiting Samar's romance with the acrobat Aaliya. Cornered on a dam, Samar will not let go of Sahir's hand, and the brothers fall to their deaths together. | Y47: Revenge on the bank that ruined their father | Z47: Exposure of the twin secret | AA47: Revenge-driven showmen are undone by love and loyalty | AB47: Antagonist-protagonists | AC47: Both die falling from the dam | AD47: Katrina Kaif | AE47: Secondary | AF47: 4 | AG47: Romance subordinate to another genre | AH47: 100 | AI47: 272.5 | AJ47: 372 | AK47: 217.2 | AL47: 556.74 | AM47: INR crore | AN47: All-time blockbuster | AP47: Mixed reviews in India, more favourable abroad (67% on Rotten Tomatoes); critics compared it with The Prestige. | AQ47: First Indian film to gross ₹500 crore worldwide; highest-grossing Indian film on release; Filmfare Best Visual Effects. | AR47: SOURCE-052 | AS47: Medium | AT47: Worldwide gross reported as ₹556.74–558.42 crore; the lower figure is entered. Domestic nett combines ₹261 crore (Hindi) and ₹11.5 crore (Tamil and Telugu). Domestic and overseas grosses (₹372 crore + ₹217.2 crore) do not sum to the worldwide total; figures come from different sources. Samar is Aaliya's partner.
A48: FILM-047 | B48: PK | C48: 41992 | D48: 2014 | E48: 2010s | F48: Hindi | G48: Science-fiction comedy-drama | H48: Religious satire | I48: 152 | J48: Rajkumar Hirani | K48: Vidhu Vinod Chopra; Rajkumar Hirani | L48: Vinod Chopra Films; Rajkumar Hirani Films | M48: Rajkumar Hirani; Abhijat Joshi | O48: Shantanu Moitra; Ajay–Atul; Ankit Tiwari | P48: Sanjay Wandrekar; Atul Raninga | Q48: Swanand Kirkire; Amitabh Varma; Manoj Muntashir | R48: PK | T48: Lead | U48: 1 | V48: Alien researcher stranded on Earth | W48: Humanoid alien with no knowledge of human customs | X48: PK, a humanoid alien on a research mission, is stranded in Rajasthan when a thief steals the remote that summons his spaceship. Told that only God can help, he tries the rituals of every religion and concludes that godmen are dialling a 'wrong number'. With the journalist Jaggu he exposes the godman Tapasvi, who holds his remote, reunites her with her lost love Sarfaraz, suppresses his own love for her and leaves Earth. | Y48: Recover his remote and return home | Z48: Religious exploitation, embodied by the godman Tapasvi | AA48: Naive outsider becomes a social critic who gives up his own love | AB48: Heroic | AC48: Returns home; later leads a new expedition to Earth | AD48: Anushka Sharma | AE48: Secondary | AF48: 4 | AG48: Unrequited love | AH48: 122 | AI48: 340.8 | AJ48: 448.74 | AK48: 304.52 | AL48: 769.89 | AM48: INR crore | AN48: All-time blockbuster | AP48: Widely praised (NDTV five stars; Bollywood Hungama 4.5/5); Hindu nationalist groups protested, and complaints were filed over religious sentiment. | AQ48: Highest-grossing Indian film on release and the first to gross over ₹700 crore and US$100 million worldwide; Filmfare Best Screenplay and Dialogue. | AR48: SOURCE-053 | AS48: Medium | AT48: Box Office India via Wikipedia. Distributor share ₹165 crore and entertainment tax ₹107.94 crore reported separately. Domestic plus overseas gross (₹753.26 crore) does not equal the stated worldwide figure; sources differ.
A49: FILM-048 | B49: Dil Dhadakne Do | C49: 42160 | D49: 2015 | E49: 2010s | F49: Hindi | G49: Family comedy-drama | I49: 173 | J49: Zoya Akhtar | K49: Ritesh Sidhwani; Farhan Akhtar | L49: Excel Entertainment; Junglee Pictures | M49: Reema Kagti, Zoya Akhtar (screenplay); Farhan Akhtar (dialogue) | O49: Shankar–Ehsaan–Loy | Q49: Javed Akhtar | R49: Pluto Mehra | S49: Voices the family dog, who narrates the film | T49: Voice role | X49: Aamir Khan voices Pluto, the Mehra family's dog, who narrates this ensemble comedy-drama about a dysfunctional family and offers wry commentary on human behaviour. He does not appear on screen. Reviewers found that the narration added philosophical depth to Zoya Akhtar's film, whose cast includes Anil Kapoor, Shefali Shah, Priyanka Chopra and Ranveer Singh. | AE49: None | AF49: 0 | AG49: No meaningful romance | AH49: 55 | AM49: INR crore | AN49: Commercial success | AP49: Positive reviews for the cast and direction, with criticism of the length and climax. | AQ49: Filmfare Best Supporting Actor (Anil Kapoor). | AR49: SOURCE-054 | AS49: Medium | AT49: Budget ₹550 million; box office ₹1.44 billion has no nett/gross label and is not entered. Pluto is both a character and the film's narrator.
A50: FILM-049 | B50: Dangal | C50: 42727 | D50: 2016 | E50: 2010s | F50: Hindi | G50: Biographical drama | H50: Sports | I50: 161 | J50: Nitesh Tiwari | K50: Aamir Khan; Kiran Rao; Siddharth Roy Kapur | L50: Aamir Khan Productions; The Walt Disney Company India | M50: Nitesh Tiwari; Piyush Gupta; Shreyas Jain; Nikhil Mehrotra | N50: True story of Mahavir Singh Phogat and his daughters Geeta and Babita | O50: Pritam | P50: Pritam | Q50: Amitabh Bhattacharya | R50: Mahavir Singh Phogat | T50: Lead | U50: 1 | V50: Former national wrestling champion turned coach of his daughters | W50: Rural Haryana (Balali); gave up wrestling for a steady job under family pressure | X50: Mahavir, a former national wrestling champion pushed by his father to take a steady job, wants a son to win the international gold he never could. After four daughters, he recognises Geeta and Babita's strength and trains them with harsh discipline despite village ridicule. When Geeta falters under the national coach's methods, he secretly guides her again and she wins Commonwealth Games gold. | Y50: Win a gold medal for India through his children | Z50: Community ridicule, then a clash with the national academy coach over Geeta's training | AA50: Resigned, disappointed father becomes an obsessive and ultimately vindicated coach | AB50: Heroic; authoritarian | AC50: Geeta wins gold at the 2010 Commonwealth Games | AD50: Sakshi Tanwar; Fatima Sana Shaikh; Sanya Malhotra | AE50: Minor | AF50: 1 | AG50: Established relationship | AH50: 70 | AJ50: 538.03 | AK50: 1512 | AL50: 2024 | AM50: INR crore | AN50: All-time blockbuster; highest-grossing Indian film | AP50: Universal acclaim for its honesty and Aamir Khan's performance; critics debated whether its feminism is undercut by centring the father as the true hero. | AQ50: Filmfare Best Film, Director and Actor; AACTA Best Asian Film; major success in China, where it influenced audience taste and India–China cultural relations; screened in the Indian Parliament. | AR50: SOURCE-055 | AS50: Medium | AT50: The marriage to Daya (Sakshi Tanwar) has minimal narrative weight, so no Romances row. Worldwide totals disagree: Bollywood Hungama ₹1,968 crore; Box Office India ₹2,024 crore (used); Box Office Mojo ₹2,050 crore; Hindustan Times over ₹2,200 crore. Domestic ₹538.03 crore is the final all-language gross; China alone about ₹1,231 crore. The component figures come from different sources and do not sum exactly to the Box Office India total.
A51: FILM-050 | B51: Secret Superstar | C51: 43027 | D51: 2017 | E51: 2010s | F51: Hindi | G51: Musical drama | I51: 150 | J51: Advait Chandan | K51: Aamir Khan; Kiran Rao; Nitin Keni; Akash Chawla | L51: Aamir Khan Productions; Zee Studios | M51: Advait Chandan | O51: Amit Trivedi | Q51: Kausar Munir | R51: Shakti Kumar | T51: Supporting | V51: Flamboyant Mumbai music director | W51: Talented but pretentious industry figure going through a divorce | X51: Shakti Kumar, a talented but pretentious music director in the middle of a divorce, discovers the teenage singer Insia through her YouTube channel and brings her to Mumbai to record. His slapstick vanity gradually gives way to genuine mentorship, and he publicly acknowledges her achievement at an awards ceremony. | Y51: Revive his flagging career | Z51: His ego and scandal-prone reputation | AA51: Self-absorbed has-been becomes a supportive mentor | AB51: Comic, redeemed | AC51: Champions Insia's success | AD51: Zaira Wasim | AE51: None | AF51: 0 | AG51: No meaningful romance | AH51: 15 | AI51: 64 | AJ51: 90 | AL51: 905.7 | AM51: INR crore | AN51: Blockbuster | AP51: Strongly positive (92% on Rotten Tomatoes); Aamir Khan's comic performance was singled out. | AQ51: Filmfare Best Actress (Critics) for Zaira Wasim and Best Supporting Actress for Meher Vij; one of the most profitable Indian films; the second-highest-grossing non-English foreign film in China at the time. | AR51: SOURCE-056 | AS51: Medium | AT51: Worldwide estimates range from ₹858.43 crore to ₹966 crore; ₹905.7 crore (US$154 million) is entered as the most specific figure. China gross about ₹751 crore; other overseas ₹65 crore. Aamir Khan received a Filmfare Best Supporting Actor nomination.
A52: FILM-051 | B52: Thugs of Hindostan | C52: 43412 | D52: 2018 | E52: 2010s | F52: Hindi | G52: Period action adventure | I52: 166 | J52: Vijay Krishna Acharya | K52: Aditya Chopra | L52: Yash Raj Films | M52: Vijay Krishna Acharya | N52: Original story set against historical events; not based on Confessions of a Thug | O52: Ajay–Atul | P52: John Stewart Eduri | Q52: Amitabh Bhattacharya | R52: Firangi Mallah | T52: Co-lead | U52: 2 | V52: Con man and East India Company informer | W52: Small-time thug from Awadh | X52: Firangi, a slippery con man from Awadh, infiltrates Khudabaksh's rebel thugs as an informer for the East India Company's John Clive. He double-crosses both sides for money, but loyalty to the rebels grows on him: he saves Khudabaksh from a fall and takes a bullet for the warrior Zafira. After helping defeat Clive, he steals a ship and sails off with the dancer Suraiyya and his friend Shanichar. | Y52: Money | Z52: Divided loyalty between the Company and the rebels | AA52: Mercenary trickster becomes a reluctant ally of the rebellion | AB52: Rogue | AC52: Escapes by ship with Suraiyya and Shanichar | AD52: Katrina Kaif; Fatima Sana Shaikh | AE52: Minor | AF52: 2 | AG52: Romance subordinate to another genre | AH52: ₹200–300 crore | AI52: 151.19 | AJ52: 193.83 | AK52: 134.21 | AL52: ₹322–335 crore | AM52: INR crore | AN52: Commercial failure after a record opening | AP52: Generally negative in India, faulting direction, screenplay and length; more favourable overseas. | AQ52: Record opening day for a Hindi film (₹52.25 crore nett). | AR52: SOURCE-057 | AS52: Medium | AT52: Budget estimates: ₹200 crore (NDTV, Zee Business), ₹220 crore (Bollywood Hungama), ₹300 crore (Hindustan Times, News18). Worldwide estimates ₹322.07 crore and ₹335 crore. Second-billed after Amitabh Bachchan. Firangi's flirtation with Suraiyya (Katrina Kaif) and his bond with Zafira (Fatima Sana Shaikh) are too thinly documented for Romances rows.
A53: FILM-052 | B53: Koi Jaane Na | C53: 44288 | D53: 2021 | E53: 2020s | F53: Hindi | G53: Psychological thriller | I53: 139 | J53: Amin Hajee | K53: Bhushan Kumar; Krishan Kumar; Amin Hajee | L53: T-Series; Amin Hajee Film Company | M53: Amin Hajee | O53: Tanishk Bagchi; Amaal Mallik; Rochak Kohli; Vikram Negi | Q53: Amitabh Bhattacharya; Kumaar; Manoj Muntashir | R53: Himself | T53: Self appearance | X53: Aamir Khan makes a special appearance in the song 'Har Funn Maula' with Elli AvrRam in this psychological thriller starring Kunal Kapoor and Amyra Dastur. Wikipedia's filmography credits him as himself; the song has no bearing on the plot, which stars Kunal Kapoor and Amyra Dastur. | AE53: None | AF53: 0 | AG53: No meaningful romance | AR53: SOURCE-058; SOURCE-001 | AS53: Medium | AT53: No box-office, reception or award data found.
A54: FILM-053 | B54: Laal Singh Chaddha | C54: 44784 | D54: 2022 | E54: 2020s | F54: Hindi | G54: Comedy-drama | I54: 159 | J54: Advait Chandan | K54: Aamir Khan; Kiran Rao; Jyoti Deshpande; Ajit Andhare | L54: Aamir Khan Productions; Viacom18 Studios; Paramount Pictures | M54: Atul Kulkarni | N54: Adaptation of Forrest Gump (1994), based on Winston Groom's novel | O54: Pritam | P54: Tanuj Tiku | Q54: Amitabh Bhattacharya | R54: Laal Singh Chaddha | S54: Also plays his ancestors Veer, Jagan and Manav Singh Chaddha | T54: Lead | U54: 1 | V54: Soldier, later undergarment entrepreneur | W54: Sikh family from a village near Pathankot; raised by a devoted mother | X54: Laal, a kind-hearted Sikh boy with a low IQ and leg braces, discovers he can run and believes, as his mother taught him, that he can achieve anything. His life crosses decades of Indian history: army service in the Kargil War, a Vir Chakra, friendship with Bala and a successful business. Throughout, he loves his childhood friend Rupa, who chases fame through troubled relationships, until she returns ill and they marry before her death. | Y54: Love for Rupa and his mother's faith in him | Z54: Rupa repeatedly leaves him for a different life | AA54: Bullied child becomes soldier, entrepreneur, husband and father | AB54: Heroic | AC54: Marries Rupa and raises their son Aman | AD54: Kareena Kapoor; Mona Singh | AE54: Central | AF54: 8 | AG54: Unrequited love | AH54: 275 | AJ54: 71.1 | AK54: 60.93 | AL54: 132.03 | AM54: INR crore | AN54: Disaster | AP54: Mixed (69% on Rotten Tomatoes, 46 on Metacritic): praised for its adaptation and music, criticised for pacing, length and Aamir Khan's performance. | AQ54: Ten Filmfare nominations including Best Actress for Kareena Kapoor; strong global Netflix viewing; the target of a boycott campaign before release. | AR54: SOURCE-059 | AS54: Medium | AT54: Box Office India via Wikipedia; the domestic figure is recorded as gross because domestic plus overseas equals the stated worldwide gross. The Indian Express estimated losses of ₹100 crore.
A55: FILM-054 | B55: Salaam Venky | C55: 44904 | D55: 2022 | E55: 2020s | F55: Hindi | G55: Drama | I55: 136 | J55: Revathi | K55: Suraj Singh; Shraddha Agrawal | L55: Connekkt Media; Blive Productions; RTake Studios | M55: Shrikant Murthy (story); Sammeer Arora (screenplay); Kausar Munir (dialogue) | N55: Based on the true story of Kolavennu Venkatesh and Shrikant Murthy's novel The Last Hurrah | O55: Mithoon | Q55: Mithoon; Sandeep Shrivastava; Kausar Munir | R55: Sujata's illusion | T55: Cameo | X55: Aamir Khan makes a cameo as an illusion seen by Sujata, the mother played by Kajol, in this drama based on the true story of Kolavennu Venkatesh and his mother. The sources consulted do not describe the length or content of the scene. | AE55: None | AF55: 0 | AG55: No meaningful romance | AM55: INR crore | AP55: Mixed: 25% of eight critics on Rotten Tomatoes, though The Times of India gave four stars. | AR55: SOURCE-060 | AS55: Medium | AT55: Bollywood Hungama's ₹1.99 crore box office has no nett/gross label and is not entered.
A56: FILM-055 | B56: Sitaare Zameen Par | C56: 45828 | D56: 2025 | E56: 2020s | F56: Hindi | G56: Sports comedy-drama | I56: 158 | J56: R. S. Prasanna | K56: Aamir Khan; Aparna Purohit | L56: Aamir Khan Productions | M56: Divy Nidhi Sharma | N56: Official remake of the Spanish film Campeones (Champions, 2018) | O56: Shankar–Ehsaan–Loy | P56: Ram Sampath | Q56: Amitabh Bhattacharya | R56: Gulshan Arora | T56: Lead | U56: 1 | V56: Assistant basketball coach | W56: Lives with his mother Preeto; married to Sunita | X56: Gulshan, an arrogant, disillusioned assistant basketball coach, is sentenced to community service for drunk driving: he must train a team of intellectually disabled players. Impatient and condescending at first, he slowly learns each player's struggles and strengths, helps Guddu overcome his fear of bathing, confronts his own phobia and comes to see the team as his teachers, while accepting the fatherhood he had resisted. | Y56: Complete a court-ordered sentence; later his team's success | Z56: His own prejudice and impatience toward his players | AA56: Arrogant, self-centred coach becomes humble and emotionally open | AB56: Flawed, redeemed | AC56: Transformed by the team and ready to become a father | AD56: Genelia Deshmukh | AE56: Secondary | AF56: 3 | AG56: Marriage under strain | AH56: 122 | AM56: INR crore | AN56: Hit | AP56: Positive reviews (63% on Rotten Tomatoes) for Aamir Khan's committed performance and its warmth, with criticism that it is preachy and less affecting than Taare Zameen Par. | AQ56: Released with closed captions, audio description and Indian Sign Language together; after its theatrical run it was released on YouTube for ₹100 in India instead of going straight to a streaming service. | AR56: SOURCE-061 | AS56: Medium | AT56: Wikipedia's 'est. ₹266.49 crore' box office is not labelled worldwide, gross or nett in the source summary and is not entered. Reported as the seventh-highest-grossing Hindi film of 2025. Awards not listed on the page as of the research date.
A57: FILM-056 | B57: Coolie | C57: 45883 | D57: 2025 | E57: 2020s | F57: Tamil | G57: Action thriller | I57: 170 | J57: Lokesh Kanagaraj | K57: Kalanithi Maran | L57: Sun Pictures | M57: Lokesh Kanagaraj; Chandhru Anbazhagan | O57: Anirudh Ravichander | P57: Anirudh Ravichander | R57: Dahaa | T57: Cameo | V57: Leader of a global crime syndicate | X57: In his first Tamil film, Aamir Khan makes a cameo as Dahaa, revealed as the leader of a global syndicate and the son of the villain Kakkar, in Lokesh Kanagaraj's Rajinikanth action thriller. He has said he accepted the part without reading the script because he admires Rajinikanth. The sources do not describe the cameo's length or reception. | AE57: None | AF57: 0 | AG57: No meaningful romance | AH57: ₹350–400 crore | AL57: ₹514–675 crore | AM57: INR crore | AN57: Commercially successful | AP57: Mixed reviews (63% on Rotten Tomatoes); Rajinikanth and the action were praised, the narrative less so. | AR57: SOURCE-062; SOURCE-001 | AS57: Low | AT57: Budget and worldwide-gross estimates vary widely and are entered as ranges. Released with Telugu, Hindi and Kannada dubs. Wikipedia's filmography describes the role as a special appearance.
A58: FILM-057 | B58: Happy Patel: Khatarnak Jasoos | C58: 46038 | D58: 2026 | E58: 2020s | F58: Hindi | G58: Spy comedy | J58: Vir Das; Kavi Shastri | K58: Aamir Khan; Aparna Purohit; Vir Das; Kavi Shastri | L58: Aamir Khan Productions | R58: Jimmy Mario | T58: Cameo | X58: Aamir Khan makes a cameo as Jimmy Mario in this spy comedy directed by and starring Vir Das, which he also produced. The sources consulted give the character's name but not the length or content of his scenes. Vir Das plays the title role opposite Mithila Palkar, with Mona Singh and Sharib Hashmi in support. | AE58: None | AF58: 0 | AG58: No meaningful romance | AM58: INR crore | AP58: Mixed (45% of 11 critics on Rotten Tomatoes): called messy and unfocused by some, chaotic fun by others. | AR58: SOURCE-063; SOURCE-001 | AS58: Medium | AT58: Wikipedia's ₹6.84 crore box office has no nett/gross label and is not entered. Runtime, writers and composers not captured.

Sheet Romances
A1: Pairing ID | B1: Film ID | C1: Film | D1: Release Year | E1: Actor’s Character | F1: Actress | G1: Actress’s Character | H1: Actress Role Prominence | I1: Principal Female Lead | J1: Relationship Category | K1: Initial Relationship | L1: How They Meet | M1: Who Initiates | N1: Courtship Pattern | O1: Emotional Dynamic | P1: Pair’s Principal Conflict | Q1: Pair Friction Score | R1: Pair Friction Explanation | S1: External Opposition Score | T1: External Opposition Source | U1: External Opposition Explanation | V1: Lover-Boy Score | W1: Lover-Boy Explanation | X1: Romance Centrality Score | Y1: Relationship Health Score | Z1: Mutuality Score | AA1: Female Agency Score | AB1: Chemistry Score | AC1: Chemistry Explanation | AD1: Playful Banter | AE1: Serious Conflict | AF1: Jealousy or Possessiveness | AG1: Deception or Mistaken Identity | AH1: Separation or Estrangement | AI1: Sacrifice | AJ1: Couple Functions as Team | AK1: Romantic Transformation of Actor’s Character | AL1: Transformation of Female Character | AM1: Relationship Outcome | AN1: Marriage or Long-Term Union | AO1: Happy, Tragic or Unresolved Ending | AP1: Major Romantic Songs | AQ1: Relationship Analysis | AR1: Contemporary Critical Reading | AS1: Source IDs | AT1: Confidence Grade
A2: PAIR-001 | B2: FILM-004 | C2: Qayamat Se Qayamat Tak | D2: 1988 | E2: Rajveer "Raj" Singh | F2: Juhi Chawla | G2: Rashmi Singh | H2: Female lead | I2: Yes | J2: Tragic lovers | K2: Strangers from feuding Rajput families | L2: Raj gatecrashes Rashmi's birthday party posing as Roop Singh, the suitor her father favours; they meet again on a holiday trip. | M2: Raj | N2: Chance holiday reunion grows into open courtship, then secret contact at home and elopement. | O2: Youthful, idealistic and mutual devotion | P2: Rashmi's shock on learning that Raj's father killed her uncle; otherwise the couple is aligned. | Q2: 2 | R2: Only a brief rupture when the family history surfaces and his early disguise; the lovers never turn against each other. | S2: 10 | T2: Family | U2: Rashmi's father arranges her marriage, threatens to kill Raj, feigns acceptance and sends assassins whose bullets kill her. | V2: 10 | W2: Romance is Raj's entire motivation; courtship, rebellion, sacrifice and a death for love, in the debut role that defined Aamir Khan's romantic image. | X2: 10 | Y2: 8 | Z2: 9 | AA2: 5 | AB2: 9 | AC2: The pairing launched Juhi Chawla and Aamir Khan as a hit screen couple, reunited in several later films; the lead performances and songs remain the film's most remembered element. | AD2: Yes | AE2: Partial | AF2: No | AG2: Yes | AH2: Yes | AI2: Yes | AJ2: Yes | AK2: Obedient son becomes a rebel who rejects his family's honour code for love. | AL2: Sheltered daughter defies her father, breaks an arranged engagement and elopes. | AM2: Rashmi is shot by killers hired by her father; Raj kills himself beside her as both families arrive. | AN2: No | AO2: Tragic | AP2: Ae Mere Humsafar; Akele Hain To Kya Gham Hai; Gazab Ka Hai Din | AQ2: The film's romance is almost frictionless inside the couple: nearly all conflict comes from the inherited feud, which makes QSQT the purest example of external opposition in the filmography. Raj's disguise at the party is a genre flourish rather than manipulation, and Rashmi's decision to leave home gives her real, if limited, agency. The tragedy indicts patriarchal honour rather than the lovers, establishing the template of young couple versus family that runs through Aamir Khan's early career. | AR2: Framed in 1988 as wholesome, family-friendly romance. A modern reading still finds the relationship healthy and consensual; the violence belongs to the fathers, making the film an early mainstream critique of honour-based control, though Rashmi's choices are largely reactive to men's decisions. | AS2: SOURCE-007 | AT2: Medium
A3: PAIR-002 | B3: FILM-005 | C3: Raakh | D3: 1989 | E3: Amir Hussein | F3: Supriya Pathak | G3: Neeta | H3: Female lead | I3: Yes | J3: Romance subordinate to another genre | K3: Existing attachment between a young man and an older, more pragmatic woman | M3: Unclear | N3: Not shown as a courtship; an established but mismatched attachment. | O3: His idealistic intensity against her pragmatism | P3: She likes him but does not share his plans for a future together; after the assault she chooses to rebuild her life rather than follow his revenge. | Q3: 4 | R3: Real but quiet incompatibility of outlook; no hostility between them. | S3: 9 | T3: Crime; Villain | U3: The crime boss Hassan Karmali rapes Neeta while Amir is forced to watch; the violence and its aftermath end any shared future. | V3: 3 | W3: Love is the trigger for the plot, but Amir's identity is organised around revenge, not courtship or devotion. | X3: 4 | Y3: 5 | Z3: 4 | AA3: 6 | AC3: Not scored: no fetched source evaluates the pairing. | AD3: Unclear | AE3: Partial | AF3: Unclear | AG3: Unclear | AH3: Yes | AI3: No | AJ3: No | AK3: The assault turns his love into a revenge obsession that consumes him. | AL3: A survivor who refuses to be defined by the assault and slowly rebuilds her life. | AM3: They go separate ways: Neeta reconstructs her life while Amir ends on death row. | AN3: No | AO3: Tragic | AQ3: Raakh inverts the romantic template Aamir Khan established the same year. The relationship is already unequal before the crime, and the woman's response to violence is to reclaim her own life rather than wait for rescue. The hero's revenge is presented as corrosive rather than redemptive, so the romance functions as an origin wound instead of a goal, giving the film a very low lover-boy score despite high external opposition. | AR3: Received as a stylish, bleak crime film. A modern reading values Neeta's autonomy, while noting that the assault still serves mainly as motivation for the male protagonist's story. | AS3: SOURCE-008 | AT3: Low
A4: PAIR-003 | B4: FILM-006 | C4: Love Love Love | D4: 1989 | E4: Amit Verma | F4: Juhi Chawla | G4: Reema Goswami | H4: Female lead | I4: Yes | J4: United couple versus external world | K4: Schoolmates from different classes | L4: They study at the same school. | M4: Unclear | N4: A school romance that becomes serious before a violent rival intervenes. | O4: Mutual devotion under threat | P4: None directly; the separation is forced by threats against his family. | Q4: 1 | R4: No documented conflict between the lovers; they part only under coercion. | S4: 9 | T4: Villain; Class | U4: Vicky's obsession with Reema, threats to kill Amit's family, the class gap and an assassination attempt on Amit. | V4: 8 | W4: Amit is defined by his love for Reema and his persistence through humiliation and danger; action set pieces share the focus. | X4: 9 | Y4: 8 | Z4: 8 | AA4: 5 | AB4: 6 | AC4: Sold on the success of the pair's debut; the fetched source says viewers appreciated the film though it fell short of expectations. | AD4: Unclear | AE4: No | AF4: Unclear | AG4: Unclear | AH4: Yes | AI4: Yes | AJ4: Yes | AK4: A humiliated poor student learns to stand up to power for the woman he loves. | AL4: Reema moves from obedience to fleeing her own engagement party with Amit. | AM4: The couple escape and are reunited after Reema's father kills Vicky and his father. | AN4: Unclear | AO4: Happy | AQ4: Love Love Love repeats the QSQT structure of a mutually devoted young couple against outside power, but moves the threat from family honour to a rich, violent rival and his father. The lovers never turn on each other, and the resolution comes from a patriarch's intervention rather than the couple's own action, which caps Reema's agency. | AR4: Framed as a crowd-pleasing romance with action. A modern reading sees the rival's obsession and the use of threats as the film's real subject, resolved through vigilante killing rather than any institutional remedy. | AS4: SOURCE-009 | AT4: Medium
A5: PAIR-004 | B5: FILM-008 | C5: Tum Mere Ho | D5: 1990 | E5: Shiva | F5: Juhi Chawla | G5: Paro | H5: Female lead | I5: Yes | J5: Forbidden love | K5: Strangers from different social worlds | L5: Shiva's snake-charmer's music enchants Paro at a fair. | M5: Mutual | N5: Fairground enchantment grows into mutual love against her family's wishes. | O5: Fairy-tale, mutual devotion | P5: None documented between the lovers. | Q5: 1 | R5: The sources record no disagreement between Shiva and Paro. | S5: 9 | T5: Family; Community; Other | U5: Paro's father sends men to kill Shiva; she is bound by the custom imposed on child widows; a vengeful serpent tries to kill her. | V5: 8 | W5: Shiva's actions after meeting Paro are driven by love for her, though the supernatural revenge plot competes for focus. | X5: 8 | Y5: 7 | Z5: 8 | AA5: 3 | AC5: Not scored: the sources discuss the film's camp appeal, not the pairing. | AD5: Unclear | AE5: No | AF5: Unclear | AG5: Unclear | AH5: Partial | AI5: Unclear | AJ5: Unclear | AK5: Shiva's love for Paro draws him into the confrontation with the serpent that defines his destiny. | AL5: Not documented; Paro is chiefly the object of the curse and the custom. | AM5: Shiva forces the serpent to lift her curse; the sources imply but do not state that the lovers are united. | AN5: Unclear | AP5: Tum Mere Ho | AQ5: The romance sits inside a supernatural revenge plot but is structurally another family-opposition story. Its unusual element is the child-widow custom, which makes the obstacle social as well as paternal; one reviewer reads the snake mythology as a vehicle for resolving that patriarchal problem. Paro has little agency in the documented plot. | AR5: Treated at release as a fantasy potboiler and later as camp. A modern reading notes the film's engagement with widowhood customs, but the heroine remains largely passive. | AS5: SOURCE-012; SOURCE-013 | AT5: Low
A6: PAIR-005 | B6: FILM-009 | C6: Dil | D6: 1990 | E6: Raja Prasad | F6: Madhuri Dixit | G6: Madhu Mehra | H6: Female lead | I6: Yes | J6: Rivals to lovers | K6: College adversaries divided by class and family greed | L6: At college, where Raja fools the arrogant Madhu by pretending to be blind and mocks her when she discovers the trick. | M6: Mutual, after the college retreat | N6: A prank war escalates to a false accusation and a confrontation, then sudden mutual love and a secret marriage. | O6: Combative rivalry turning into fierce loyalty | P6: Humiliating pranks, Madhu's false accusation that Raja tried to rape her, and later his belief that she abandoned him. | Q6: 6 | R6: Recurring hostile pranks and a serious false accusation precede the romance; the later rupture is engineered by his father, so it is scored mainly as external. | S6: 9 | T6: Family; Class | U6: Hazari's greed and Mehra's class pride; both fathers disown the couple, and Hazari blackmails Madhu into giving up the marriage and lies to Raja. | V6: 8 | W6: After the prankster first half, Raja's life is organised around marrying and providing for Madhu against his father. | X6: 10 | Y6: 5 | Z6: 8 | AA6: 6 | AB6: 8 | AC6: Interpretive: the pairing anchored the year's highest-grossing film, Madhuri Dixit won Filmfare Best Actress and the love songs were major hits. | AD6: Yes | AE6: Yes | AF6: Unclear | AG6: Yes | AH6: Yes | AI6: Yes | AJ6: Yes | AK6: A spoiled prankster becomes a labouring husband who stands up to his father. | AL6: An arrogant heiress becomes a wife who gives up her marriage to pay for his emergency surgery. | AM6: Raja's mother reveals Hazari's blackmail; Raja rushes to the airport, Madhu has not boarded, and they reunite. | AN6: Yes | AO6: Happy | AP6: Mujhe Neend Na Aaye; Hum Pyar Karne Wale; Saansein Teri Chalti Rahe | AQ6: Dil splits into two romances: a hostile prank-war courtship and a devoted marriage under siege from greedy fathers. It scores high on both friction and opposition, unlike the frictionless QSQT. Madhu's sacrifice for Raja's surgery gives her the decisive act of the second half, even though it is coerced by his father. | AR6: Framed in 1990 as spirited romance and melodrama. A modern reading finds the false rape accusation used as a romantic turning point deeply troubling, and the pranks that humiliate Madhu are presented as flirtation. | AS6: SOURCE-014 | AT6: Medium
A7: PAIR-006 | B7: FILM-010 | C7: Deewana Mujh Sa Nahin | D7: 1990 | E7: Ajay Sharma | F7: Madhuri Dixit | G7: Anita | H7: Female lead | I7: Yes | J7: Obsessive pursuit | K7: Colleagues and friends at a modelling agency | L7: They work at the same modelling agency. | M7: Ajay | N7: One-sided: he assumes she loves him and keeps planning their marriage after her engagement to another man. | O7: Fixation against friendly refusal | P7: Anita regards Ajay only as a friend and has to act to stop his obsession. | Q7: 7 | R7: Sustained refusal and her efforts to halt his fixation amount to a serious rupture, even though the film treats it sympathetically. | S7: 4 | T7: Existing relationship | U7: Her engagement to Vikram, who is eventually shown not to love her. | V7: 6 | W7: Framed as a devoted 'deewana', but the role is an obsessive pursuer rather than a reciprocated romantic hero. | X7: 9 | Y7: 3 | Z7: 3 | AA7: 5 | AC7: Not scored: no fetched source evaluates the pairing. | AD7: Unclear | AE7: Yes | AF7: Unclear | AG7: Unclear | AH7: Partial | AI7: Unclear | AJ7: No | AK7: His persistence is ultimately validated rather than corrected. | AL7: Anita moves from rejecting Ajay to accepting him after learning that Vikram does not love her. | AM7: Anita recognises Ajay's sincerity and Vikram's indifference; they end together. | AN7: Unclear | AO7: Happy | AQ7: The clearest early example of the obsessive-pursuit pattern in the filmography. Nearly all the tension is between the pair: Ajay refuses to accept her answer, and the plot rewards that refusal by discrediting her fiancé. The low health and mutuality scores reflect the documented premise rather than the film's romantic framing. | AR7: Presented in 1990 as a tale of devoted love. A modern reading sees a narrative that treats disregard for a woman's refusal as proof of true love, a pattern common in Hindi cinema of the period. | AS7: SOURCE-015 | AT7: Low
A8: PAIR-007 | B8: FILM-011 | C8: Jawani Zindabad | D8: 1990 | E8: Shashi Sharma | F8: Farha Naaz | G8: Sugandha Srivastav | H8: Female lead | I8: Yes | J8: Romance subordinate to another genre | K8: Not documented | M8: Unclear | N8: Not documented beyond Shashi marrying her without dowry against his mother's wishes. | O8: Presented as a supportive marriage | P8: None documented. | Q8: 1 | R8: No conflict between the couple is recorded; low score carries Low confidence. | S8: 4 | T8: Family | U8: Shashi's mother opposes a marriage without dowry. | V8: 3 | W8: The marriage expresses his anti-dowry principle; his narrative function is social crusader, not romantic hero. | X8: 3 | Y8: 7 | AC8: Not scored: no fetched source evaluates the pairing. | AD8: Unclear | AE8: No | AF8: Unclear | AG8: No | AH8: Unclear | AI8: Partial | AJ8: Unclear | AK8: The marriage is proof of his vow rather than a turning point. | AL8: Not documented. | AM8: The marriage holds through the fight against his sister's in-laws. | AN8: Yes | AO8: Happy | AP8: Husn Ishq Ki Yeh Kahani; Meri Jaan Jao Na | AQ8: The marriage is an instrument of the film's anti-dowry message: Shashi's refusal to take dowry, over his mother's objection, is the only documented romantic conflict. Mutuality, agency and chemistry are left unscored because the sources describe nothing of Sugandha beyond the marriage. | AR8: Framed as a progressive social message about dowry. A modern reading welcomes the stance but notes that the wife exists mainly to demonstrate the hero's principles. | AS8: SOURCE-016 | AT8: Low
A9: PAIR-008 | B9: FILM-012 | C9: Afsana Pyar Ka | D9: 1991 | E9: Raj | F9: Neelam | G9: Nikita | H9: Female lead | I9: Yes | J9: Forbidden love | K9: College strangers from feuding families, unaware of the feud | L9: At college. | M9: Unclear | N9: Early misunderstandings give way to love and plans to marry. | O9: Mutual | P9: Early misunderstandings. | Q9: 3 | R9: Only initial misunderstandings are documented. | S9: 7 | T9: Family | U9: Both families forbid the match because of a long-standing feud and arrange other marriages. | V9: 8 | W9: A college romantic lead defined by his love for Nikita and willingness to elope. | X9: 9 | Y9: 7 | Z9: 8 | AA9: 5 | AC9: Not scored: no fetched source evaluates the pairing. | AD9: Unclear | AE9: Partial | AF9: Unclear | AG9: Unclear | AH9: Unclear | AI9: Partial | AJ9: Yes | AK9: College romance hardens into defiance of both families. | AL9: Nikita chooses elopement over an arranged match. | AM9: The couple decide to elope; the final outcome is not documented in the sources consulted. | AN9: Unclear | AP9: Nazren Mili; Tip Tip Tip Tip Baarish Shuru Ho Gayi | AQ9: A direct variation on the QSQT template of young lovers against feuding families, complicated by Raj's hidden relationship to the college principal. The documented shape is a mutual romance under strong family opposition; the resolution is unverified. | AR9: Framed conventionally as young love against elders. A modern reading finds a consensual, mutual relationship; details of the heroine's role are too thin to assess. | AS9: SOURCE-017; SOURCE-065 | AT9: Low
A10: PAIR-009 | B10: FILM-013 | C10: Dil Hai Ke Manta Nahin | D10: 1991 | E10: Raghu Jetley | F10: Pooja Bhatt | G10: Pooja Dharamchand | H10: Female lead | I10: Yes | J10: Playful conflict masking attraction | K10: Strangers; he recognises her as a runaway heiress | L10: On a bus, after Pooja escapes her father's yacht to reach her film-star fiancé in Bangalore. | M10: Raghu, through a coercive bargain; the romance becomes mutual | N10: Forced road trip of bickering and dependence that turns into affection. | O10: Sparring and mistrust softening into tenderness | P10: He blackmails her with exposure; later she mistakes his departure to raise money for abandonment. | Q10: 5 | R10: Recurring arguments, an exploitative starting bargain and a serious misunderstanding that sends her back to her fiancé. | S10: 5 | T10: Family; Class; Existing relationship | U10: Her wealthy father opposes her choices, she is engaged to the actor Deepak Kumar, and Raghu's poverty seems to rule out marriage. | V10: 7 | W10: Clearly the romantic hero of a romantic comedy, but he begins as an opportunist chasing a story rather than a devoted lover. | X10: 9 | Y10: 5 | Z10: 7 | AA10: 6 | AB10: 7 | AC10: The film's success was built on the sparring road-trip dynamic, and it boosted newcomer Pooja Bhatt's career; the assessment is interpretive, as the fetched sources do not quote reviews of the pair. | AD10: Yes | AE10: Partial | AF10: Unclear | AG10: Yes | AH10: Yes | AI10: Partial | AJ10: Partial | AK10: From using Pooja for a scoop to protecting her interests and approaching her father honestly. | AL10: From impulsive runaway chasing a celebrity to choosing a partner on character rather than status. | AM10: Her father reveals Raghu's honesty; she abandons the wedding to Deepak Kumar and joins Raghu. | AN10: Yes | AO10: Happy | AP10: Dil Hai Ki Manta Nahin; Tu Pyaar Hai Kisi Aur Ka; Adayein Bhi Hain Mohabbat Bhi Hai | AQ10: This is the pilot's clearest test of the difference between banter and friction. Much of the conflict is comic sparring, but the premise rests on real coercion: Raghu threatens exposure to secure a story. The narrative redeems him through his integrity about money, and Pooja makes the decisive final choice. The couple's obstacles are split between internal mistrust and her father's class expectations, placing the film at moderate levels on both scales. | AR10: Presented in 1991 as a charming adaptation of screwball conventions. A modern reading notes that the blackmail-based meet-cute and the heroine's financial dependence create a power imbalance the film treats as romantic, softened by Raghu's later scruples. | AS10: SOURCE-018 | AT10: Medium
A11: PAIR-010 | B11: FILM-014 | C11: Daulat Ki Jung | D11: 1992 | E11: Rajesh Chaudhry | F11: Juhi Chawla | G11: Asha Agarwal | H11: Female lead | I11: Yes | J11: United couple versus external world | K11: Classmates whose fathers are business rivals | L11: They study in the same college class. | M11: Unclear | N11: A college romance hidden from rival fathers, followed by elopement. | O11: Mutual devotion under pressure | P11: None documented. | Q11: 1 | R11: No conflict between the lovers is recorded. | S11: 7 | T11: Family; Crime | U11: Both fathers clamp down because of their business rivalry; after eloping, the couple are caught up with treasure-hunting criminals. | V11: 7 | W11: An eloping romantic lead, though the second half turns into a treasure-hunt adventure. | X11: 7 | Y11: 8 | Z11: 8 | AA11: 5 | AC11: Not scored: no fetched source evaluates the pairing. | AD11: Unclear | AE11: No | AF11: Unclear | AG11: Unclear | AH11: Yes | AI11: Partial | AJ11: Yes | AK11: A sheltered rich son becomes a fugitive who protects Asha. | AL11: Asha moves from fear of her father to eloping. | AM11: The lovers are united once the criminals are dealt with. | AN11: Unclear | AO11: Happy | AQ11: Another young-couple-versus-fathers romance, here driven by business rivalry rather than honour or class, before the plot shifts genre into a Mackenna's Gold-style adventure. The couple remain aligned throughout; all pressure is external. | AR11: Framed as romantic adventure. A modern reading finds a consensual, mutual relationship with little independent characterisation for the heroine. | AS11: SOURCE-020 | AT11: Low
A12: PAIR-011 | B12: FILM-015 | C12: Jo Jeeta Wohi Sikandar | D12: 1992 | E12: Sanjaylal "Sanju" Sharma | F12: Ayesha Jhulka | G12: Anjali | H12: Female lead | I12: Yes | J12: Friendship to love | K12: Classmates and close friends | L12: Classmates at Model College; she helps him with his training. | M12: Unclear | N12: A long friendship in which she supports him and warns him about Devika. | O12: Steady loyalty on her side against his distraction | P12: Sanju ignores Anjali's warnings and chases Devika. | Q12: 4 | R12: His neglect and pursuit of another woman strain the friendship; no open hostility is documented. | S12: 3 | T12: Other | U12: Sanju's infatuation with the wealthy Devika and the college class rivalry pull him away. | V12: 5 | W12: Sanju is a charming romantic protagonist, but his arc centres on growing up and winning the race. | X12: 4 | Y12: 6 | Z12: 4 | AA12: 5 | AC12: Not scored: no fetched source evaluates the pairing. | AD12: Unclear | AE12: Partial | AF12: Unclear | AG12: No | AH12: Partial | AI12: Unclear | AJ12: Yes | AK12: His humiliation over Devika contrasts his superficial pursuit with Anjali's steady loyalty. | AL12: Not documented. | AM12: Anjali stands by Sanju through his redemption; the sources consulted do not document how the film resolves their romance. | AN12: Unclear | AQ12: The film sets two romances against each other: the loyal classmate who knows who Sanju really is, and the rich outsider he deceives. Anjali's role is supportive rather than self-directed in the documented plot, which keeps mutuality and agency moderate. | AR12: Framed as a nostalgic campus romance. A modern reading notes the familiar pattern of a loyal heroine waiting for the hero to mature. | AS12: SOURCE-021 | AT12: Low
A13: PAIR-012 | B13: FILM-015 | C13: Jo Jeeta Wohi Sikandar | D13: 1992 | E13: Sanjaylal "Sanju" Sharma | F13: Pooja Bedi | G13: Devika | H13: Second female lead | I13: Partial | J13: Relationship damaged by mistrust | K13: Strangers; she is a wealthy Queens' College student | L13: After Devika's falling-out with Shekhar, Sanju puts on a false show of wealth to attract her. | M13: Sanju | N13: Dates built on a pretence of being rich. | O13: Status-driven infatuation | P13: His lie about his wealth. | Q13: 7 | R13: The relationship rests on deception and ends in a public humiliation when she discovers the truth. | S13: 3 | T13: Class | U13: Class snobbery and the rivalry with Rajput College frame and end the relationship. | V13: 4 | W13: Sanju's pursuit is infatuation and social climbing rather than devotion. | X13: 4 | Y13: 2 | Z13: 3 | AA13: 6 | AC13: Not scored: no fetched source evaluates the pairing; Pooja Bedi's performance received a Filmfare supporting nomination. | AD13: Unclear | AE13: Yes | AF13: Partial | AG13: Yes | AH13: Yes | AI13: No | AJ13: No | AK13: The public humiliation shatters his vanity and starts his turn toward responsibility. | AL13: Not documented. | AM13: When Devika learns Sanju is not rich, she dumps him in front of Shekhar's friends. | AN13: No | AQ13: A failed romance that functions as the hero's lesson. The friction score comes from his deception, not her cruelty; her dismissal of him is a response to being lied to. Her independent agenda against Shekhar gives her more agency than most heroines of the period. | AR13: Framed at release as the glamorous wrong choice. A modern reading notes that the film casts the Westernised rich woman as shallow while excusing the hero's lie as youthful folly. | AS13: SOURCE-021 | AT13: Medium
A14: PAIR-013 | B14: FILM-019 | C14: Hum Hain Rahi Pyar Ke | D14: 1993 | E14: Rahul Malhotra | F14: Juhi Chawla | G14: Vyjayanti Iyer | H14: Female lead | I14: Yes | J14: Friendship to love | K14: Strangers | L14: Rahul's nephews and niece befriend Vyjayanti at a carnival after she escapes her father's confinement, and hide her in his house. | M14: Facilitated by the children; the romance becomes mutual | N14: Domestic comedy of hiding and discovery; affection grows as she wins over the children. | O14: Warm and teasing, increasingly tender | P14: Rahul's anger at the deception and Vyjayanti's heartbreak over his engagement to Maya. | Q14: 4 | R14: Anger at being deceived and hurt over his engagement, resolved without lasting hostility. | S14: 6 | T14: Family; Community; Existing relationship | U14: Her father rejects a marriage outside the Iyer community, Rahul is committed to marry Maya, and the Bijlanis sabotage his business in revenge. | V14: 6 | W14: Rahul is a reluctant romantic whose central role is guardian and businessman; the romance grows out of domestic duty. | X14: 8 | Y14: 7 | Z14: 8 | AA14: 7 | AB14: 7 | AC14: Juhi Chawla won Filmfare Best Actress and reviews praised her performance; the film repeated a proven screen pairing. | AD14: Yes | AE14: Partial | AF14: Partial | AG14: Yes | AH14: Partial | AI14: Unclear | AJ14: Partial | AK14: From stern disciplinarian to compassionate partner and father figure. | AL14: A runaway from paternal control finds a chosen family. | AM14: Rahul defends Vyjayanti against insults; her father relents after Natarajan backs the couple, and they marry in a South Indian ceremony. | AN14: Yes | AO14: Happy | AP14: Ghoonghat Ki Aad Se; Yunhi Kat Jayega; Mujhse Mohabbat Ka; Woh Meri Neend Mera Chain | AQ14: The romance is filtered through the children, who engineer the meeting and later disrupt Rahul's engagement. Vyjayanti is the most active heroine of the early phase: she escapes confinement, wins over a hostile household and chooses her own partner. Rahul's role is paternal before it is romantic, which keeps his lover-boy score moderate despite high centrality. | AR14: Framed as warm family comedy. A modern reading finds a respectful, mutual relationship; the heroine's defiance of her father's community rules is presented sympathetically. | AS14: SOURCE-025 | AT14: Medium
A15: PAIR-014 | B15: FILM-021 | C15: Andaz Apna Apna | D15: 1994 | E15: Amar Manohar | F15: Raveena Tandon | G15: Karishma (the secretary posing as the heiress Raveena Bajaj) | H15: Female co-lead | I15: Yes | J15: Romance subordinate to another genre | K15: Strangers; he courts her believing she is the heiress | L15: Amar sets out to woo the heiress Raveena Bajaj, not knowing that the woman presented as Raveena is her secretary Karishma. | M15: Amar | N15: A mercenary courtship built on pretence on both sides that turns into genuine love. | O15: Comic pretence becoming real affection | P15: Mutual deception about identity and Amar's mercenary motive. | Q15: 4 | R15: Both partners deceive each other, but the film treats it as farce; no serious rupture is documented. | S15: 5 | T15: Villain; Other | U15: The rival suitor Prem, the heiress's father's scrutiny, and the villains Teja and Crime Master Gogo. | V15: 4 | W15: Amar begins as a gold-digger; romance is one engine of a comedy of cons rather than his defining identity. | X15: 5 | Y15: 5 | Z15: 6 | AA15: 6 | AC15: Not scored: the sources praise the film's comedy, not the pairing. | AD15: Yes | AE15: No | AF15: Unclear | AG15: Yes | AH15: Unclear | AI15: No | AJ15: Partial | AK15: A gold-digging schemer discovers he loves the woman regardless of her fortune. | AL15: Not documented. | AM15: Ram Gopal Bajaj approves Amar's marriage to the real Karishma. | AN15: Yes | AO15: Happy | AQ15: The identity swap, arranged by the women to test suitors, makes the romance a satire of fortune-hunting: Amar ends up loving the secretary he mistook for money. Friction is performative rather than wounding, and the women's scheme gives them unusual control over the courtship for a 1990s comedy. | AR15: Received first as a failure and later as a cult comedy. A modern reading finds the relationship harmless farce; the heroines are sketched lightly beside the two male leads. | AS15: SOURCE-027; SOURCE-065 | AT15: Low
A16: PAIR-015 | B16: FILM-022 | C16: Baazi | D16: 1995 | E16: Inspector Amar Damjee Rathod | F16: Mamta Kulkarni | G16: Sanjana Roy | H16: Female lead | I16: Yes | J16: Romance subordinate to another genre | K16: Not documented | M16: Unclear | N16: Not documented in plot summaries; the film's soundtrack carries several romantic numbers. | O16: Not documented | P16: None documented. | Q16: 1 | R16: No interpersonal conflict is recorded; Low confidence. | S16: 7 | T16: Villain; Crime | U16: Amar is framed and hunted by Chaubey, and Sanjana, a journalist, is endangered in the hostage siege. | V16: 3 | W16: A cop-avenger role in which romance is peripheral. | X16: 3 | AC16: Not scored: no fetched source evaluates the pairing. | AD16: Unclear | AE16: Unclear | AF16: Unclear | AG16: Unclear | AH16: Unclear | AI16: Unclear | AJ16: Unclear | AK16: Not documented. | AL16: Not documented. | AM16: Not documented in the sources consulted. | AN16: Unclear | AQ16: Sanjana is documented only as a journalist caught in the climactic siege, so most relationship measures are left blank. The row exists because she is the hero's love interest; the scores that are filled reflect the action plot's dangers rather than any known dynamic between the pair. | AR16: Not assessable from the sources consulted. | AS16: SOURCE-028 | AT16: Low
A17: PAIR-016 | B17: FILM-024 | C17: Rangeela | D17: 1995 | E17: Munna | F17: Urmila Matondkar | G17: Mili Joshi | H17: Female lead | I17: Yes | J17: Love triangle | K17: Childhood best friends | L17: They grew up together as best friends. | M17: Munna, though he cannot say it | N17: Years of unspoken love, repeated failed attempts to confess, and finally a farewell letter. | O17: Affectionate friendship shadowed by his insecurity | P17: His failure to confess and jealousy of Raj Kamal; her misreading of his intentions. | Q17: 4 | R17: Misunderstandings and jealous withdrawal rather than hostility. | S17: 3 | T17: Class; Other | U17: The star Raj Kamal's attention and the glamour of film stardom make Munna feel inferior; Raj later helps reunite them. | V17: 9 | W17: Munna's whole arc is his unspoken love and fear of losing Mili. | X17: 9 | Y17: 8 | Z17: 6 | AA17: 7 | AB17: 7 | AC17: Interpretive: the film's acclaim centred on its music and Urmila Matondkar's performance, with the friendship-romance as its emotional core. | AD17: Yes | AE17: Partial | AF17: Yes | AG17: No | AH17: Yes | AI17: Partial | AJ17: No | AK17: An insecure street hustler learns to voice his love instead of retreating. | AL17: Mili rises to film stardom and recognises Munna's love. | AM17: Mili learns of his love from his farewell letter on her film's opening night; with Raj's help she intercepts Munna and they reunite. | AN17: Unclear | AO17: Happy | AQ17: Rangeela shifts the obstacle from family to self-doubt: the rival is a benign star, and the real barrier is Munna's class insecurity. Mili pursues her own career throughout, giving her more agency than most earlier heroines. The high lover-boy score with low opposition shows the two scales working independently. | AR17: Hailed as a modern, stylish romance. A modern reading finds a respectful relationship. | AS17: SOURCE-030 | AT17: Medium
A18: PAIR-017 | B18: FILM-025 | C18: Akele Hum Akele Tum | D18: 1995 | E18: Rohit Kumar | F18: Manisha Koirala | G18: Kiran | H18: Female lead | I18: Yes | J18: Marriage under strain | K18: Strangers who quickly fall in love | M18: Unclear | N18: A quick romance and marriage despite her parents' opposition. | O18: Loving but competitive; his pride against her ambition | P18: His pride and stalled career against her growing career, ending in separation and a custody case. | Q18: 7 | R18: Pride, resentment and separation escalate into a court fight over their son. | S18: 3 | T18: Family | U18: Kiran's parents oppose the marriage; later pressures come mainly from within the couple. | V18: 5 | W18: A romantic husband and devoted father; the role centres on marriage and fatherhood rather than courtship. | X18: 9 | Y18: 5 | Z18: 6 | AA18: 8 | AB18: 7 | AC18: Both leads' performances were acclaimed, and the duet 'Raja Ko Rani Se' became the film's signature song. | AD18: Unclear | AE18: Yes | AF18: Partial | AG18: No | AH18: Yes | AI18: Yes | AJ18: Partial | AK18: A proud husband learns humility through single fatherhood. | AL18: A wife who shelved her ambitions becomes an independent professional, then chooses reconciliation on her terms. | AM18: Kiran wins custody but lets their son stay with Rohit; the couple and their son reconcile. | AN18: Yes | AO18: Happy | AP18: Raja Ko Rani Se; Dil Kehta Hai | AQ18: The first sustained study of marriage in the filmography, and the highest pair-friction score among his happy-ending romances. The conflict is almost entirely internal: male pride against female ambition. Kiran's career choice and her decision over custody give her more narrative power than any earlier heroine, even if the reconciliation restores the family unit. | AR18: Framed as a sympathetic domestic drama. A modern reading credits its attention to a wife's career, while noting that the husband's wounded pride is treated more indulgently than the wife's departure. | AS18: SOURCE-031 | AT18: Medium
A19: PAIR-018 | B19: FILM-026 | C19: Raja Hindustani | D19: 1996 | E19: Raja Hindustani | F19: Karisma Kapoor | G19: Aarti Sehgal | H19: Female lead | I19: Yes | J19: Relationship manipulated by outsiders | K19: A wealthy visitor and the taxi driver she hires | L19: Aarti hires Raja as her driver during a trip to Palankhet to recover memories of her late mother. | M19: Mutual, after an accidental kiss | N19: Road-trip companionship, a much-discussed kiss, and marriage over her father's objection. | O19: Passionate, proud and easily wounded | P19: Misunderstandings planted by her stepmother; Raja's pride leads him to take their infant son. | Q19: 5 | R19: Real mistrust and a drastic act by Raja, though the misunderstandings are engineered by Shalini. | S19: 8 | T19: Family; Class | U19: Aarti's father initially rejects the class-crossing match, and her stepmother Shalini conspires to break the marriage by telling each partner the other wants out. | V19: 9 | W19: Raja is defined by passionate devotion and wounded pride; the role won Aamir Khan Filmfare Best Actor and anchored his biggest 1990s romantic hit. | X19: 10 | Y19: 5 | Z19: 8 | AA19: 5 | AB19: 9 | AC19: The fetched source records that the lead pair's chemistry was praised, and the kiss became one of the film's most discussed elements. | AD19: Yes | AE19: Yes | AF19: Unclear | AG19: Yes | AH19: Yes | AI19: Partial | AJ19: No | AK19: His love survives humiliation and separation, though his pride nearly costs him his family. | AL19: A sheltered heiress chooses a working-class husband and ultimately exposes her stepmother. | AM19: Shalini's deception is exposed and the couple reunite with their son. | AN19: Yes | AO19: Happy | AP19: Pardesi Pardesi; Aaye Ho Meri Zindagi Mein | AQ19: Raja Hindustani is the high point of the class-crossing lover-boy role: a poor, proud man whose devotion is tested less by his wife than by the rich family around her. Internal friction is moderate but consequential, because Raja's pride turns manipulation into the abduction of their child. Aarti's agency is real at the start and the end but largely suspended during the conspiracy. | AR19: Framed as a crowd-pleasing melodrama about love across class. A modern reading questions the romanticising of possessive male pride and the taking of the baby, while noting the film treats the scheming stepmother, not the couple, as the true villain. | AS19: SOURCE-032 | AT19: Medium
A20: PAIR-019 | B20: FILM-027 | C20: Ishq | D20: 1997 | E20: Raja | F20: Juhi Chawla | G20: Madhu Lal | H20: Female co-lead | I20: Yes | J20: United couple versus external world | K20: The heiress meant for Ajay and his poor best friend | M20: Unclear | N20: Cross-class romance pursued against both fathers' schemes. | O20: Comic and devoted | P20: Forged photographs make Madhu believe Raja is involved with Kajal. | Q20: 4 | R20: Mistrust created by the fathers' forgeries, resolved in the climax. | S20: 8 | T20: Family; Class | U20: Madhu's father Harbans Lal and Ajay's father Ranjit Rai use bribery, violence and forged photographs to stop cross-class marriages. | V20: 7 | W20: A comic romantic hero whose screen time is split between romance, slapstick and friendship with Ajay. | X20: 8 | Y20: 7 | Z20: 7 | AA20: 4 | AC20: Not scored: reviews in the fetched source praise the cast generally, not this pairing. | AD20: Yes | AE20: Partial | AF20: Partial | AG20: Yes | AH20: Yes | AI20: Unclear | AJ20: Partial | AK20: Raja's loyalty to Ajay and love for Madhu drive him to outwit both fathers. | AL20: Not documented beyond her reconciliation with Raja. | AM20: Madhu and Ajay reach the departing ship in time; Raja and Madhu reunite. | AN20: Unclear | AO20: Happy | AQ20: Ishq doubles the young-lovers-versus-fathers template into two cross-class couples. External opposition is high and farcical; the couple's own friction comes entirely from the fathers' forgeries. The romance shares focus with comedy and the male friendship, keeping the lover-boy score below the purely romantic roles. | AR20: Framed as broad masala comedy. A modern reading finds the relationship mutual and harmless, though the heroines are secondary to the male leads' antics. | AS20: SOURCE-033 | AT20: Medium
A21: PAIR-020 | B21: FILM-028 | C21: Ghulam | D21: 1998 | E21: Siddharth "Siddhu" Marathe | F21: Rani Mukerji | G21: Alisha Mafatlal | H21: Female lead | I21: Yes | J21: Romance subordinate to another genre | K21: Strangers; she is linked to a local motorcycle gang | L21: Siddhu befriends Alisha, unaware that her brother Hari is a social worker opposing Ronnie. | M21: Unclear | N21: Friendship that develops into love amid neighbourhood rivalries. | O21: Attraction strained by guilt | P21: Siddhu's unwitting role in luring Hari to his death, followed by a breakup. | Q21: 6 | R21: The couple break up after Siddhu unwittingly helps set up her brother's killing. | S21: 7 | T21: Crime; Villain | U21: Ronnie's gang murders Alisha's brother and holds Siddhu's family in its grip. | V21: 5 | W21: The romance humanises Siddhu, but his arc is about guilt, courage and confronting Ronnie. | X21: 5 | Y21: 6 | Z21: 6 | AA21: 5 | AC21: Not scored: no fetched source evaluates the pairing. | AD21: Unclear | AE21: Yes | AF21: Unclear | AG21: Unclear | AH21: Yes | AI21: Unclear | AJ21: Unclear | AK21: Guilt over Hari's death and the loss of Alisha push Siddhu to testify against Ronnie. | AL21: Not documented. | AM21: The couple break up after Hari's death; the sources consulted do not record whether they reunite. | AN21: Unclear | AO21: Unresolved | AQ21: The romance is structurally tied to the crime plot: Siddhu's love for Alisha is what makes Hari's death a moral catastrophe for him. The breakup is caused by his own complicity rather than family disapproval, placing the pairing unusually high on friction for a secondary romance. | AR21: Framed as the emotional stake in an On the Waterfront-style redemption story. A modern reading notes that the heroine's grief chiefly serves the hero's moral awakening. | AS21: SOURCE-034; SOURCE-065 | AT21: Low
A22: PAIR-021 | B22: FILM-029 | C22: Sarfarosh | D22: 1999 | E22: ACP Ajay Singh Rathod | F22: Sonali Bendre | G22: Seema Nagrath | H22: Female lead with limited screen time | I22: Yes | J22: Romance subordinate to another genre | K22: College acquaintances; Ajay had a crush on her in Delhi | L22: They reconnect in Mumbai years after college. | M22: Mutual after the reunion | N22: Low-conflict romance carried mainly by songs between investigation set pieces. | O22: Warm, supportive and uncomplicated | P22: None documented; the danger of his work is the only strain. | Q22: 1 | R22: No meaningful disagreement between the couple is recorded. | S22: 2 | T22: Other | U22: Only the demands and danger of Ajay's counter-terrorism work intrude on the relationship. | V22: 4 | W22: Romance supplies charm and songs, but Ajay's identity is organised around duty and revenge on terrorism. | X22: 3 | Y22: 8 | Z22: 7 | AA22: 4 | AB22: 6 | AC22: Pleasant and song-driven; reviews in the fetched source praise the performances generally without singling out the pair. | AD22: Yes | AE22: No | AF22: No | AG22: No | AH22: No | AI22: No | AJ22: Partial | AK22: Seema offers emotional grounding; the hospital conversation with her triggers the insight that breaks the case. | AL22: Not applicable; her character has little independent arc. | AM22: The couple remains together as Ajay completes his mission. | AN22: Unclear | AO22: Happy | AP22: Is Deewane Ladke Ko; Jo Haal Dil Ka; Yeh Jawani Hadd Kar De | AQ22: A benchmark for secondary romance: warm, mutual and nearly conflict-free, but structurally ornamental. Seema's one plot function, helping Ajay return to the site after his epiphany, keeps her from being purely decorative. The low lover-boy score despite a pleasant romance illustrates why the scale is kept separate from relationship health. | AR22: Framed conventionally as a hero's reward and respite. A modern reading finds nothing coercive, but notes the thinness of the female role typical of late-1990s action thrillers. | AS22: SOURCE-036 | AT22: Medium
A23: PAIR-022 | B23: FILM-030 | C23: Mann | D23: 1999 | E23: Dev Karan Singh | F23: Manisha Koirala | G23: Priya Verma | H23: Female lead | I23: Yes | J23: Frictionless idealized romance | K23: Strangers, each engaged to someone else | L23: On a cruise. | M23: Unclear | N23: A shipboard romance followed by a pact to meet on Valentine's Day in six months after ending their engagements. | O23: Idealised mutual devotion; her self-sacrificing concealment | P23: Priya hides her amputation so as not to burden Dev; he believes she rejected him. | Q23: 3 | R23: Her concealment and his sense of rejection cause a painful but loving misunderstanding. | S23: 7 | T23: Fate; Existing relationship | U23: Both are engaged to others, and a car accident that costs Priya her legs keeps her from the rendezvous. | V23: 9 | W23: Dev's transformation from casanova to faithful artist is driven entirely by his love for Priya. | X23: 10 | Y23: 7 | Z23: 8 | AA23: 5 | AC23: Not scored: the fetched source reports positive reviews without assessing the pairing. | AD23: Unclear | AE23: Partial | AF23: Unclear | AG23: Partial | AH23: Yes | AI23: Yes | AJ23: No | AK23: A debt-ridden casanova breaks a mercenary engagement and earns success through his art. | AL23: After losing her legs, Priya builds an independent life running a music academy. | AM23: Dev recognises the painting he gave her, discovers her disability, assures her of his love, and they marry with Raj's blessing. | AN23: Yes | AO23: Happy | AP23: Chaaha Hai Tujhko; Nasha Yeh Pyar Ka; Kehna Hai Tumse | AQ23: Mann is the purest late-1990s lover-boy vehicle: the man is redeemed by love, the couple never truly quarrel, and the obstacles are prior engagements and fate. Priya's concealment is framed as noble sacrifice, which keeps friction low while producing a long separation. | AR23: Framed as a classic weepie in the An Affair to Remember mould. A modern reading questions the premise that a disabled woman must hide herself to avoid being a burden, even though the hero's unconditional acceptance is presented as the resolution. | AS23: SOURCE-037 | AT23: Medium
A24: PAIR-023 | B24: FILM-031 | C24: Earth | D24: 1999 | E24: Dil Navaz, the Ice Candy Man | F24: Nandita Das | G24: Shanta | H24: Female lead | I24: Yes | J24: Love triangle | K24: Friends in a mixed-faith circle in Lahore | L24: Dil Navaz is part of the group of friends who gather daily around Shanta in a park. | M24: Dil Navaz | N24: Persistent attention within the group; Shanta chooses Hassan and plans to marry him. | O24: Unrequited desire curdling into resentment | P24: Shanta prefers Hassan; Dil Navaz's jealousy grows until he betrays her. | Q24: 9 | R24: Rejected pursuit ends in betrayal: he tricks a child into revealing Shanta's hiding place to a mob. | S24: 9 | T24: War or politics; Religion; Existing relationship | U24: Partition's communal violence tears the friendship circle apart, and Shanta's commitment to Hassan closes the triangle. | V24: 3 | W24: Dil Navaz begins as a charming suitor, but the role becomes a study of jealous, destructive desire rather than romantic heroism. | X24: 7 | Y24: 1 | Z24: 1 | AA24: 6 | AC24: Not scored: reviews praise Aamir Khan's performance but do not assess the pairing. | AD24: Unclear | AE24: Yes | AF24: Yes | AG24: Yes | AH24: Not applicable | AI24: No | AJ24: No | AK24: Rejection and communal grief turn a charming suitor into a betrayer. | AL24: Not documented beyond her choice of Hassan and her abduction. | AM24: Dil Navaz tricks Lenny into revealing Shanta's hiding place, and she is seized by a mob. | AN24: No | AO24: Tragic | AQ24: The most destructive pairing in the filmography and the sharpest inversion of the lover-boy persona. Shanta exercises clear choice, and Dil Navaz converts rejection into violence under cover of communal hatred. Friction and opposition are both extreme, but the decisive act is his, which is why friction is scored as high as the external Partition context. | AR24: Received as a powerful, disturbing Partition film. A modern reading sees an unflinching portrait of male entitlement and of women's bodies becoming targets in communal violence. | AS24: SOURCE-035 | AT24: Medium
A25: PAIR-024 | B25: FILM-032 | C25: Mela | D25: 2000 | E25: Kishan Pyare | F25: Twinkle Khanna | G25: Roopa Singh | H25: Female lead | I25: Yes | J25: Relationship damaged by mistrust | K25: Strangers | L25: Roopa steals Kishan's clothes at a restaurant; he confronts her, then defends her when goons harass her. | M25: Kishan | N25: He makes her the heroine of his dance show; she feigns love to secure his help against Gujjar Singh. | O25: His sincere love against her strategic pretence, becoming mutual | P25: Roopa's deception about her feelings and purpose. | Q25: 6 | R25: Calculated deception and his heartbroken departure mark a serious rupture before reconciliation. | S25: 8 | T25: Villain; Crime | U25: The bandit Gujjar Singh killed Roopa's brother and wants her as his mistress. | V25: 7 | W25: Kishan is a romantic hero, but the second half turns to revenge action. | X25: 7 | Y25: 5 | Z25: 5 | AA25: 7 | AC25: Not scored: reviews criticise Twinkle Khanna's dubbed voice and praise Aamir Khan, but do not assess the pairing. | AD25: Yes | AE25: Yes | AF25: Unclear | AG25: Yes | AH25: Yes | AI25: Unclear | AJ25: Yes | AK25: An easy-going performer becomes a committed protector despite having been used. | AL25: A woman bent on revenge moves from using Kishan to loving him. | AM25: After Gujjar Singh is defeated, Kishan and Roopa end together. | AN25: Unclear | AO25: Happy | AQ25: Mela reverses the usual deception pattern: the heroine manipulates the hero, for a revenge goal the film endorses. Her agency is therefore high, while mutuality and health are moderate until the truth comes out. The villain supplies extreme external danger. | AR25: Framed as masala entertainment. A modern reading finds Roopa's purposeful deception more interesting than the film's reviews allowed, though her revenge still requires male fighters. | AS25: SOURCE-038 | AT25: Medium
A26: PAIR-025 | B26: FILM-033 | C26: Lagaan | D26: 2001 | E26: Bhuvan | F26: Gracy Singh | G26: Gauri | H26: Female lead | I26: Yes | J26: Love triangle | K26: Fellow villagers; she is the village medic's daughter | L26: They live in the same village. | M26: Bhuvan | N26: Village courtship running alongside the cricket preparations. | O26: Mutual, understated affection | P26: None documented between them. | Q26: 2 | R26: No meaningful disagreement is recorded; rivalry comes from outside the couple. | S26: 4 | T26: Other | U26: Lakha covets Gauri, and his jealousy feeds his betrayal of the team; Elizabeth's feelings for Bhuvan form a second, unspoken rivalry. | V26: 4 | W26: Bhuvan is a leader first; the romance is a secondary thread in a sports epic. | X26: 3 | Y26: 8 | Z26: 7 | AA26: 3 | AC26: Not scored: no fetched source evaluates the pairing. | AD26: Unclear | AE26: No | AF26: Partial | AG26: No | AH26: No | AI26: No | AJ26: Partial | AK26: Not significant; Bhuvan's arc is driven by the wager. | AL26: Not documented. | AM26: They marry after the cricket victory, blessed by the Raja. | AN26: Yes | AO26: Happy | AQ26: A secondary, conflict-light village romance whose main narrative use is to motivate Lakha's betrayal. Gauri has little independent agency in the documented plot, which is typical of the film's male-centred epic structure. | AR26: Framed as a traditional romance within a celebrated epic. A modern reading notes that Gauri is defined almost entirely by her love for Bhuvan. | AS26: SOURCE-039 | AT26: Medium
A27: PAIR-026 | B27: FILM-033 | C27: Lagaan | D27: 2001 | E27: Bhuvan | F27: Rachel Shelley | G27: Elizabeth Russell | H27: Supporting lead | I27: Partial | J27: Unrequited love | K27: The British captain's sister, newly arrived from England | L27: Elizabeth encounters the villagers after her brother's wager and chooses to help them. | M27: Elizabeth | N27: She secretly coaches the team in cricket; her infatuation with Bhuvan stays unspoken. | O27: One-sided admiration across the colonial divide | P27: None between them; her love is simply not returned. | Q27: 1 | R27: No conflict; the relationship is platonic on his side. | S27: 7 | T27: War or politics; Class; Existing relationship | U27: Colonial hierarchy, her brother's authority and Bhuvan's love for Gauri make any romance impossible. | V27: 1 | W27: Bhuvan shows no romantic interest in Elizabeth. | X27: 3 | Y27: 8 | Z27: 1 | AA27: 8 | AC27: Not scored: no fetched source evaluates the pairing. | AD27: Unclear | AE27: No | AF27: No | AG27: Partial | AH27: Yes | AI27: Yes | AJ27: Yes | AK27: Not applicable; Bhuvan's arc is unaffected. | AL27: Elizabeth crosses colonial lines to help the villagers and leaves India carrying an unrequited love. | AM27: She sees Bhuvan and Gauri together, returns to England and never marries. | AN27: No | AO27: Unresolved | AQ27: A meaningful romantic thread that exists entirely on the woman's side. Elizabeth is the most self-directed woman in Lagaan: she defies her brother and her community to coach the villagers. The pairing shows why mutuality and lover-boy scores must be kept separate from female agency. | AR27: Framed as a poignant cross-cultural subplot. A modern reading sees a sympathetic coloniser figure whose unreturned love flatters the hero while giving her a rare independent moral choice. | AS27: SOURCE-039 | AT27: Medium
A28: PAIR-027 | B28: FILM-034 | C28: Dil Chahta Hai | D28: 2001 | E28: Akash Malhotra | F28: Preity Zinta | G28: Shalini | H28: Female lead of one of three storylines | I28: Yes | J28: Friendship to love | K28: Acquaintances; she is engaged to his college batchmate Rohit | L28: They spend time together in Sydney, where Akash is working and Shalini is living with her uncle. | M28: Akash | N28: Sightseeing and companionship in Sydney that deepens into unspoken feeling, followed by a late declaration. | O28: A cynic disarmed by sincerity; she is drawn to him but bound by duty | P28: Her commitment to Rohit and her family's arrangements against his belated recognition of love. | Q28: 3 | R28: Hesitation and unspoken feelings rather than argument; the tension is timing and loyalty, not incompatibility. | S28: 6 | T28: Existing relationship; Family; Distance | U28: Her engagement to Rohit, her uncle Mahesh's wedding arrangements and her return to India separate them. | V28: 7 | W28: Akash's arc becomes a romantic awakening, but he is one of three ensemble leads and much of his screen persona is comic detachment. | X28: 6 | Y28: 8 | Z28: 7 | AA28: 5 | AB28: 7 | AC28: Interpretive: the understated Sydney scenes rely on ease rather than melodrama; the fetched source praises the film's performances overall. | AD28: Yes | AE28: Partial | AF28: Unclear | AG28: No | AH28: Yes | AI28: Partial | AJ28: No | AK28: Loving Shalini forces Akash to abandon ironic detachment and admit vulnerability. | AL28: She moves from dutiful acceptance of an arranged future to choosing her own partner. | AM28: Shalini leaves her wedding to Rohit to be with Akash. | AN28: Partial | AO28: Happy | AQ28: Dil Chahta Hai modernises the lover-boy role: the romance is conversational and restrained, with no family villainy beyond an existing engagement. The pair's friction is low and mostly about timing, while the external obstacle is structural rather than hostile. It marks the shift from the feuding-family romances of the early 1990s to relationship stories driven by self-knowledge. | AR28: Received as a fresh, realistic portrait of urban relationships. A modern reading finds the relationship respectful; the runaway-bride resolution is conventional, and Shalini's agency arrives mainly in the final decision. | AS28: SOURCE-040 | AT28: Medium
A29: PAIR-028 | B29: FILM-035 | C29: Mangal Pandey: The Rising | D29: 2005 | E29: Mangal Pandey | F29: Rani Mukerji | G29: Heera | H29: Female lead with limited screen time | I29: Yes | J29: Tragic lovers | K29: Strangers; she is a courtesan sold to a brothel | L29: Pandey stops Captain Hewson from raping Heera at the brothel run by Lal Bibi, and is beaten for it. | M29: Mutual | N29: Love grows from his act of protection; she later passes him intelligence gathered from Hewson. | O29: Tender, loyal and fatalistic | P29: None documented between the lovers. | Q29: 2 | R29: No interpersonal conflict is recorded; the difficulty of her circumstances is external. | S29: 9 | T29: War or politics; Class | U29: Colonial power, her bondage in the brothel and Pandey's court-martial and execution. | V29: 3 | W29: The romance softens a rebel-martyr role whose identity is organised around faith, dignity and revolt. | X29: 3 | Y29: 7 | Z29: 7 | AA29: 6 | AC29: Not scored: reviews in the fetched source do not assess the pairing. | AD29: Unclear | AE29: No | AF29: No | AG29: Partial | AH29: Yes | AI29: Yes | AJ29: Partial | AK29: Not central to his arc, though protecting Heera is an early act of defiance toward a British officer. | AL29: A bonded courtesan acts for the rebellion and claims marriage on her own terms. | AM29: On the night before his execution, Heera visits Pandey's cell and has him apply sindoor, marking their marriage. | AN29: Partial | AO29: Tragic | AQ29: A secondary romance that mirrors the political story: protection against colonial violence becomes loyalty and an act of resistance. Heera's spying on Hewson for Pandey gives her a purpose of her own. The cell marriage is a gesture of dignity rather than a future, so the ending is tragic and the long-term union partial. | AR29: Its depiction of Pandey visiting a brothel drew political protests and ban demands. A modern reading sees an attempt to give a marginalised woman a place in a nationalist story, though her plotline is compressed and she is defined through him. | AS29: SOURCE-041 | AT29: Medium
A30: PAIR-029 | B30: FILM-037 | C30: Fanaa | D30: 2006 | E30: Rehan Qadri | F30: Kajol | G30: Zooni Ali Beg | H30: Female lead | I30: Yes | J30: Tragic lovers | K30: A tourist and her tour guide | L30: Rehan is the guide for Zooni and her friends on her first visit to Delhi. | M30: Rehan | N30: Flirtatious seduction and poetry over a few days in Delhi, ending in a night together before her departure. | O30: Intense romantic idealism shadowed by concealment | P30: His secret life as a militant, his faked death, his killing of her father and his threat to her when she tries to stop him. | Q30: 9 | R30: The relationship is founded on deception and ends with him drawing a gun on her and her shooting him. | S30: 7 | T30: War or politics; Crime | U30: The separatist conflict, the IKF's demands and the army's hunt for Rehan. | V30: 7 | W30: The first half is a full romantic-hero courtship with poetry and songs, but the role turns into an antagonist torn between love and the cause. | X30: 9 | Y30: 2 | Z30: 6 | AA30: 8 | AB30: 8 | AC30: Rediff's Sukanya Verma singled out the leads' 'dynamic equation', and the casting was treated as the film's main draw; Raja Sen argued the casting could not rescue the script. | AD30: Yes | AE30: Yes | AF30: No | AG30: Yes | AH30: Yes | AI30: Yes | AJ30: No | AK30: Love for Zooni and their son makes Rehan waver, but he cannot abandon the cause. | AL30: A blind, sheltered romantic regains her sight and becomes the woman who kills the man she loves to protect others. | AM30: Zooni shoots Rehan as he tries to deliver the nuclear trigger, and he dies in her arms. | AN30: Partial | AO30: Tragic | AP30: Chand Sifarish; Mere Haath Mein; Chanda Chamke | AQ30: Fanaa is the most extreme case of pair friction coexisting with a high lover-boy score. The courtship is designed to make Rehan irresistible, and the second half turns that charm into the threat. Zooni holds the decisive agency: she chooses to kill him. The film's structure romanticises a relationship founded on lies, then punishes it. | AR30: Framed in 2006 as a sweeping love story against terrorism. A modern reading finds the seduction of a blind woman by a man hiding his identity deeply manipulative, and critics at the time already called the plot a melodramatic series of coincidences. | AS30: SOURCE-043 | AT30: Medium
A31: PAIR-030 | B31: FILM-039 | C31: Ghajini | D31: 2008 | E31: Sanjay Singhania | F31: Asin | G31: Kalpana Shetty | H31: Female lead | I31: Yes | J31: Tragic lovers | K31: Strangers linked by a false rumour that she is his girlfriend | L31: Sanjay goes to confront Kalpana over her claim to be his girlfriend, sees her helping disabled schoolgirls and is moved. | M31: Sanjay | N31: He courts her as a struggling model called Sachin; she sells her car to pay for his invented mother's treatment; he proposes on New Year's Eve. | O31: Warm, playful and generous on both sides | P31: Mutual pretence: she poses as his girlfriend, and he hides that he is the tycoon. | Q31: 2 | R31: The deceptions are comic and loving rather than damaging; no quarrel is documented. | S31: 10 | T31: Villain; Crime | U31: The trafficker Ghajini murders Kalpana in front of Sanjay after she rescues girls from his ring. | V31: 8 | W31: The courtship is a full romantic-hero arc, and his revenge is driven entirely by grief for her. | X31: 8 | Y31: 8 | Z31: 8 | AA31: 7 | AC31: Not scored: reviews split on Asin's performance (praised in some outlets, criticised by Raja Sen). | AD31: Yes | AE31: No | AF31: No | AG31: Yes | AH31: Yes | AI31: Yes | AJ31: No | AK31: A privileged tycoon learns humility courting her as an ordinary man; her murder turns him into an avenger. | AL31: A small-time model becomes the person who rescues trafficked girls and confronts a crime lord. | AM31: Kalpana accepts his proposal but is murdered by Ghajini before learning who he is; Sanjay avenges her and later works at an orphanage named after her. | AN31: No | AO31: Tragic | AP31: Guzarish; Behka; Kaise Mujhe | AQ31: Ghajini puts a healthy, generous romance inside a revenge thriller: friction is almost nil, and the tragedy comes entirely from outside. Kalpana is the most active heroine of his action films; her moral courage causes her death. The relationship's goodness is what gives the brutal second half its emotional charge. | AR31: Received as a crowd-pleasing romance-revenge hybrid; some reviewers objected to its violence. A modern reading notes that the heroine's courage is punished to motivate the hero. | AS31: SOURCE-045 | AT31: Medium
A32: PAIR-031 | B32: FILM-041 | C32: 3 Idiots | D32: 2009 | E32: Ranchhoddas "Rancho" Shamaldas Chanchad | F32: Kareena Kapoor | G32: Pia Sahastrabuddhe | H32: Female lead | I32: Yes | J32: United couple versus external world | K32: Strangers; she is the college director's daughter | L32: At a wedding hosted by her father, Virus. | M32: Rancho | N32: Teasing friendship that grows into love under her father's hostility; a long separation after graduation. | O32: Playful, mutually respectful | P32: None documented between them; his disappearance separates them. | Q32: 2 | R32: No interpersonal conflict is recorded; the ten-year absence is imposed by his secret identity. | S32: 6 | T32: Family; Existing relationship; Distance | U32: Her father's hostility to Rancho, her engagement to the materialistic Suhas, and years apart. | V32: 5 | W32: A significant romance, but Rancho's defining function is rebel student and loyal friend. | X32: 4 | Y32: 8 | Z32: 7 | AA32: 6 | AC32: Not scored: no fetched source evaluates the pairing. | AD32: Yes | AE32: No | AF32: No | AG32: Partial | AH32: Yes | AI32: Partial | AJ32: Yes | AK32: Not central; Rancho's convictions are fixed from the start. | AL32: Pia moves from obedience to her father and a status-driven engagement toward choosing Rancho. | AM32: Farhan and Raju bring Pia from her wedding in Manali to Ladakh, where she reunites with Rancho. | AN32: Unclear | AO32: Happy | AP32: Zoobi Doobi | AQ32: A secondary romance that reinforces the film's theme: Pia's movement away from her engagement to Suhas and toward Rancho aligns her with the film's argument against conventional success. Friction is minimal and the obstacles are her father and time. Rancho is a hero of friendship and ideas first, which caps the lover-boy score. | AR32: Framed as a charming subplot in a crowd-pleasing campus film. A modern reading finds the relationship respectful, though Pia's wedding escape is arranged largely by the male friends. | AS32: SOURCE-047 | AT32: Medium
A33: PAIR-032 | B33: FILM-042 | C33: Dhobi Ghat | D33: 2011 | E33: Arun | F33: Monica Dogra | G33: Shai Edulji | H33: Ensemble lead | I33: Yes | J33: Unrequited love | K33: Strangers who meet at an art exhibition | L33: At Arun's exhibition; he invites her back to his flat. | M33: Arun for the night together; Shai for any continuation | N33: A one-night stand followed by his coldness and her later attempts to find him. | O33: Her interest against his emotional withdrawal | P33: Arun tells her the next morning that he does not want a relationship, and she storms out. | Q33: 5 | R33: Hurt and rejection sour the connection, softened by his later apology. | S33: 1 | T33: Other | U33: Only chance and Munna's reluctance to share Arun's new address stand in the way. | V33: 1 | W33: Arun is emotionally unavailable and shows no sustained romantic pursuit. | X33: 3 | Y33: 4 | Z33: 3 | AA33: 8 | AC33: Not scored: no fetched source evaluates the pairing. | AD33: Unclear | AE33: Partial | AF33: No | AG33: No | AH33: Yes | AI33: No | AJ33: No | AK33: Minimal; Arun's emotional change comes from Yasmin's tapes rather than from Shai. | AL33: Shai explores Mumbai on her own terms, befriending Munna and seeking Arun out. | AM33: Munna finally gives Shai Arun's new address; whether they reconnect is left open. | AN33: No | AO33: Unresolved | AQ33: The least romantic relationship in the Romances sheet that still merits a row: a sexual encounter and one-sided interest in a film about loneliness. Arun's deepest emotional bond is with Yasmin, the dead former tenant he knows only through her video diaries, which is recorded in Films rather than here because they never meet. Shai's agency is high: she chooses whom to pursue across class lines. | AR33: Received as a poetic art-house portrait of Mumbai. A modern reading sees an honest depiction of emotional unavailability, and class in Munna's unspoken love for Shai. | AS33: SOURCE-048 | AT33: Medium
A34: PAIR-033 | B34: FILM-044 | C34: Talaash: The Answer Lies Within | D34: 2012 | E34: Inspector Surjan Singh Shekhawat | F34: Rani Mukerji | G34: Roshni Shekhawat | H34: Female lead | I34: Yes | J34: Marriage under strain | K34: Married couple grieving the drowning of their son | M34: Not applicable | N34: Not applicable; an established marriage frozen by grief. | O34: Silent blame and emotional distance | P34: Grief and guilt over Karan's death; Surjan's anger at Roshni's consultations with a psychic. | Q34: 6 | R34: Sustained emotional estrangement and resentment over how each copes with grief. | S34: 5 | T34: Fate | U34: Their son's accidental drowning is the external blow behind the strain. | V34: 1 | W34: Surjan is a grieving, emotionally closed husband, not a romantic hero. | X34: 4 | Y34: 5 | Z34: 5 | AA34: 6 | AC34: Not scored: Rani Mukerji was nominated for Filmfare Best Supporting Actress, but the sources do not assess the pairing. | AD34: No | AE34: Yes | AF34: No | AG34: No | AH34: Partial | AI34: No | AJ34: No | AK34: Surjan moves from denial and guilt to acceptance, allowing reconciliation. | AL34: Roshni seeks her own path through grief and is vindicated when the psychic delivers their son's message. | AM34: After receiving a letter from their son via the psychic, Surjan reconciles with Roshni. | AN34: Yes | AO34: Happy | AQ34: A mature marriage story embedded in a noir thriller. The friction is entirely emotional and caused by bereavement. Surjan's night-time interactions with Rosie are investigative and ultimately supernatural, not romantic, so they have no row. Roshni's belief, which he mocks, is ultimately proven right. | AR34: Received as a well-acted psychological drama. A modern reading appreciates its restrained portrait of grief in a marriage, though the wife's arc exists mainly to mirror the husband's healing. | AS34: SOURCE-050 | AT34: Medium
A35: PAIR-034 | B35: FILM-046 | C35: Dhoom 3 | D35: 2013 | E35: Samar Khan | F35: Katrina Kaif | G35: Aaliya Hussain | H35: Female lead | I35: Yes | J35: Tragic lovers | K35: Circus colleagues; she is hired as an acrobat | L35: Sahir hires Aaliya for the Great Indian Circus; the hidden twin Samar befriends her on his weekly outings. | M35: Samar | N35: Gentle friendship during Samar's rare time outdoors, encouraged by the detective Jai to expose the twins. | O35: Innocent and tender, under surveillance | P35: She does not know that Samar is a hidden twin involved in the robberies. | Q35: 3 | R35: Concealment rather than conflict; no quarrel is documented. | S35: 9 | T35: Crime; Other | U35: The heists, the police manhunt and Jai's use of the romance to break the twins' secret end in Samar's death. | V35: 5 | W35: Samar's romance is the gentlest thread in the role, but the twins' identity is revenge and spectacle. | X35: 4 | Y35: 6 | Z35: 6 | AA35: 4 | AC35: Not scored: the fetched source records only a satirical 'Worst Couple' nomination at the Ghanta Awards, which is not treated as evidence. | AD35: Unclear | AE35: No | AF35: No | AG35: Yes | AH35: Yes | AI35: Partial | AJ35: No | AK35: Love gives Samar a life beyond his brother's revenge, and makes him hesitate at the dam. | AL35: Aaliya takes over the circus after the twins' deaths and performs in Samar's memory. | AM35: At the dam Aaliya begs Samar to stop; the brothers fall to their deaths. | AN35: No | AO35: Tragic | AQ35: The romance belongs to Samar, the hidden, vulnerable twin, and becomes the lever the police use to expose the brothers. Opposition is extreme because the love story sits inside a crime plot. Aaliya has little knowledge or choice until the end, though she inherits the circus. | AR35: Framed as the emotional hook of a spectacle film. A modern reading notes the detective's deliberate use of a vulnerable man's romance as bait. | AS35: SOURCE-052 | AT35: Medium
A36: PAIR-035 | B36: FILM-047 | C36: PK | D36: 2014 | E36: PK | F36: Anushka Sharma | G36: Jagat Janani "Jaggu" Sahni | H36: Female lead | I36: Yes | J36: Unrequited love | K36: A television journalist and the stranger she meets handing out 'missing God' pamphlets | L36: In Delhi, Jaggu notices PK distributing pamphlets about a missing God and secures his release after an arrest. | M36: PK develops feelings; Jaggu's affection is friendship | N36: No courtship: PK silently falls in love while helping her expose Tapasvi. | O36: Devoted, unspoken love on his side; warm friendship on hers | P36: None; he hides his feelings out of respect for her love for Sarfaraz. | Q36: 1 | R36: No conflict between them. | S36: 6 | T36: Existing relationship; Distance | U36: Jaggu loves Sarfaraz, and PK must return to his planet. | V36: 4 | W36: The love is devoted and self-sacrificing, but PK's main function is religious satire. | X36: 4 | Y36: 8 | Z36: 2 | AA36: 7 | AC36: Not scored: no fetched source evaluates the pairing. | AD36: Yes | AE36: No | AF36: No | AG36: No | AH36: Yes | AI36: Yes | AJ36: Yes | AK36: PK learns love and lying from Jaggu, and chooses to hide his feelings rather than disrupt her happiness. | AL36: Jaggu moves from heartbreak to reuniting with Sarfaraz and writing a bestseller about PK. | AM36: PK reunites Jaggu with Sarfaraz and departs; she discovers his recordings of her voice and lets him go. | AN36: No | AO36: Unresolved | AQ36: The film's one romance belongs to Jaggu and Sarfaraz, whose separation Tapasvi engineers; PK's love is the secret emotional layer. It is a self-effacing, older version of Aamir Khan's romantic devotion: sacrifice without pursuit. Jaggu drives the investigation, giving her strong agency. | AR36: Framed as a bittersweet grace note. A modern reading finds the unrequited love gentle and respectful of the woman's choice, unusual in a genre that often rewards persistence. | AS36: SOURCE-053 | AT36: Medium
A37: PAIR-036 | B37: FILM-053 | C37: Laal Singh Chaddha | D37: 2022 | E37: Laal Singh Chaddha | F37: Kareena Kapoor | G37: Rupa D'Souza | H37: Female lead | I37: Yes | J37: Unrequited love | K37: Childhood friends at a missionary school | L37: Rupa becomes Laal's only friend at school. | M37: Laal | N37: Lifelong devotion on his side, interrupted by her repeated departures in pursuit of fame. | O37: His constancy against her restlessness and self-destruction | P37: Rupa repeatedly leaves him, choosing glamour and dangerous relationships. | Q37: 6 | R37: Repeated rejections and abandonment over decades, without hostility on his part. | S37: 7 | T37: Crime; Illness; Other | U37: Her involvement with a gangster leads to six months in prison; terminal illness ends their marriage. | V37: 9 | W37: Laal's love for Rupa is the constant of his life and drives his cross-country run. | X37: 8 | Y37: 5 | Z37: 3 | AA37: 7 | AC37: Not scored: Kareena Kapoor was nominated for Filmfare Best Actress, but the sources do not assess the pairing. | AD37: Unclear | AE37: Partial | AF37: Unclear | AG37: Partial | AH37: Yes | AI37: Yes | AJ37: No | AK37: His steady love, once refused, becomes the home Rupa returns to. | AL37: From chasing a glamorous life to returning, ill, to the man who always loved her. | AM37: Rupa returns with their son Aman; Laal marries her despite her terminal illness and raises Aman after her death. | AN37: Yes | AO37: Tragic | AP37: Tere Hawaale; Phir Na Aisi Raat Aayegi; Main Ki Karaan | AQ37: A late-career variation on the devoted lover: no courtship, only constancy across decades. The friction comes from the woman's choices rather than conflict, and her agency is high but self-destructive. It pairs the highest lover-boy score of his later films with low mutuality. | AR37: Framed, as in Forrest Gump, as a tale of pure love. A modern reading questions a narrative that frames the ambitious woman as lost until she returns home. | AS37: SOURCE-059 | AT37: Medium
A38: PAIR-037 | B38: FILM-055 | C38: Sitaare Zameen Par | D38: 2025 | E38: Gulshan Arora | F38: Genelia Deshmukh | G38: Sunita Arora | H38: Supporting | I38: Yes | J38: Marriage under strain | K38: Married couple | M38: Not applicable | N38: Not applicable; an established marriage. | O38: Strained by his reluctance to start a family | P38: Gulshan's resistance to having children. | Q38: 5 | R38: A sustained disagreement about family plans; separation is not stated. | S38: 1 | T38: Other | U38: No outside obstacle; the strain comes from Gulshan's immaturity. | V38: 2 | W38: A husband subplot in a coaching drama. | X38: 3 | Y38: 6 | Z38: 5 | AA38: 5 | AC38: Not scored: no fetched source evaluates the pairing. | AD38: Unclear | AE38: Partial | AF38: No | AG38: No | AH38: Unclear | AI38: No | AJ38: Unclear | AK38: His growth through coaching makes him ready to embrace fatherhood. | AL38: Not documented. | AM38: The film closes with Gulshan joyfully accepting Sunita's pregnancy. | AN38: Yes | AO38: Happy | AQ38: A moderate-prominence marriage subplot that externalises the hero's inner change: learning from his players makes him ready for a family. Friction is internal and resolved by his maturity, echoing the older-husband roles of his later career. | AR38: Framed as a sweet subplot. A modern reading notes that the wife's wish for a child is resolved through the husband's growth rather than her own arc. | AS38: SOURCE-061 | AT38: Low

Sheet Collaborators
A1: Person ID | B1: Name | C1: Profession or Function | D1: Birth Year | E1: Death Year | F1: Years Active | G1: Industry or Primary Language | H1: Career Background | I1: Debut or Early Breakthrough | J1: Major Works | K1: Recurring Genres or Themes | L1: Creative Style | M1: Major Awards | N1: Historical Importance | O1: Relationship with Selected Actor | P1: Number of Collaborations | Q1: Collaboration Film IDs | R1: Most Important Collaboration | S1: Extended Biography | T1: Source IDs | U1: Confidence Grade
A2: PERSON-001 | B2: Aamir Khan Productions | C2: Production banner | F2: Founded 1999 | G2: Hindi | H2: Founded by Aamir Khan; Kiran Rao, who met him as an assistant director on Lagaan, became a key producer. | I2: Lagaan (2001). | J2: Lagaan (2001); Taare Zameen Par (2007); Jaane Tu... Ya Jaane Na (2008); Peepli Live (2010); Dhobi Ghat (2011); Delhi Belly (2011); Talaash (2012); Dangal (2016); Secret Superstar (2017); Laal Singh Chaddha (2022); Laapataa Ladies (2024); Sitaare Zameen Par (2025); Happy Patel: Khatarnak Jasoos (2026); Lahore 1947 / Batwara 1947 (2026) | K2: Socially engaged mainstream films, new directors and occasional art-house releases | M2: Academy Award nomination (Lagaan); Filmfare Best Film (Lagaan; Taare Zameen Par; Dangal); National Film Awards including Best Popular Film (Lagaan) and Best Film on Family Welfare (Taare Zameen Par) | N2: Credited with opening Chinese markets to Indian films through the success of Dangal and Secret Superstar. | O2: His own company, which produced or co-produced ten of his acting films, including his directorial debut. | P2: 11 | Q2: FILM-033; FILM-038; FILM-042; FILM-043; FILM-044; FILM-045; FILM-049; FILM-050; FILM-053; FILM-055; FILM-057 | R2: Lagaan (2001) | S2: Aamir Khan Productions was founded by Aamir Khan in 1999 and launched with Lagaan (2001), a then-unprecedentedly expensive cricket epic nominated for the Academy Award for Best Foreign Language Film. The company became the vehicle for Aamir's selective, message-led career. He directed Taare Zameen Par (2007) for it, and it backed first-time or early-career directors including Abbas Tyrewala (Jaane Tu... Ya Jaane Na), Kiran Rao (Dhobi Ghat, Laapataa Ladies), Abhinay Deo (Delhi Belly) and Advait Chandan (Secret Superstar, Laal Singh Chaddha). Many productions were made with partners, among them PVR, UTV, Excel Entertainment, Disney, Zee Studios, Paramount and Viacom18, and Jio Studios. Dangal (2016), co-produced with Disney, became the highest-grossing Indian film and, with Secret Superstar (2017), is credited with opening China to Indian cinema. The banner's recent run is mixed: the costly Laal Singh Chaddha (2022) was a box-office disaster, while Sitaare Zameen Par (2025) was a hit and Lahore 1947, released in 2026 as Batwara 1947, was not. Of its films, ten feature Aamir Khan on screen, from lead roles to a cameo in Happy Patel: Khatarnak Jasoos. | T2: SOURCE-099; SOURCE-039; SOURCE-044; SOURCE-055; SOURCE-056; SOURCE-059; SOURCE-061; SOURCE-064 | U2: Medium
A3: PERSON-002 | B3: A. R. Rahman | C3: Music director (songs and background score) | D3: 1967 | F3: 1992–present | G3: Tamil; Hindi; international | H3: Born Arunachalam Shekhar Dileep Kumar, son of Malayalam film composer R. K. Shekhar; composed advertising jingles from 1987. | I3: Roja (1992); Hindi breakthrough with Rangeela (1995). | J3: Roja (1992); Bombay (1995); Rangeela (1995); Dil Se.. (1998); Taal (1999); Lagaan (2001); Swades (2004); Rang De Basanti (2006); Jodhaa Akbar (2008); Slumdog Millionaire (2008); Rockstar (2011) | K3: Epic, patriotic and romantic scores | L3: Synthesises Carnatic, Hindustani, Western classical and qawwali traditions with electronic production; introduced 7.1 surround sound to South Indian films. | M3: Two Academy Awards and two Grammy Awards (Slumdog Millionaire); seven National Film Awards; Padma Shri (2000); Padma Bhushan (2010) | N3: The most internationally celebrated Indian film composer, who transformed the sound of Hindi and Tamil film music from the 1990s. | O3: Scored six Aamir Khan films, including three of his most acclaimed. | P3: 6 | Q3: FILM-024; FILM-031; FILM-033; FILM-035; FILM-036; FILM-039 | R3: Lagaan (2001) | S3: A. R. Rahman was born Arunachalam Shekhar Dileep Kumar in 1967, the son of Malayalam film composer R. K. Shekhar, and made his name composing advertising jingles before Mani Ratnam's Roja (1992) launched his film career. Bombay (1995) sold 15 million soundtrack copies, and Ram Gopal Varma's Rangeela (1995) was his Hindi breakthrough and his first film with Aamir Khan; it won him the Filmfare Best Music Director award. His music blends Carnatic, Hindustani, Western classical and qawwali influences with state-of-the-art production. The partnership with Aamir continued through Deepa Mehta's Earth, then Lagaan (2001), whose songs won the Filmfare and National Film Awards for music and whose lyricist Javed Akhtar also won both. Rahman scored Mangal Pandey: The Rising (2005) and Rang De Basanti (2006), winning another Filmfare award for the latter, and Ghajini (2008), the first Hindi film to cross ₹100 crore nett in India, whose soundtrack was the year's best-selling Bollywood album. His international career peaked with Slumdog Millionaire, which brought two Academy Awards and two Grammys. He has seven National Film Awards and received the Padma Shri in 2000 and the Padma Bhushan in 2010. Across six films he supplied the sound of Aamir Khan's move from romantic hero to epic and political roles. | T3: SOURCE-094; SOURCE-030; SOURCE-035; SOURCE-039; SOURCE-041; SOURCE-042; SOURCE-045; SOURCE-071 | U3: Medium
A4: PERSON-003 | B4: Anand–Milind | C4: Music directors (song composers) | F4: 1983–present | G4: Hindi | H4: Brothers Anand and Milind Srivastava, sons of the composer Chitragupt. | I4: Ab Ayega Mazaa (1984); breakthrough with Qayamat Se Qayamat Tak (1988). | J4: Ab Ayega Mazaa (1984); Jalwa (1987); Qayamat Se Qayamat Tak (1988); Baaghi: A Rebel for Love (1990); Dil (1990); Tum Mere Ho (1990); Deewana Mujh Sa Nahin (1990); Jawani Zindabad (1990); Daulat Ki Jung (1992) | K4: Youthful romantic soundtracks for the late-1980s and early-1990s romance boom | L4: Melodic, song-led romantic scores, frequently with lyricists Majrooh Sultanpuri and Sameer. | M4: Filmfare Best Music Director (Qayamat Se Qayamat Tak, 1989); Lata Mangeshkar Award, Government of Madhya Pradesh (2020) | N4: Composed for more than 200 Hindi films; their Qayamat Se Qayamat Tak songs defined the sound of the romantic revival. | O4: The most frequent composers of Aamir Khan's early career, scoring six of his films between 1988 and 1992. | P4: 6 | Q4: FILM-004; FILM-008; FILM-009; FILM-010; FILM-011; FILM-014 | R4: Qayamat Se Qayamat Tak (1988) | S4: Anand and Milind Srivastava are brothers and the sons of the veteran composer Chitragupt. Working as Anand–Milind from 1983, they debuted with Ab Ayega Mazaa (1984) and scored Jalwa (1987) before their breakthrough with Qayamat Se Qayamat Tak (1988). Its songs, including 'Papa Kehte Hain' and 'Ae Mere Humsafar', won them the Filmfare Best Music Director award and helped make the film a phenomenon. The success tied them closely to the romantic cycle it started and to Aamir Khan's early stardom. Within two years they had scored Tum Mere Ho, Indra Kumar's Dil (a Filmfare nomination and the year's highest-grossing film), Deewana Mujh Sa Nahin and Jawani Zindabad, followed by Daulat Ki Jung (1992). Their collaborations with Majrooh Sultanpuri (QSQT, Tum Mere Ho, Daulat Ki Jung) and Sameer (Dil, Deewana Mujh Sa Nahin) supplied the courtship songs central to these films' appeal. Their long career includes more than 200 Hindi films, and in 2020 the Madhya Pradesh government gave them the Lata Mangeshkar Award. The fetched biography gives no birth years or detailed account of their style, so the stylistic description here draws on the film records. | T4: SOURCE-080; SOURCE-007; SOURCE-012; SOURCE-014; SOURCE-015; SOURCE-016; SOURCE-020 | U4: Medium
A5: PERSON-004 | B5: Bappi Lahiri | C5: Music director (song composer) | D5: 1952 | E5: 2022 | F5: 1972–2022 | G5: Hindi; Bengali; Telugu; other Indian languages | H5: Born Alokesh Aparesh Lahiri in Siliguri to classical musicians; maternal uncle was Kishore Kumar. | I5: Bengali film Daadu (1972); recognition in Hindi with Tahir Hussain's Zakhmee (1975) and Chalte Chalte (1976). | J5: Zakhmee (1975); Chalte Chalte (1976); Disco Dancer (1982); Namak Halaal (1982); Himmatwala (1983); Sharaabi (1984); Love Love Love (1989); Awwal Number (1990); Afsana Pyar Ka (1991) | K5: Dance-floor pop and disco for mass entertainers | L5: Pioneered synthesised disco in Indian film music, fusing Indian melody with international pop rhythms. | M5: Filmfare Best Music Director (Sharaabi, 1985); Filmfare Lifetime Achievement Award (2018); Guinness World Record (1986) for recording more than 180 songs in one year | N5: Transformed Hindi film music in the 1980s with electronic disco and a distinctive public image. | O5: Scored five Aamir Khan films between 1989 and 1995, mostly lower-profile releases. | P5: 5 | Q5: FILM-006; FILM-007; FILM-012; FILM-016; FILM-023 | R5: Afsana Pyar Ka (1991) | S5: Bappi Lahiri was born Alokesh Aparesh Lahiri in Siliguri in 1952 to parents who were classical musicians; the singer Kishore Kumar was his maternal uncle. He scored his first film, the Bengali Daadu, in 1972 and gained recognition in Hindi cinema with Zakhmee (1975), produced by Tahir Hussain, before national success with Chalte Chalte (1976). In the 1980s he became the dominant sound of mass entertainers, introducing synthesised disco with Disco Dancer, Namak Halaal, Himmatwala and Sharaabi, which won him the Filmfare Best Music Director award. He set a Guinness record in 1986 for recording more than 180 songs in a year and composed across Hindi, Bengali, Telugu, Kannada, Tamil and Marathi cinema. His work was also the subject of an international copyright case after portions of 'Thoda Resham Lagta Hai' appeared in a 2002 song by the American singer Truth Hurts. By the time he worked with Aamir Khan, the disco wave had peaked: he scored Love Love Love (1989), Dev Anand's Awwal Number (1990), Afsana Pyar Ka (1991), whose 'Tip Tip Tip Tip Baarish Shuru Ho Gayi' was a popular song, Isi Ka Naam Zindagi (1992) and Aatank Hi Aatank (1995). None became a major Aamir Khan hit. He received the Filmfare Lifetime Achievement Award in 2018 and died in Mumbai in 2022. | T5: SOURCE-082; SOURCE-009; SOURCE-010; SOURCE-017; SOURCE-022; SOURCE-029 | U5: Medium
A6: PERSON-005 | B6: Excel Entertainment | C6: Production banner | F6: Founded 9 August 1999 | G6: Hindi; streaming series | H6: Founded by Farhan Akhtar and Ritesh Sidhwani. | I6: Dil Chahta Hai (2001). | J6: Dil Chahta Hai (2001); Lakshya (2004); Don (2006); Rock On!! (2008); Luck by Chance (2009); Zindagi Na Milegi Dobara (2011); Talaash (2012); Bombay Talkies (2013); Dil Dhadakne Do (2015); Gully Boy (2019); Mirzapur; Made in Heaven | K6: Contemporary urban stories and unusual characters | M6: National Film Awards for Dil Chahta Hai and Rock On!!; Gully Boy selected as India's Academy Award entry | N6: Pioneered contemporary Hindi cinema and moved early into original streaming series. | O6: Produced two films starring Aamir Khan, and three in which he appears as himself or as a voice. | P6: 5 | Q6: FILM-034; FILM-040; FILM-044; FILM-045; FILM-048 | R6: Dil Chahta Hai (2001) | S6: Excel Entertainment was founded on 9 August 1999 by Farhan Akhtar and producer Ritesh Sidhwani. Its first film, Dil Chahta Hai (2001), starring Aamir Khan, Saif Ali Khan and Akshaye Khanna, won the National Film Award for Best Feature Film in Hindi, and the company became associated with contemporary urban storytelling through Lakshya, Don, Rock On!!, Zindagi Na Milegi Dobara and Gully Boy, India's Academy Award entry. It later moved into streaming series with Inside Edge, Mirzapur and Made in Heaven. Aamir Khan's work with the banner covers leading roles in Dil Chahta Hai and in Talaash (2012), co-produced with Aamir Khan Productions; appearances as himself in Luck by Chance (2009) and, among many stars, in a song of the anthology Bombay Talkies (2013); and the narrating voice of the dog Pluto in Dil Dhadakne Do (2015). | T6: SOURCE-101; SOURCE-040; SOURCE-046; SOURCE-050; SOURCE-051; SOURCE-054; SOURCE-071 | U6: Medium
A7: PERSON-006 | B7: Kiran Rao | C7: Director; writer; producer | D7: 1973 | F7: 2001–present | G7: Hindi | H7: Born in Bangalore and raised in Calcutta; studied economics at Sophia College and mass communication at Jamia Millia Islamia; assistant director on Lagaan, Monsoon Wedding and Swades. | I7: Directorial debut Dhobi Ghat (2011); earlier associate producer of Jaane Tu... Ya Jaane Na (2008). | J7: Jaane Tu... Ya Jaane Na (2008, associate producer); Peepli Live (2010); Dhobi Ghat (2011); Delhi Belly (2011); Talaash (2012); Dangal (2016); Secret Superstar (2017); Laal Singh Chaddha (2022); Laapataa Ladies (2024) | K7: Loneliness and class in the city; women's lives and small-town India | L7: Intimate, observational filmmaking as director; producer of mainstream and independent films at Aamir Khan Productions. | M7: Laapataa Ladies selected as India's entry for the 97th Academy Awards; Dhobi Ghat longlisted for a BAFTA | N7: Chairperson of the Mumbai Film Festival (MAMI) from 2015 and co-founder of the Paani Foundation. | O7: Former wife (married December 2005, divorced July 2021); directed him in Dhobi Ghat and co-produced five more of his films. | P7: 5 | Q7: FILM-042; FILM-043; FILM-049; FILM-050; FILM-053 | R7: Dhobi Ghat (2011) | S7: Kiran Rao was born in Bangalore in 1973 and grew up in Calcutta. She studied economics at Sophia College and mass communication at Jamia Millia Islamia's AJK Mass Communication Research Centre before working as an assistant director on Lagaan, where she met Aamir Khan, and on Mira Nair's Monsoon Wedding and Ashutosh Gowariker's Swades. She also appears briefly in Dil Chahta Hai. She married Aamir Khan in December 2005; their son Azad was born in 2011, and they divorced in July 2021 while continuing to work together. At Aamir Khan Productions she was associate producer on Jaane Tu... Ya Jaane Na and producer of Peepli Live, Delhi Belly, Talaash, Dangal, Secret Superstar and Laal Singh Chaddha. Her directorial debut, Dhobi Ghat (2011), which she wrote, follows four Mumbai lives, with Aamir as Arun, a reclusive painter haunted by a former tenant's video diaries. It premiered at the Toronto festival, drew strong reviews and was longlisted for a BAFTA. Her second feature, Laapataa Ladies (2024), was India's entry for the 97th Academy Awards. She has chaired the Mumbai Film Festival since 2015 and co-founded the non-profit Paani Foundation in 2016. | T7: SOURCE-113; SOURCE-048; SOURCE-049; SOURCE-050; SOURCE-055; SOURCE-056; SOURCE-059 | U7: Medium
A8: PERSON-007 | B8: Shankar–Ehsaan–Loy | C8: Music directors (songs and background score) | F8: 1997–present | G8: Hindi | H8: Shankar Mahadevan (vocalist trained in Indian classical music), Ehsaan Noorani (guitarist, Musicians Institute, Los Angeles) and Loy Mendonsa (keyboardist) came together through advertising jingles and Mumbai's non-film music scene. | I8: First film Dus (begun 1997, left incomplete); mainstream entry with Mission Kashmir (2000); breakthrough with Dil Chahta Hai (2001). | J8: Mission Kashmir (2000); Dil Chahta Hai (2001); Kal Ho Naa Ho (2003); Bunty Aur Babli (2005); Don (2006); Taare Zameen Par (2007); Rock On!! (2008); Luck by Chance (2009); Zindagi Na Milegi Dobara (2011); Bhaag Milkha Bhaag (2013); Dil Dhadakne Do (2015); Sitaare Zameen Par (2025) | K8: Contemporary urban soundtracks; emotionally direct songs for coming-of-age and family stories | L8: Fusion of Carnatic and Hindustani vocals with Western rock, jazz and electronic arrangement; Gulzar called it 'a sensible synthesis of popularity and class'. | M8: National Film Award for Best Music Direction (Kal Ho Naa Ho); three Filmfare Best Music Director awards; Padma Shri to Shankar Mahadevan (2019) | N8: Defined the sound of the post-2000 urban Hindi film. | O8: Scored five films featuring Aamir Khan, from Dil Chahta Hai to Sitaare Zameen Par. | P8: 5 | Q8: FILM-034; FILM-038; FILM-040; FILM-048; FILM-055 | R8: Dil Chahta Hai (2001) | S8: Shankar Mahadevan, Ehsaan Noorani and Loy Mendonsa came from Mumbai's rock, blues, jazz and pop scene. Ehsaan and Loy began working together around 1989 composing advertising jingles, and Shankar joined them through composer Ranjit Barot. Their first film, Mukul Anand's Dus, was left incomplete after the director's death; Mission Kashmir (2000) brought them into the mainstream. Their breakthrough was Farhan Akhtar's Dil Chahta Hai (2001), with Aamir Khan, whose songs won them Filmfare's R. D. Burman Award for New Music Talent and became part of the film's cult status. The trio fuse Shankar's Carnatic and Hindustani vocals with Ehsaan's rock guitar and Loy's electronic arrangement, a mix Gulzar called 'a sensible synthesis of popularity and class'. They won the National Film Award for Kal Ho Naa Ho and Filmfare awards for Bunty Aur Babli and 2 States. With Aamir Khan they also scored Taare Zameen Par (2007), whose song 'Maa', sung by Shankar Mahadevan, won National Film Awards for playback and lyrics, as well as Luck by Chance, Dil Dhadakne Do and, nearly two decades after TZP, the songs of Sitaare Zameen Par (2025). Shankar Mahadevan received the Padma Shri in 2019. | T8: SOURCE-102; SOURCE-040; SOURCE-044; SOURCE-046; SOURCE-054; SOURCE-061; SOURCE-070; SOURCE-072 | U8: Medium
A9: PERSON-008 | B9: Aditya Chopra | C9: Producer; Writer (Yash Raj Films) | D9: 1971 | F9: 1988–present | G9: Hindi cinema | H9: Chairman of Yash Raj Films, elder son of Yash and Pamela Chopra, who began as an assistant director to his father at eighteen and is described as the highest-grossing Indian film producer. | I9: Screenplays for Parampara (1993) and Aaina; directorial debut Dilwale Dulhania Le Jayenge (1995). | J9: With Khan: Parampara (1993, writer), Fanaa (2006), Dhoom 3 (2013, also writer), Thugs of Hindostan (2018). Wider work: Dilwale Dulhania Le Jayenge, Mohabbatein, Rab Ne Bana Di Jodi; the YRF Spy Universe. | K9: Romantic melodrama; later large-scale action franchises. | M9: National Film Awards in 1995, 2004, 2007 and 2015. | N9: Widely regarded as the most influential executive in Indian entertainment. | O9: Four films across 25 years. He wrote Parampara, an early Khan flop directed by Yash Chopra; then, as head of YRF, produced Fanaa, a major success with Khan as a Kashmiri militant, and Dhoom 3, which he also co-wrote and which became an all-time blockbuster with Khan in a double role. Thugs of Hindostan, YRF's most expensive film, opened to a record and then failed. | P9: 4 | Q9: FILM-018; FILM-037; FILM-046; FILM-051 | R9: Dhoom 3 (2013) | S9: Aditya Chopra wrote his first screenplays for his father's Parampara (1993) — in which Aamir Khan has a co-lead — and his mother's production Aaina, then directed Dilwale Dulhania Le Jayenge (1995) and took over Yash Raj Films, which he has made the largest Hindi studio. His Aamir Khan films came under YRF: Kunal Kohli's Fanaa (2006), with Khan as a charming tour guide who is secretly a militant, was a major commercial success; Dhoom 3 (2013), which Chopra co-wrote, cast Khan as twin circus performers turned thieves and was one of the highest-grossing Hindi films ever made; and Thugs of Hindostan (2018), a period adventure with Khan and Amitabh Bachchan, opened to a record but was a commercial failure. He is notably publicity-shy despite his influence. | T9: SOURCE-122; SOURCE-024; SOURCE-043; SOURCE-052; SOURCE-057 | U9: Medium
